Workbook

Sheet games
A1: 遊戲名稱 | B1: Logo | C1: Facebook | D1: 官方網站 | E1: App Store | F1: 禮包碼 | G1: GooglePlay | H1: canonical_url | I1: 簡介 | J1: 商品1名稱 | K1: 商品1價格 | L1: 商品2名稱 | M1: 商品2價格 | N1: 商品3名稱 | O1: 商品3價格 | P1: 商品4名稱 | Q1: 商品4價格 | R1: 商品5名稱 | S1: 商品5價格 | T1: 商品6名稱 | U1: 商品6價格 | V1: 商品7名稱 | W1: 商品7價格 | X1: 商品8名稱 | Y1: 商品8價格 | Z1: 商品9名稱 | AA1: 商品9價格 | AB1: 商品10名稱 | AC1: 商品10價格 | AD1: 商品11名稱 | AE1: 商品11價格 | AF1: 商品12名稱 | AG1: 商品12價格 | AH1: 商品13名稱 | AI1: 商品13價格 | AJ1: 商品14名稱 | AK1: 商品14價格 | AL1: 商品15名稱 | AM1: 商品15價格
A2: 巔峰極速 | F2: =IF(A2="","", "https://www.ssbuy.tw/detail_giftcode/dist/giftcodes/" & IF(ISNUMBER(LEFT(A2,1)*1), "game-", "") & A2 & ".html") -> https://www.ssbuy.tw/detail_giftcode/dist/giftcodes/巔峰極速.html | H2: =IF(A2="","", "https://www.ssbuy.tw/detail_giftcode/dist/gamedetail/" & IF(ISNUMBER(LEFT(A2,1)*1), "game-", "") & A2 & ".html") -> https://www.ssbuy.tw/detail_giftcode/dist/gamedetail/巔峰極速.html | I2: 《巔峰極速》是與Codemasters®深度合作, 3A級巔峰品質擬真競速遊戲。 玩家可以自由收集、改裝超過100款正版授權的豪華車輛，馳騁在全世界的街道與專業賽道上，感受極致光影與真實轟鳴聲帶來的沉浸體驗，更擁有豐富的競速玩法，立即加入與其他玩家進行即時競速對決，突破賽車的速度極限！ | J2: 鑽石 60顆 | K2: 30 | L2: 鑽石 300顆 | M2: 137 | N2: 鑽石 680顆 | O2: 260 | P2: 鑽石 980顆 | Q2: 390 | R2: 鑽石 1280顆 | S2: 520 | T2: 鑽石 1980顆 | U2: 780 | V2: 鑽石 3280顆 | W2: 1300 | X2: 鑽石6480顆 | Y2: 2395 | Z2: 月卡 | AA2: 137 | AB2: 高級合約 | AC2: 260 | AD2: 特級合約 | AE2: 520 | AF2: 合約組合禮包 | AG2: 1260 | AH2: 合約組合禮包(折扣) | AI2: 1150
A3: 原神 | F3: =IF(A3="","", "https://www.ssbuy.tw/detail_giftcode/dist/giftcodes/" & IF(ISNUMBER(LEFT(A3,1)*1), "game-", "") & A3 & ".html") -> https://www.ssbuy.tw/detail_giftcode/dist/giftcodes/原神.html | H3: =IF(A3="","", "https://www.ssbuy.tw/detail_giftcode/dist/gamedetail/" & IF(ISNUMBER(LEFT(A3,1)*1), "game-", "") & A3 & ".html") -> https://www.ssbuy.tw/detail_giftcode/dist/gamedetail/原神.html | I3: 《原神》是一款開放世界冒險角色扮演遊戲。 踏上跨越奇幻世界提瓦特大陸的旅程。 在這個廣闊世界中，探索七個國家，遇到擁有獨特性格和能力的不同角色，並與他們一起對抗強大的敵人，並同時尋找您失散的手足。 自由冒險，沈浸在充滿生命力的世界中，讓好奇心引領您揭開它所有的神秘面紗。 | J3: 創世結晶 60顆 | K3: 30 | L3: 創世結晶 300顆 | M3: 137 | N3: 創世結晶 980顆 | O3: 390 | P3: 創世結晶 1980顆 | Q3: 780 | R3: 創世結晶 3280顆 | S3: 1300 | T3: 創世結晶 6480顆 | U3: 2350 | V3: 空月祝福 | W3: 137 | X3: 珍珠紀行 | Y3: 260 | Z3: 珍珠之歌 | AA3: 520
A4: 極速快感 | F4: =IF(A4="","", "https://www.ssbuy.tw/detail_giftcode/dist/giftcodes/" & IF(ISNUMBER(LEFT(A4,1)*1), "game-", "") & A4 & ".html") -> https://www.ssbuy.tw/detail_giftcode/dist/giftcodes/極速快感.html | H4: =IF(A4="","", "https://www.ssbuy.tw/detail_giftcode/dist/gamedetail/" & IF(ISNUMBER(LEFT(A4,1)*1), "game-", "") & A4 & ".html") -> https://www.ssbuy.tw/detail_giftcode/dist/gamedetail/極速快感.html | I4: 《極速快感：集結》（英語：Need for Speed Mobile，中國大陸譯作「極品飛車：集結」）是一款由騰訊遊戲旗下天美工作室群開發、美商藝電發行的開放世界競速手機遊戲，台灣、香港和澳門地區由Garena代理發行。 | J4: 66點券 | K4: 35 | L4: 340點券 | M4: 137 | N4: 660點券 | O4: 264 | P4: 980點券 | Q4: 394 | R4: 1980點券 | S4: 786 | T4: 2580點券 | U4: 1130 | V4: 3380點券 | W4: 1323 | X4: 6580點券 | Y4: 2551 | Z4: 月卡 | AA4: 137 | AB4: 普通通行證 | AC4: 270 | AD4: 豪華通行證 | AE4: 540 | AF4: 超值理財 | AG4: 267
A5: 俠客傳說：小小英雄 | F5: =IF(A5="","", "https://www.ssbuy.tw/detail_giftcode/dist/giftcodes/" & IF(ISNUMBER(LEFT(A5,1)*1), "game-", "") & A5 & ".html") -> https://www.ssbuy.tw/detail_giftcode/dist/giftcodes/俠客傳說：小小英雄.html | H5: =IF(A5="","", "https://www.ssbuy.tw/detail_giftcode/dist/gamedetail/" & IF(ISNUMBER(LEFT(A5,1)*1), "game-", "") & A5 & ".html") -> https://www.ssbuy.tw/detail_giftcode/dist/gamedetail/俠客傳說：小小英雄.html | I5: 有你的地方，就有江湖。 | J5: 9999仙玉 | K5: 8300 | L5: 3290仙玉 | M5: 2551 | N5: 1690仙玉 | O5: 1323 | P5: 670仙玉 | Q5: 539 | R5: 330仙玉 | S5: 267 | T5: 170仙玉 | U5: 137 | V5: 33仙玉 | W5: 40
A6: 逆水寒 | F6: =IF(A6="","", "https://www.ssbuy.tw/detail_giftcode/dist/giftcodes/" & IF(ISNUMBER(LEFT(A6,1)*1), "game-", "") & A6 & ".html") -> https://www.ssbuy.tw/detail_giftcode/dist/giftcodes/逆水寒.html | H6: =IF(A6="","", "https://www.ssbuy.tw/detail_giftcode/dist/gamedetail/" & IF(ISNUMBER(LEFT(A6,1)*1), "game-", "") & A6 & ".html") -> https://www.ssbuy.tw/detail_giftcode/dist/gamedetail/逆水寒.html | I6: 新武俠大世界冒險RPG《俠客傳說：小小英雄》 | J6: 6480玉 | K6: 2390 | L6: 3280玉 | M6: 1323 | N6: 1980玉 | O6: 810 | P6: 980玉 | Q6: 410 | R6: 300玉 | S6: 137 | T6: 60玉 | U6: 30
A7: RO仙境傳說：一定要可愛 | F7: =IF(A7="","", "https://www.ssbuy.tw/detail_giftcode/dist/giftcodes/" & IF(ISNUMBER(LEFT(A7,1)*1), "game-", "") & A7 & ".html") -> https://www.ssbuy.tw/detail_giftcode/dist/giftcodes/RO仙境傳說：一定要可愛.html | H7: =IF(A7="","", "https://www.ssbuy.tw/detail_giftcode/dist/gamedetail/" & IF(ISNUMBER(LEFT(A7,1)*1), "game-", "") & A7 & ".html") -> https://www.ssbuy.tw/detail_giftcode/dist/gamedetail/RO仙境傳說：一定要可愛.html | I7: 可不可愛？我們說了算！ | J7: 4500鑽 | K7: 2551 | L7: 3000鑽 | M7: 1720 | N7: 1500鑽 | O7: 786 | P7: 750鑽 | Q7: 394 | R7: 450鑽 | S7: 267 | T7: 225鑽 | U7: 137 | V7: 75鑽 | W7: 50
A8: RO新世代 | F8: =IF(A8="","", "https://www.ssbuy.tw/detail_giftcode/dist/giftcodes/" & IF(ISNUMBER(LEFT(A8,1)*1), "game-", "") & A8 & ".html") -> https://www.ssbuy.tw/detail_giftcode/dist/giftcodes/RO新世代.html | H8: =IF(A8="","", "https://www.ssbuy.tw/detail_giftcode/dist/gamedetail/" & IF(ISNUMBER(LEFT(A8,1)*1), "game-", "") & A8 & ".html") -> https://www.ssbuy.tw/detail_giftcode/dist/gamedetail/RO新世代.html | I8: 官方正版RO最新作「RO仙境傳説：新世代的誕生」，煥新啓航！不刪檔公測開啟！ | J8: 3290商品 | K8: 2551 | L8: 1690商品 | M8: 1323 | N8: 990商品 | O8: 786 | P8: 670商品 | Q8: 539 | R8: 330商品 | S8: 267 | T8: 170商品 | U8: 137 | V8: 33商品 | W8: 35
A9: 上古：龍神覺醒 | F9: =IF(A9="","", "https://www.ssbuy.tw/detail_giftcode/dist/giftcodes/" & IF(ISNUMBER(LEFT(A9,1)*1), "game-", "") & A9 & ".html") -> https://www.ssbuy.tw/detail_giftcode/dist/giftcodes/上古：龍神覺醒.html | H9: =IF(A9="","", "https://www.ssbuy.tw/detail_giftcode/dist/gamedetail/" & IF(ISNUMBER(LEFT(A9,1)*1), "game-", "") & A9 & ".html") -> https://www.ssbuy.tw/detail_giftcode/dist/gamedetail/上古：龍神覺醒.html | I9: 首款龍主題MMO鉅作！ | J9: 9999紅寶石 | K9: 2551 | L9: 4999紅寶石 | M9: 1380 | N9: 2999紅寶石 | O9: 830 | P9: 1999紅寶石 | Q9: 539 | R9: 1499紅寶石 | S9: 394 | T9: 999紅寶石 | U9: 267 | V9: 499紅寶石 | W9: 137 | X9: 99紅寶石 | Y9: 35
A10: 小艦艦超勇 | F10: =IF(A10="","", "https://www.ssbuy.tw/detail_giftcode/dist/giftcodes/" & IF(ISNUMBER(LEFT(A10,1)*1), "game-", "") & A10 & ".html") -> https://www.ssbuy.tw/detail_giftcode/dist/giftcodes/小艦艦超勇.html | H10: =IF(A10="","", "https://www.ssbuy.tw/detail_giftcode/dist/gamedetail/" & IF(ISNUMBER(LEFT(A10,1)*1), "game-", "") & A10 & ".html") -> https://www.ssbuy.tw/detail_giftcode/dist/gamedetail/小艦艦超勇.html | I10: 無止境的武器升級，打造你的最強艦隊！ | J10: 9999冰海水晶 | K10: 2551 | L10: 4999冰海水晶 | M10: 1323 | N10: 1999冰海水晶 | O10: 539 | P10: 999冰海水晶 | Q10: 267 | R10: 499冰海水晶 | S10: 137 | T10: 99冰海水晶 | U10: 40
A11: 天使軍團 | F11: =IF(A11="","", "https://www.ssbuy.tw/detail_giftcode/dist/giftcodes/" & IF(ISNUMBER(LEFT(A11,1)*1), "game-", "") & A11 & ".html") -> https://www.ssbuy.tw/detail_giftcode/dist/giftcodes/天使軍團.html | H11: =IF(A11="","", "https://www.ssbuy.tw/detail_giftcode/dist/gamedetail/" & IF(ISNUMBER(LEFT(A11,1)*1), "game-", "") & A11 & ".html") -> https://www.ssbuy.tw/detail_giftcode/dist/gamedetail/天使軍團.html | I11: 天使軍團是最新推出的3D天使銀河冒險RPG手遊。 希拉星系，深邃而瑰麗……這裡曾存在著古老時期的文明。 | J11: 3290商品 | K11: 2551 | L11: 1690商品 | M11: 1323 | N11: 990商品 | O11: 786 | P11: 670商品 | Q11: 539 | R11: 330商品 | S11: 267 | T11: 170商品 | U11: 137 | V11: 33商品 | W11: 35
A12: 天堂W | F12: =IF(A12="","", "https://www.ssbuy.tw/detail_giftcode/dist/giftcodes/" & IF(ISNUMBER(LEFT(A12,1)*1), "game-", "") & A12 & ".html") -> https://www.ssbuy.tw/detail_giftcode/dist/giftcodes/天堂W.html | H12: =IF(A12="","", "https://www.ssbuy.tw/detail_giftcode/dist/gamedetail/" & IF(ISNUMBER(LEFT(A12,1)*1), "game-", "") & A12 & ".html") -> https://www.ssbuy.tw/detail_giftcode/dist/gamedetail/天堂W.html | I12: 《天堂W》是繼承PC MMORPG天堂正統性的跨平台遊戲，全球單一版本服務，即時AI翻譯；Full 3D畫面和斜45度視角開發的暗黑奇幻世界；將天堂的核心內容戰鬥社群延伸到世界。 | J12: 5900商品 | K12: 5300 | L12: 2600商品 | M12: 2360 | N12: 1300商品 | O12: 1180 | P12: 780商品 | Q12: 730 | R12: 260商品 | S12: 250
A13: 少女前線2：追放 | F13: =IF(A13="","", "https://www.ssbuy.tw/detail_giftcode/dist/giftcodes/" & IF(ISNUMBER(LEFT(A13,1)*1), "game-", "") & A13 & ".html") -> https://www.ssbuy.tw/detail_giftcode/dist/giftcodes/少女前線2：追放.html | H13: =IF(A13="","", "https://www.ssbuy.tw/detail_giftcode/dist/gamedetail/" & IF(ISNUMBER(LEFT(A13,1)*1), "game-", "") & A13 & ".html") -> https://www.ssbuy.tw/detail_giftcode/dist/gamedetail/少女前線2：追放.html | I13: 講述了指揮官與格里芬之間無法調和的理念衝突，導致指揮官選擇自我流放，成為賞金獵人。 | J13: 3290商品 | K13: 2551 | L13: 1690商品 | M13: 1323 | N13: 990商品 | O13: 786 | P13: 670商品 | Q13: 539 | R13: 330商品 | S13: 267 | T13: 170商品 | U13: 137 | V13: 33商品 | W13: 35
A14: 幻獸傳說Ｍ | F14: =IF(A14="","", "https://www.ssbuy.tw/detail_giftcode/dist/giftcodes/" & IF(ISNUMBER(LEFT(A14,1)*1), "game-", "") & A14 & ".html") -> https://www.ssbuy.tw/detail_giftcode/dist/giftcodes/幻獸傳說Ｍ.html | H14: =IF(A14="","", "https://www.ssbuy.tw/detail_giftcode/dist/gamedetail/" & IF(ISNUMBER(LEFT(A14,1)*1), "game-", "") & A14 & ".html") -> https://www.ssbuy.tw/detail_giftcode/dist/gamedetail/幻獸傳說Ｍ.html | I14: 2025年萬眾期待的幻獸手遊來啦！異世界捉獸育獸RPG《幻獸傳說M》現已上市！豆花蔡黃汝可愛代言，演繹疾海兔！ | J14: 6488彩鑽 | K14: 2551 | L14: 3280彩鑽 | M14: 1323 | N14: 1980彩鑽 | O14: 786 | P14: 1280彩鑽 | Q14: 539 | R14: 980彩鑽 | S14: 394 | T14: 680彩鑽 | U14: 267 | V14: 300彩鑽 | W14: 137 | X14: 60彩鑽 | Y14: 35
A15: 未定事件簿 | F15: =IF(A15="","", "https://www.ssbuy.tw/detail_giftcode/dist/giftcodes/" & IF(ISNUMBER(LEFT(A15,1)*1), "game-", "") & A15 & ".html") -> https://www.ssbuy.tw/detail_giftcode/dist/giftcodes/未定事件簿.html | H15: =IF(A15="","", "https://www.ssbuy.tw/detail_giftcode/dist/gamedetail/" & IF(ISNUMBER(LEFT(A15,1)*1), "game-", "") & A15 & ".html") -> https://www.ssbuy.tw/detail_giftcode/dist/gamedetail/未定事件簿.html | I15: 當正義與邪惡的界定越來越模糊，妳手中的天平將會傾向何方？一場戀愛與推理的冒險，此刻，邀妳共赴。 | J15: 3290商品 | K15: 2551 | L15: 1690商品 | M15: 1323 | N15: 990商品 | O15: 786 | P15: 670商品 | Q15: 539 | R15: 330商品 | S15: 267 | T15: 170商品 | U15: 137 | V15: 33商品 | W15: 35
A16: 永恆靈魂 | F16: =IF(A16="","", "https://www.ssbuy.tw/detail_giftcode/dist/giftcodes/" & IF(ISNUMBER(LEFT(A16,1)*1), "game-", "") & A16 & ".html") -> https://www.ssbuy.tw/detail_giftcode/dist/giftcodes/永恆靈魂.html | H16: =IF(A16="","", "https://www.ssbuy.tw/detail_giftcode/dist/gamedetail/" & IF(ISNUMBER(LEFT(A16,1)*1), "game-", "") & A16 & ".html") -> https://www.ssbuy.tw/detail_giftcode/dist/gamedetail/永恆靈魂.html | I16: 末日的今天，精靈們等候您的指示…救援者，帶領著她們的靈魂活下去吧。 | J16: 3290商品 | K16: 2551 | L16: 1690商品 | M16: 1323 | N16: 990商品 | O16: 786 | P16: 670商品 | Q16: 539 | R16: 330商品 | S16: 267 | T16: 170商品 | U16: 137 | V16: 33商品 | W16: 35
A17: 守住呀主公 | F17: =IF(A17="","", "https://www.ssbuy.tw/detail_giftcode/dist/giftcodes/" & IF(ISNUMBER(LEFT(A17,1)*1), "game-", "") & A17 & ".html") -> https://www.ssbuy.tw/detail_giftcode/dist/giftcodes/守住呀主公.html | H17: =IF(A17="","", "https://www.ssbuy.tw/detail_giftcode/dist/gamedetail/" & IF(ISNUMBER(LEFT(A17,1)*1), "game-", "") & A17 & ".html") -> https://www.ssbuy.tw/detail_giftcode/dist/gamedetail/守住呀主公.html | I17: 喜歡策略塔防、鍾愛三國名將的你，絕對不容錯過這款高畫質3D塔防力作！豐富的塔防玩法、酷炫的技能特效，讓你盡享爽快的遊戲體驗。 | J17: 6000元寶 | K17: 2551 | L17: 3000元寶 | M17: 1323 | N17: 1800元寶 | O17: 786 | P17: 1200元寶 | Q17: 539 | R17: 900元寶 | S17: 394 | T17: 600元寶 | U17: 267 | V17: 300元寶 | W17: 137 | X17: 60元寶 | Y17: 30
A18: 吟遊戰記 | F18: =IF(A18="","", "https://www.ssbuy.tw/detail_giftcode/dist/giftcodes/" & IF(ISNUMBER(LEFT(A18,1)*1), "game-", "") & A18 & ".html") -> https://www.ssbuy.tw/detail_giftcode/dist/giftcodes/吟遊戰記.html | H18: =IF(A18="","", "https://www.ssbuy.tw/detail_giftcode/dist/gamedetail/" & IF(ISNUMBER(LEFT(A18,1)*1), "game-", "") & A18 & ".html") -> https://www.ssbuy.tw/detail_giftcode/dist/gamedetail/吟遊戰記.html | I18: 新感覺放置型勇者冒險RPG，登入即可獲得免費9999連抽！輕鬆休閒的冒險，來一場解放雙手的戰鬥吧！ | J18: 6480鑽石 | K18: 2551 | L18: 3280鑽石 | M18: 1323 | N18: 1980鑽石 | O18: 786 | P18: 1280鑽石 | Q18: 539 | R18: 980鑽石 | S18: 394 | T18: 680鑽石 | U18: 267 | V18: 300鑽石 | W18: 137 | X18: 60鑽石 | Y18: 30
A19: 我獨自升級：ARISE | F19: =IF(A19="","", "https://www.ssbuy.tw/detail_giftcode/dist/giftcodes/" & IF(ISNUMBER(LEFT(A19,1)*1), "game-", "") & A19 & ".html") -> https://www.ssbuy.tw/detail_giftcode/dist/giftcodes/我獨自升級：ARISE.html | H19: =IF(A19="","", "https://www.ssbuy.tw/detail_giftcode/dist/gamedetail/" & IF(ISNUMBER(LEFT(A19,1)*1), "game-", "") & A19 & ".html") -> https://www.ssbuy.tw/detail_giftcode/dist/gamedetail/我獨自升級：ARISE.html | I19: 德國最強的獵人，也是世界獵人排名第12名的S級「萊納德．尼爾曼」已加入完成！ | J19: 8700鑽 | K19: 1940 | L19: 4750鑽 | M19: 1150 | N19: 2600鑽 | O19: 620 | P19: 1150鑽 | Q19: 267 | R19: 335鑽 | S19: 90 | T19: 110鑽 | U19: 30
A20: 命運聖契：少女的羈絆 | F20: =IF(A20="","", "https://www.ssbuy.tw/detail_giftcode/dist/giftcodes/" & IF(ISNUMBER(LEFT(A20,1)*1), "game-", "") & A20 & ".html") -> https://www.ssbuy.tw/detail_giftcode/dist/giftcodes/命運聖契：少女的羈絆.html | H20: =IF(A20="","", "https://www.ssbuy.tw/detail_giftcode/dist/gamedetail/" & IF(ISNUMBER(LEFT(A20,1)*1), "game-", "") & A20 & ".html") -> https://www.ssbuy.tw/detail_giftcode/dist/gamedetail/命運聖契：少女的羈絆.html | I20: 2025首款命運少女輕放置RPG手遊《命運聖契：少女的羈絆》霜糖奇典活动開啟！登錄可得自選SSR、限定頭像框及海量高價值虛寶。 | J20: 6480星鑽 | K20: 2551 | L20: 3280星鑽 | M20: 1323 | N20: 1980星鑽 | O20: 786 | P20: 980星鑽 | Q20: 394 | R20: 300星鑽 | S20: 137 | T20: 60星鑽 | U20: 40
A21: 放置軍團 | F21: =IF(A21="","", "https://www.ssbuy.tw/detail_giftcode/dist/giftcodes/" & IF(ISNUMBER(LEFT(A21,1)*1), "game-", "") & A21 & ".html") -> https://www.ssbuy.tw/detail_giftcode/dist/giftcodes/放置軍團.html | H21: =IF(A21="","", "https://www.ssbuy.tw/detail_giftcode/dist/gamedetail/" & IF(ISNUMBER(LEFT(A21,1)*1), "game-", "") & A21 & ".html") -> https://www.ssbuy.tw/detail_giftcode/dist/gamedetail/放置軍團.html | I21: 我們敬愛的魔王大人在與人類的決戰中，因為死亡騎士臨陣倒戈，被人類打碎成了渣渣。我們三個忠心耿耿的小鬼抬著魔王的靈魂碎片，躲進了一座廢棄的地下城。在這裡我們要重新建立地下城，儲備物資，集結軍團！ | J21: 6480氪晶 | K21: 2540 | L21: 3280氪晶 | M21: 1280 | N21: 1280氪晶 | O21: 539 | P21: 680氪晶 | Q21: 267 | R21: 300氪晶 | S21: 137
A22: 明日方舟 | F22: =IF(A22="","", "https://www.ssbuy.tw/detail_giftcode/dist/giftcodes/" & IF(ISNUMBER(LEFT(A22,1)*1), "game-", "") & A22 & ".html") -> https://www.ssbuy.tw/detail_giftcode/dist/giftcodes/明日方舟.html | H22: =IF(A22="","", "https://www.ssbuy.tw/detail_giftcode/dist/gamedetail/" & IF(ISNUMBER(LEFT(A22,1)*1), "game-", "") & A22 & ".html") -> https://www.ssbuy.tw/detail_giftcode/dist/gamedetail/明日方舟.html | I22: 迷宮裡……竟然存在這樣的地方？準備好刀劍和法杖，也別忘了鍋、鏟和調味料！準備好了嗎，我們要開動了喔！ | J22: 3290商品 | K22: 2551 | L22: 1690商品 | M22: 1323 | N22: 990商品 | O22: 786 | P22: 670商品 | Q22: 539 | R22: 330商品 | S22: 267 | T22: 170商品 | U22: 137 | V22: 33商品 | W22: 35
A23: 屍鬼三國 | F23: =IF(A23="","", "https://www.ssbuy.tw/detail_giftcode/dist/giftcodes/" & IF(ISNUMBER(LEFT(A23,1)*1), "game-", "") & A23 & ".html") -> https://www.ssbuy.tw/detail_giftcode/dist/giftcodes/屍鬼三國.html | H23: =IF(A23="","", "https://www.ssbuy.tw/detail_giftcode/dist/gamedetail/" & IF(ISNUMBER(LEFT(A23,1)*1), "game-", "") & A23 & ".html") -> https://www.ssbuy.tw/detail_giftcode/dist/gamedetail/屍鬼三國.html | I23: 獨一款屍鬼化的三國卡牌手遊上市啦！新世代三國卡牌鉅作，融合了ARPG的開放世界設計，你可以在屍鬼橫行的三國亂世中自由探索。 | J23: 6000金玉 | K23: 2551 | L23: 3000金玉 | M23: 1323 | N23: 1800金玉 | O23: 786 | P23: 900金玉 | Q23: 394 | R23: 300金玉 | S23: 137 | T23: 60金玉 | U23: 30
A24: 星鏈計畫：未來少女 | F24: =IF(A24="","", "https://www.ssbuy.tw/detail_giftcode/dist/giftcodes/" & IF(ISNUMBER(LEFT(A24,1)*1), "game-", "") & A24 & ".html") -> https://www.ssbuy.tw/detail_giftcode/dist/giftcodes/星鏈計畫：未來少女.html | H24: =IF(A24="","", "https://www.ssbuy.tw/detail_giftcode/dist/gamedetail/" & IF(ISNUMBER(LEFT(A24,1)*1), "game-", "") & A24 & ".html") -> https://www.ssbuy.tw/detail_giftcode/dist/gamedetail/星鏈計畫：未來少女.html | I24: 在無盡的絕望中，為少女們構築希望藍圖！ | J24: 5500星際比特 | K24: 2150 | L24: 4400星際比特 | M24: 1750 | N24: 2750星際比特 | O24: 1130 | P24: 1650星際比特 | Q24: 700 | R24: 750星際比特 | S24: 340 | T24: 165星際比特 | U24: 90
A25: 英雄之王 | F25: =IF(A25="","", "https://www.ssbuy.tw/detail_giftcode/dist/giftcodes/" & IF(ISNUMBER(LEFT(A25,1)*1), "game-", "") & A25 & ".html") -> https://www.ssbuy.tw/detail_giftcode/dist/giftcodes/英雄之王.html | H25: =IF(A25="","", "https://www.ssbuy.tw/detail_giftcode/dist/gamedetail/" & IF(ISNUMBER(LEFT(A25,1)*1), "game-", "") & A25 & ".html") -> https://www.ssbuy.tw/detail_giftcode/dist/gamedetail/英雄之王.html | I25: 除了我們分享的遊戲畫面、影片和其他細節之外，我還想讓大家了解我們對遊戲的期望與願景。 我們希望能藉由《英雄之王》捕捉遊戲的本質。 | J25: 3290商品 | K25: 2551 | L25: 1690商品 | M25: 1323 | N25: 990商品 | O25: 786 | P25: 670商品 | Q25: 539 | R25: 330商品 | S25: 267 | T25: 170商品 | U25: 137 | V25: 33商品 | W25: 35
A26: 英雄聯盟 | F26: =IF(A26="","", "https://www.ssbuy.tw/detail_giftcode/dist/giftcodes/" & IF(ISNUMBER(LEFT(A26,1)*1), "game-", "") & A26 & ".html") -> https://www.ssbuy.tw/detail_giftcode/dist/giftcodes/英雄聯盟.html | H26: =IF(A26="","", "https://www.ssbuy.tw/detail_giftcode/dist/gamedetail/" & IF(ISNUMBER(LEFT(A26,1)*1), "game-", "") & A26 & ".html") -> https://www.ssbuy.tw/detail_giftcode/dist/gamedetail/英雄聯盟.html | I26: 別再讓老媽扛傷害了 | J26: 12150聯盟幣 | K26: 2420 | L26: 7050聯盟幣 | M26: 1323 | N26: 3500聯盟幣 | O26: 740 | P26: 1380聯盟幣 | Q26: 267 | R26: 660聯盟幣 | S26: 137
A27: 恐龍突變 | F27: =IF(A27="","", "https://www.ssbuy.tw/detail_giftcode/dist/giftcodes/" & IF(ISNUMBER(LEFT(A27,1)*1), "game-", "") & A27 & ".html") -> https://www.ssbuy.tw/detail_giftcode/dist/giftcodes/恐龍突變.html | H27: =IF(A27="","", "https://www.ssbuy.tw/detail_giftcode/dist/gamedetail/" & IF(ISNUMBER(LEFT(A27,1)*1), "game-", "") & A27 & ".html") -> https://www.ssbuy.tw/detail_giftcode/dist/gamedetail/恐龍突變.html | I27: » 配對以產生受精卵: 進行戰略性交配以創造更強大的恐龍。» 點擊孵化無限的蛋: 不斷擴展你的恐龍收藏。 | J27: 1490商品 | K27: 1323 | L27: 1290商品 | M27: 1120 | N27: 990商品 | O27: 786 | P27: 790商品 | Q27: 680 | R27: 690商品 | S27: 539 | T27: 490商品 | U27: 394 | V27: 320商品 | W27: 267 | X27: 190商品 | Y27: 170
A28: 神域 | F28: =IF(A28="","", "https://www.ssbuy.tw/detail_giftcode/dist/giftcodes/" & IF(ISNUMBER(LEFT(A28,1)*1), "game-", "") & A28 & ".html") -> https://www.ssbuy.tw/detail_giftcode/dist/giftcodes/神域.html | H28: =IF(A28="","", "https://www.ssbuy.tw/detail_giftcode/dist/gamedetail/" & IF(ISNUMBER(LEFT(A28,1)*1), "game-", "") & A28 & ".html") -> https://www.ssbuy.tw/detail_giftcode/dist/gamedetail/神域.html | I28: 對抗邪惡勢力，策略過人的您並非孤軍奮戰，來自世界各地且為數眾多的神話英雄，正等待您的召喚！透過遊戲掛機得到的寶石、材料及各種資源，一支強而有力且技能靈活的自訂專屬軍團，就在您的股掌之間！ | J28: 3290商品 | K28: 2551 | L28: 1690商品 | M28: 1323 | N28: 990商品 | O28: 786 | P28: 670商品 | Q28: 539 | R28: 330商品 | S28: 267 | T28: 170商品 | U28: 137 | V28: 33商品 | W28: 35
A29: 崩壞：星穹鐵道 | F29: =IF(A29="","", "https://www.ssbuy.tw/detail_giftcode/dist/giftcodes/" & IF(ISNUMBER(LEFT(A29,1)*1), "game-", "") & A29 & ".html") -> https://www.ssbuy.tw/detail_giftcode/dist/giftcodes/崩壞：星穹鐵道.html | H29: =IF(A29="","", "https://www.ssbuy.tw/detail_giftcode/dist/gamedetail/" & IF(ISNUMBER(LEFT(A29,1)*1), "game-", "") & A29 & ".html") -> https://www.ssbuy.tw/detail_giftcode/dist/gamedetail/崩壞：星穹鐵道.html | I29: 這片銀河中有名為「星神」的存在，祂們造就現實，抹消星辰，在無數「世界」中留下祂們的痕跡。你——一名特殊的旅客，將偕同繼承「開拓」意志的同伴們，乘坐星穹列車穿越銀河，沿著某位「星神」曾經所行之途前進。你將由此探索新的文明、結識新的夥伴、在無數光怪陸離的「世界」之間展開新的冒險。所有你想知道的，都將在群星中找到解答。 那麼，準備好開始這段「開拓」之旅了嗎？ | J29: 6480古老夢華 | K29: 2320 | L29: 3280古老夢華 | M29: 1250 | N29: 1980古老夢華 | O29: 790 | P29: 980古老夢華 | Q29: 394 | R29: 300古老夢華 | S29: 137 | T29: 60古老夢華 | U29: 30 | V29: 列車補給憑證 | W29: 137 | X29: 無名客的榮勳 | Y29: 260 | Z29: 無名客的獎章 | AA29: 520
A30: 救世者之樹：新世界 | F30: =IF(A30="","", "https://www.ssbuy.tw/detail_giftcode/dist/giftcodes/" & IF(ISNUMBER(LEFT(A30,1)*1), "game-", "") & A30 & ".html") -> https://www.ssbuy.tw/detail_giftcode/dist/giftcodes/救世者之樹：新世界.html | H30: =IF(A30="","", "https://www.ssbuy.tw/detail_giftcode/dist/gamedetail/" & IF(ISNUMBER(LEFT(A30,1)*1), "game-", "") & A30 & ".html") -> https://www.ssbuy.tw/detail_giftcode/dist/gamedetail/救世者之樹：新世界.html | I30: 在重磅上線的樹緣系統中，舉行浪漫的樹緣典禮；集結戰友做好準備，迎戰魔神副本BOSS！ 新手可領取70抽、金色時裝4件套還有限定自選坐騎！ 讓我們來看看來自亞洲11地區的勇者們的留言！ -「日本韓國泰國的妹妹都搶著跟我結緣…好難選哦！」 --來自世界頻道的建巨集007號 樹緣系統重磅上線，在全服玩家的見證和祝福下，完成盛大浪漫的樹緣典禮！還會擁有一個共同的家園，一起創造美好生活！ | J30: 3290商品 | K30: 2551 | L30: 1690商品 | M30: 1323 | N30: 990商品 | O30: 786 | P30: 670商品 | Q30: 539 | R30: 330商品 | S30: 267 | T30: 170商品 | U30: 137 | V30: 33商品 | W30: 35
A31: 球球英雄 | F31: =IF(A31="","", "https://www.ssbuy.tw/detail_giftcode/dist/giftcodes/" & IF(ISNUMBER(LEFT(A31,1)*1), "game-", "") & A31 & ".html") -> https://www.ssbuy.tw/detail_giftcode/dist/giftcodes/球球英雄.html | H31: =IF(A31="","", "https://www.ssbuy.tw/detail_giftcode/dist/gamedetail/" & IF(ISNUMBER(LEFT(A31,1)*1), "game-", "") & A31 & ".html") -> https://www.ssbuy.tw/detail_giftcode/dist/gamedetail/球球英雄.html | I31: 怪物們在這一天毫無預兆地突然降臨，城市與家園都籠罩在猙獰與陰霾中。 我們需要你，勇士！為我們抵禦黑暗勢力！ 來吧！和我們一起，召喚出賦有神奇力量的球球，與黑暗勢力戰鬥！ | J31: 3290商品 | K31: 2551 | L31: 1690商品 | M31: 1390 | N31: 990商品 | O31: 786 | P31: 670商品 | Q31: 539 | R31: 330商品 | S31: 267 | T31: 170商品 | U31: 137 | V31: 33商品 | W31: 35
A32: 第七史詩 | F32: =IF(A32="","", "https://www.ssbuy.tw/detail_giftcode/dist/giftcodes/" & IF(ISNUMBER(LEFT(A32,1)*1), "game-", "") & A32 & ".html") -> https://www.ssbuy.tw/detail_giftcode/dist/giftcodes/第七史詩.html | H32: =IF(A32="","", "https://www.ssbuy.tw/detail_giftcode/dist/gamedetail/" & IF(ISNUMBER(LEFT(A32,1)*1), "game-", "") & A32 & ".html") -> https://www.ssbuy.tw/detail_giftcode/dist/gamedetail/第七史詩.html | I32: 第七個世界的故事...生命的女神迪彩將自己的權勢瓜分，創造出聖約的繼承者及神獸 | J32: 3290商品 | K32: 2551 | L32: 1690商品 | M32: 1390 | N32: 990商品 | O32: 786 | P32: 670商品 | Q32: 539 | R32: 330商品 | S32: 267 | T32: 170商品 | U32: 137 | V32: 33商品 | W32: 35
A33: 創世紀戰M：阿修羅計畫 | F33: =IF(A33="","", "https://www.ssbuy.tw/detail_giftcode/dist/giftcodes/" & IF(ISNUMBER(LEFT(A33,1)*1), "game-", "") & A33 & ".html") -> https://www.ssbuy.tw/detail_giftcode/dist/giftcodes/創世紀戰M：阿修羅計畫.html | H33: =IF(A33="","", "https://www.ssbuy.tw/detail_giftcode/dist/gamedetail/" & IF(ISNUMBER(LEFT(A33,1)*1), "game-", "") & A33 & ".html") -> https://www.ssbuy.tw/detail_giftcode/dist/gamedetail/創世紀戰M：阿修羅計畫.html | I33: 富饒廣闊的安塔利亞大陸，因戰爭爆發一切風雲變色，飽受戰爭欺凌， 王女伊歐林帶著王國騎士團，憑藉勇氣與智慧復國，對抗艱難命運。 面對強大武力的蓋席勒帝國，也絕不屈服！ | J33: 6350鑽石 | K33: 2551 | L33: 4400鑽石 | M33: 1980 | N33: 3200鑽石 | O33: 1323 | P33: 1850鑽石 | Q33: 786 | R33: 1250鑽石 | S33: 539 | T33: 900鑽石 | U33: 394 | V33: 310鑽石 | W33: 137 | X33: 60鑽石 | Y33: 40
A34: 最強宗師 | F34: =IF(A34="","", "https://www.ssbuy.tw/detail_giftcode/dist/giftcodes/" & IF(ISNUMBER(LEFT(A34,1)*1), "game-", "") & A34 & ".html") -> https://www.ssbuy.tw/detail_giftcode/dist/giftcodes/最強宗師.html | H34: =IF(A34="","", "https://www.ssbuy.tw/detail_giftcode/dist/gamedetail/" & IF(ISNUMBER(LEFT(A34,1)*1), "game-", "") & A34 & ".html") -> https://www.ssbuy.tw/detail_giftcode/dist/gamedetail/最強宗師.html | I34: 《最強宗師》是一款最強卡牌策略RPG，在這裡，每位角色都有獨特特質，不存在廢卡，所有資源都能無損傳承，讓你輕鬆成為最強宗師！躺平掛機也能生產材料，輕鬆實現戰力飆升。策略搭配、多樣玩法，帶你領略充滿熱血與智慧的宗門修煉之路！在這裡，人人都可以是主角，天選之人，唯我最強！ | J34: 99.99美金仙玉 | K34: 2551 | L34: 49.99美金仙玉 | M34: 1323 | N34: 29.99美金仙玉 | O34: 786 | P34: 19.99美金仙玉 | Q34: 539 | R34: 14.99美金仙玉 | S34: 394 | T34: 9.99美金仙玉 | U34: 267 | V34: 4.99美金仙玉 | W34: 137 | X34: 1.99美金仙玉 | Y34: 60 | Z34: 0.99美金仙玉 | AA34: 35
A35: 無期迷途 | F35: =IF(A35="","", "https://www.ssbuy.tw/detail_giftcode/dist/giftcodes/" & IF(ISNUMBER(LEFT(A35,1)*1), "game-", "") & A35 & ".html") -> https://www.ssbuy.tw/detail_giftcode/dist/giftcodes/無期迷途.html | H35: =IF(A35="","", "https://www.ssbuy.tw/detail_giftcode/dist/gamedetail/" & IF(ISNUMBER(LEFT(A35,1)*1), "game-", "") & A35 & ".html") -> https://www.ssbuy.tw/detail_giftcode/dist/gamedetail/無期迷途.html | I35: 《無期迷途》是款以混沌都市為主題的RPG即時策略攻防手遊。身為【米諾斯危機管理局】局長的你，將親手追蹤並收容擁有特殊力量的異能使者——禁閉者們。使用禁閉者的禁忌力量，揭開隱藏在這個世界的真相！ 「您好，新任的局長，我們一直都在等你。」這裡是米諾斯危機管理局，一座收容禁閉者的隱密場所。而您——令人尊敬的局長，將在此釋放其中最強大的禁閉者們。他們或舉止優雅，或性情乖張，或美艷狡猾；唯一的共同點他們都有不為人知的過去，以及超越常人的超凡之力。 局長，請盡情使用他們的力量，深入狄斯城的禁區，尋找讓世界異變的源頭，解開瘋狂恐怖謎團，去扭轉命運吧！ | J35: 6480晶源 | K35: 2360 | L35: 3280晶源 | M35: 1200 | N35: 1980晶源 | O35: 800 | P35: 980晶源 | Q35: 420 | R35: 300晶源 | S35: 137 | T35: 60晶源 | U35: 30
A36: 絕區零 | F36: =IF(A36="","", "https://www.ssbuy.tw/detail_giftcode/dist/giftcodes/" & IF(ISNUMBER(LEFT(A36,1)*1), "game-", "") & A36 & ".html") -> https://www.ssbuy.tw/detail_giftcode/dist/giftcodes/絕區零.html | H36: =IF(A36="","", "https://www.ssbuy.tw/detail_giftcode/dist/gamedetail/" & IF(ISNUMBER(LEFT(A36,1)*1), "game-", "") & A36 & ".html") -> https://www.ssbuy.tw/detail_giftcode/dist/gamedetail/絕區零.html | I36: 遊戲故事發生在被神秘災害「空洞」所侵襲的後世界末日世界中，主角是一位名為「繩匠」的角色，負責引導人們進入「空洞」並與怪物「以骸」戰鬥。 | J36: 6480菲林底片 | K36: 2520 | L36: 3280菲林底片 | M36: 1323 | N36: 1980菲林底片 | O36: 786 | P36: 980菲林底片 | Q36: 394 | R36: 300菲林底片 | S36: 137 | T36: 60菲林底片 | U36: 30 | V36: 繩網會員 | W36: 137 | X36: 成長計畫 | Y36: 270 | Z36: 典藏計畫 | AA36: 540
A37: 傳說對決 | F37: =IF(A37="","", "https://www.ssbuy.tw/detail_giftcode/dist/giftcodes/" & IF(ISNUMBER(LEFT(A37,1)*1), "game-", "") & A37 & ".html") -> https://www.ssbuy.tw/detail_giftcode/dist/giftcodes/傳說對決.html | H37: =IF(A37="","", "https://www.ssbuy.tw/detail_giftcode/dist/gamedetail/" & IF(ISNUMBER(LEFT(A37,1)*1), "game-", "") & A37 & ".html") -> https://www.ssbuy.tw/detail_giftcode/dist/gamedetail/傳說對決.html | I37: Garena 傳說對決是一款節奏快速、輕鬆又不失競技成分的MOBA 手遊，經典玩法加上獨特的輪盤指向施法的直覺操作模式，輕鬆競技於指掌之間！ | J37: 4110點券 | K37: 2660 | L37: 3692點券 | M37: 2350 | N37: 2943點券 | O37: 1890 | P37: 2047點券 | Q37: 1390 | R37: 1466點券 | S37: 970 | T37: 1092點券 | U37: 750 | V37: 728點券 | W37: 490 | X37: 364點券 | Y37: 250
A38: 楓之谷M | F38: =IF(A38="","", "https://www.ssbuy.tw/detail_giftcode/dist/giftcodes/" & IF(ISNUMBER(LEFT(A38,1)*1), "game-", "") & A38 & ".html") -> https://www.ssbuy.tw/detail_giftcode/dist/giftcodes/楓之谷M.html | H38: =IF(A38="","", "https://www.ssbuy.tw/detail_giftcode/dist/gamedetail/" & IF(ISNUMBER(LEFT(A38,1)*1), "game-", "") & A38 & ".html") -> https://www.ssbuy.tw/detail_giftcode/dist/gamedetail/楓之谷M.html | I38: 《楓之谷M》是一款由Nexon開發的免費大型多人線上角色扮演遊戲，是基於《楓之谷》的移動版。 遊戲中玩家可以扮演來自各地的角色，進行冒險、戰鬥、任務、以及和其他玩家互動。 | J38: 3290商品 | K38: 2551 | L38: 1690商品 | M38: 1390 | N38: 990商品 | O38: 786 | P38: 670商品 | Q38: 539 | R38: 330商品 | S38: 267 | T38: 170商品 | U38: 137 | V38: 33商品 | W38: 35
A39: 鳴潮 | F39: =IF(A39="","", "https://www.ssbuy.tw/detail_giftcode/dist/giftcodes/" & IF(ISNUMBER(LEFT(A39,1)*1), "game-", "") & A39 & ".html") -> https://www.ssbuy.tw/detail_giftcode/dist/giftcodes/鳴潮.html | H39: =IF(A39="","", "https://www.ssbuy.tw/detail_giftcode/dist/gamedetail/" & IF(ISNUMBER(LEFT(A39,1)*1), "game-", "") & A39 & ".html") -> https://www.ssbuy.tw/detail_giftcode/dist/gamedetail/鳴潮.html | I39: 《鳴潮》是一款末世題材的開放世界遊戲，具有高自由度且豐富的內容。 遊戲玩法包括攀爬、滑翔、採集等開放世界要素，還新增了「跑牆」的元素。 本作動作方面採用玩家能夠「閃避」和「彈刀」兩種招架方式。 | J39: 6480月相 | K39: 2320 | L39: 3280月相 | M39: 1323 | N39: 1980月相 | O39: 786 | P39: 980月相 | Q39: 394 | R39: 300月相 | S39: 137 | T39: 60月相 | U39: 30 | V39: 月相觀測卡 | W39: 137 | X39: 寰宇頻道 | Y39: 260 | Z39: 寰宇特約 | AA39: 520
A40: 劍與遠征：啟程 | F40: =IF(A40="","", "https://www.ssbuy.tw/detail_giftcode/dist/giftcodes/" & IF(ISNUMBER(LEFT(A40,1)*1), "game-", "") & A40 & ".html") -> https://www.ssbuy.tw/detail_giftcode/dist/giftcodes/劍與遠征：啟程.html | H40: =IF(A40="","", "https://www.ssbuy.tw/detail_giftcode/dist/gamedetail/" & IF(ISNUMBER(LEFT(A40,1)*1), "game-", "") & A40 & ".html") -> https://www.ssbuy.tw/detail_giftcode/dist/gamedetail/劍與遠征：啟程.html | I40: 《劍與遠征：啟程》是一款全球多平台的輕鬆放置大世界RPG遊戲，由放置始祖《劍與遠征》開發團隊所打造。 玩家將集結超過百位不同能力、各具魅力的英雄夥伴，與他們一起探索名為「伊索米亞」的廣闊大世界，並逐漸揭開其中秘辛 | J40: 3290商品 | K40: 2420 | L40: 1690商品 | M40: 1323 | N40: 990商品 | O40: 786 | P40: 670商品 | Q40: 539 | R40: 330商品 | S40: 267 | T40: 170商品 | U40: 137 | V40: 33商品 | W40: 35
A41: 熱血大作戰 | F41: =IF(A41="","", "https://www.ssbuy.tw/detail_giftcode/dist/giftcodes/" & IF(ISNUMBER(LEFT(A41,1)*1), "game-", "") & A41 & ".html") -> https://www.ssbuy.tw/detail_giftcode/dist/giftcodes/熱血大作戰.html | H41: =IF(A41="","", "https://www.ssbuy.tw/detail_giftcode/dist/gamedetail/" & IF(ISNUMBER(LEFT(A41,1)*1), "game-", "") & A41 & ".html") -> https://www.ssbuy.tw/detail_giftcode/dist/gamedetail/熱血大作戰.html | I41: 《熱血大作戰》是一款輕策略街機放置型RPG遊戲，它結合了經典復古的畫風和無厘頭的搞怪元素。 遊戲以熱血沸騰的戰鬥和獨特的玩法，讓玩家重溫經典遊戲的感動，並與朋友一同體驗遊戲的樂趣。 | J41: 6580元寶 | K41: 2551 | L41: 3380元寶 | M41: 1323 | N41: 1980元寶 | O41: 786 | P41: 980元寶 | Q41: 450 | R41: 340元寶 | S41: 137 | T41: 66元寶 | U41: 40
A42: 骷髏傳說：戰神崛起 | F42: =IF(A42="","", "https://www.ssbuy.tw/detail_giftcode/dist/giftcodes/" & IF(ISNUMBER(LEFT(A42,1)*1), "game-", "") & A42 & ".html") -> https://www.ssbuy.tw/detail_giftcode/dist/giftcodes/骷髏傳說：戰神崛起.html | H42: =IF(A42="","", "https://www.ssbuy.tw/detail_giftcode/dist/gamedetail/" & IF(ISNUMBER(LEFT(A42,1)*1), "game-", "") & A42 & ".html") -> https://www.ssbuy.tw/detail_giftcode/dist/gamedetail/骷髏傳說：戰神崛起.html | I42: MMORPG遊戲，擁有英雄系統、豐富的戰鬥玩法、打寶交易機制，以及沙城爭霸等特色內容. 玩家可以自由搭配英雄，參與野外PK、奪寶、領地戰等活動，並透過交易系統進行道具和裝備的交易. | J42: 4500000金券 | K42: 2200 | L42: 2820000金券 | M42: 1380 | N42: 900000金券 | O42: 450 | P42: 480000金券 | Q42: 240 | R42: 300000金券 | S42: 137
A43: 黎明：血色魔女 | F43: =IF(A43="","", "https://www.ssbuy.tw/detail_giftcode/dist/giftcodes/" & IF(ISNUMBER(LEFT(A43,1)*1), "game-", "") & A43 & ".html") -> https://www.ssbuy.tw/detail_giftcode/dist/giftcodes/黎明：血色魔女.html | H43: =IF(A43="","", "https://www.ssbuy.tw/detail_giftcode/dist/gamedetail/" & IF(ISNUMBER(LEFT(A43,1)*1), "game-", "") & A43 & ".html") -> https://www.ssbuy.tw/detail_giftcode/dist/gamedetail/黎明：血色魔女.html | I43: 隨著《黎明：血色魔女》的正式上線，遊戲內的五大職業特色也逐漸明朗。 擁有雙面形態的血色魔女，白天為聖潔修女，擅長偽裝偵查等末世生存技巧，而入夜則化身為手持大鐮刀的血色魔女，肆意收割魔物獲取血液，貫徹永恆的生存之道。 | J43: 6480鑽石 | K43: 2551 | L43: 3280鑽石 | M43: 1323 | N43: 1980鑽石 | O43: 786 | P43: 1280鑽石 | Q43: 539 | R43: 980鑽石 | S43: 394 | T43: 680鑽石 | U43: 267 | V43: 300鑽石 | W43: 137 | X43: 60鑽石 | Y43: 35
A44: 黎明啟示錄 | F44: =IF(A44="","", "https://www.ssbuy.tw/detail_giftcode/dist/giftcodes/" & IF(ISNUMBER(LEFT(A44,1)*1), "game-", "") & A44 & ".html") -> https://www.ssbuy.tw/detail_giftcode/dist/giftcodes/黎明啟示錄.html | H44: =IF(A44="","", "https://www.ssbuy.tw/detail_giftcode/dist/gamedetail/" & IF(ISNUMBER(LEFT(A44,1)*1), "game-", "") & A44 & ".html") -> https://www.ssbuy.tw/detail_giftcode/dist/gamedetail/黎明啟示錄.html | I44: 有聲有色不俗套的英雄設定，超過90名來源於世界各地的神話人物與歷史大家齊聚一堂，不同信仰的夥伴助力你的異世界之旅！ | J44: 3290商品 | K44: 2551 | L44: 1690商品 | M44: 1390 | N44: 990商品 | O44: 786 | P44: 670商品 | Q44: 539 | R44: 330商品 | S44: 267 | T44: 170商品 | U44: 137 | V44: 33商品 | W44: 35
A45: 龍魂旅人 | F45: =IF(A45="","", "https://www.ssbuy.tw/detail_giftcode/dist/giftcodes/" & IF(ISNUMBER(LEFT(A45,1)*1), "game-", "") & A45 & ".html") -> https://www.ssbuy.tw/detail_giftcode/dist/giftcodes/龍魂旅人.html | H45: =IF(A45="","", "https://www.ssbuy.tw/detail_giftcode/dist/gamedetail/" & IF(ISNUMBER(LEFT(A45,1)*1), "game-", "") & A45 & ".html") -> https://www.ssbuy.tw/detail_giftcode/dist/gamedetail/龍魂旅人.html | I45: 一款日系輕鬆番RPG遊戲，玩家將作為失去力量的傳說之龍法夫納，與尋求幫助的傲嬌公主兼屠龍勇士齊格菲，一同穿梭在奇幻世界的相愛相殺之旅。 | J45: 6580鑽石 | K45: 2551 | L45: 3380鑽石 | M45: 1460 | N45: 1340鑽石 | O45: 539 | P45: 660鑽石 | Q45: 267 | R45: 340鑽石 | S45: 137 | T45: 60鑽石 | U45: 30
A46: 戀與深空 | F46: =IF(A46="","", "https://www.ssbuy.tw/detail_giftcode/dist/giftcodes/" & IF(ISNUMBER(LEFT(A46,1)*1), "game-", "") & A46 & ".html") -> https://www.ssbuy.tw/detail_giftcode/dist/giftcodes/戀與深空.html | H46: =IF(A46="","", "https://www.ssbuy.tw/detail_giftcode/dist/gamedetail/" & IF(ISNUMBER(LEFT(A46,1)*1), "game-", "") & A46 & ".html") -> https://www.ssbuy.tw/detail_giftcode/dist/gamedetail/戀與深空.html | I46: 《戀與深空》以「︁愛無界限」︁為核心理念，在科幻宇宙背景下融合緊張刺激的怪物狩獵玩法。 玩家可與五位男主——秦徹，祁煜，黎深、沈星回以及夏以晝——建立情感羈絆。 玩家化身深空獵人，運用名為"Evol"的超能力對抗宇宙生命體"流浪體"。 | J46: 3290商品 | K46: 2551 | L46: 1690商品 | M46: 1323 | N46: 990商品 | O46: 786 | P46: 670商品 | Q46: 539 | R46: 330商品 | S46: 267 | T46: 170商品 | U46: 137 | V46: 33商品 | W46: 35
A47: 靈魂衝擊：無限放置 | F47: =IF(A47="","", "https://www.ssbuy.tw/detail_giftcode/dist/giftcodes/" & IF(ISNUMBER(LEFT(A47,1)*1), "game-", "") & A47 & ".html") -> https://www.ssbuy.tw/detail_giftcode/dist/giftcodes/靈魂衝擊：無限放置.html | H47: =IF(A47="","", "https://www.ssbuy.tw/detail_giftcode/dist/gamedetail/" & IF(ISNUMBER(LEFT(A47,1)*1), "game-", "") & A47 & ".html") -> https://www.ssbuy.tw/detail_giftcode/dist/gamedetail/靈魂衝擊：無限放置.html | I47: 玩家將透過召喚職業與技能來殲滅蜂擁而至的怪物，稀有的職業將額外擁有特殊的被動技能屬性，可增加角色的暴擊傷害量或是閃避效果等 | J47: 99900乙醚 | K47: 2290 | L47: 49900乙醚 | M47: 1180 | N47: 29900乙醚 | O47: 720 | P47: 11900乙醚 | Q47: 267 | R47: 5900乙醚 | S47: 137 | T47: 1400乙醚 | U47: 40
A48: 楓葉島 | F48: =IF(A48="","", "https://www.ssbuy.tw/detail_giftcode/dist/giftcodes/" & IF(ISNUMBER(LEFT(A48,1)*1), "game-", "") & A48 & ".html") -> https://www.ssbuy.tw/detail_giftcode/dist/giftcodes/楓葉島.html | H48: =IF(A48="","", "https://www.ssbuy.tw/detail_giftcode/dist/gamedetail/" & IF(ISNUMBER(LEFT(A48,1)*1), "game-", "") & A48 & ".html") -> https://www.ssbuy.tw/detail_giftcode/dist/gamedetail/楓葉島.html | I48: 在一個叫礁石鎮的小鎮中，你緩緩醒來，走出門找到了本地村民，才知道是一個叫“米娜”的小姑娘救了你，得知礁石鎮是由有著同樣遭遇的冒險者們建立。 | J48: 6480彩晶 | K48: 2530 | L48: 3280彩晶 | M48: 1323 | N48: 1980彩晶 | O48: 786 | P48: 980彩晶 | Q48: 394 | R48: 300彩晶 | S48: 137 | T48: 120彩晶 | U48: 60 | V48: 60彩晶 | W48: 30
A49: 無名江湖 | F49: =IF(A49="","", "https://www.ssbuy.tw/detail_giftcode/dist/giftcodes/" & IF(ISNUMBER(LEFT(A49,1)*1), "game-", "") & A49 & ".html") -> https://www.ssbuy.tw/detail_giftcode/dist/giftcodes/無名江湖.html | H49: =IF(A49="","", "https://www.ssbuy.tw/detail_giftcode/dist/gamedetail/" & IF(ISNUMBER(LEFT(A49,1)*1), "game-", "") & A49 & ".html") -> https://www.ssbuy.tw/detail_giftcode/dist/gamedetail/無名江湖.html | I49: 以收集百家武學為目標的放置類卡牌遊戲。 遊戲中，玩家可以體驗完整的俠客人生，拜師學藝，闖蕩江湖，一步步成為一代大俠的傳奇故事。 | J49: 6480元寶 | K49: 2551 | L49: 3280元寶 | M49: 1400 | N49: 1980元寶 | O49: 786 | P49: 1280元寶 | Q49: 539 | R49: 680元寶 | S49: 267 | T49: 300元寶 | U49: 137
A50: 萬妖領域 | F50: =IF(A50="","", "https://www.ssbuy.tw/detail_giftcode/dist/giftcodes/" & IF(ISNUMBER(LEFT(A50,1)*1), "game-", "") & A50 & ".html") -> https://www.ssbuy.tw/detail_giftcode/dist/giftcodes/萬妖領域.html | H50: =IF(A50="","", "https://www.ssbuy.tw/detail_giftcode/dist/gamedetail/" & IF(ISNUMBER(LEFT(A50,1)*1), "game-", "") & A50 & ".html") -> https://www.ssbuy.tw/detail_giftcode/dist/gamedetail/萬妖領域.html | I50: 終身每日送10連抽，無限策略搭配，無損養成神將，帶給你前所未有的卡牌樂趣，獸戰到底，作妖捉妖隨你意！ 還在精打細算規劃資源，為抽不到喜歡的角色而發愁？ 史上最佛心的《萬妖領域》為您送上終生每日送10連抽，一年3650抽，讓你抽到嫑嫑！ | J50: 648仙玉 | K50: 2580 | L50: 328仙玉 | M50: 1370 | N50: 198仙玉 | O50: 786 | P50: 128仙玉 | Q50: 539 | R50: 68仙玉 | S50: 267 | T50: 30仙玉 | U50: 137
A51: 一姬當千TD | F51: =IF(A51="","", "https://www.ssbuy.tw/detail_giftcode/dist/giftcodes/" & IF(ISNUMBER(LEFT(A51,1)*1), "game-", "") & A51 & ".html") -> https://www.ssbuy.tw/detail_giftcode/dist/giftcodes/一姬當千TD.html | H51: =IF(A51="","", "https://www.ssbuy.tw/detail_giftcode/dist/gamedetail/" & IF(ISNUMBER(LEFT(A51,1)*1), "game-", "") & A51 & ".html") -> https://www.ssbuy.tw/detail_giftcode/dist/gamedetail/一姬當千TD.html | I51: 這裡是一姬當千TD的官方中心，歡迎follow我們獲取最新的遊戲訊息。這是一款輕鬆趣味策略塔防遊戲，在遊戲中您將運用策略來合理佈局，通關不同難度的關卡。 | J51: 6480元寶 | K51: 2580 | L51: 3280元寶 | M51: 1323 | N51: 1280元寶 | O51: 540 | P51: 300元寶 | Q51: 137 | R51: 60元寶 | S51: 30
A52: 劍客行 | F52: =IF(A52="","", "https://www.ssbuy.tw/detail_giftcode/dist/giftcodes/" & IF(ISNUMBER(LEFT(A52,1)*1), "game-", "") & A52 & ".html") -> https://www.ssbuy.tw/detail_giftcode/dist/giftcodes/劍客行.html | H52: =IF(A52="","", "https://www.ssbuy.tw/detail_giftcode/dist/gamedetail/" & IF(ISNUMBER(LEFT(A52,1)*1), "game-", "") & A52 & ".html") -> https://www.ssbuy.tw/detail_giftcode/dist/gamedetail/劍客行.html | I52: 故事大綱 展白背負父親「霹雷劍」展雲天被五個結義兄弟以奸計密謀殺害的血海深仇，闖蕩江湖，學成天下第一奇書《鎖骨銷魂天佛卷》，終報父仇，並獨力對抗企圖一統中原武林的強大惡勢力「南海門」，除「三煞」，誅「四凶」，力挽狂瀾，創下赫赫聲名，最終與五個美艷動人的嬌妻隱居洞庭湖畔，成就武林傳奇，一時傳為佳話。 | J52: 6480元寶 | K52: 2580 | L52: 3280元寶 | M52: 1323 | N52: 1980元寶 | O52: 786 | P52: 980元寶 | Q52: 394 | R52: 680元寶 | S52: 267 | T52: 300元寶 | U52: 137 | V52: 60元寶 | W52: 30
A53: 時之樹少女 | F53: =IF(A53="","", "https://www.ssbuy.tw/detail_giftcode/dist/giftcodes/" & IF(ISNUMBER(LEFT(A53,1)*1), "game-", "") & A53 & ".html") -> https://www.ssbuy.tw/detail_giftcode/dist/giftcodes/時之樹少女.html | H53: =IF(A53="","", "https://www.ssbuy.tw/detail_giftcode/dist/gamedetail/" & IF(ISNUMBER(LEFT(A53,1)*1), "game-", "") & A53 & ".html") -> https://www.ssbuy.tw/detail_giftcode/dist/gamedetail/時之樹少女.html | I53: ❤ 殿下，你回來了!❤ | J53: 6870龍玉 | K53: 2551 | L53: 3470龍玉 | M53: 1323 | N53: 2070龍玉 | O53: 786 | P53: 680龍玉 | Q53: 267 | R53: 330龍玉 | S53: 137 | T53: 60龍玉 | U53: 30
A54: 錨點降臨Re：Code | F54: =IF(A54="","", "https://www.ssbuy.tw/detail_giftcode/dist/giftcodes/" & IF(ISNUMBER(LEFT(A54,1)*1), "game-", "") & A54 & ".html") -> https://www.ssbuy.tw/detail_giftcode/dist/giftcodes/錨點降臨Re：Code.html | H54: =IF(A54="","", "https://www.ssbuy.tw/detail_giftcode/dist/gamedetail/" & IF(ISNUMBER(LEFT(A54,1)*1), "game-", "") & A54 & ".html") -> https://www.ssbuy.tw/detail_giftcode/dist/gamedetail/錨點降臨Re：Code.html | I54: 結合了半即時戰鬥和深度戰略玩法。 遊戲的背景設定在一場名為「修格爾戰爭」的異空間入侵戰爭之後，人類重建並復甦過來，並建立「空天星鏈」來防禦，利用「安比斯—鏈接系統」打造「戰員」。 玩家可以透過組成戰隊，利用技能與敵人屬性制定戰略，並透過源能技發動連攜攻擊，享受自由搭建的冒險旅程。 | J54: 6480源晶 | K54: 2380 | L54: 3280源晶 | M54: 1230 | N54: 1980源晶 | O54: 786 | P54: 980源晶 | Q54: 394 | R54: 300源晶 | S54: 130 | T54: 60源晶 | U54: 40
A55: 神契氣靈師 | F55: =IF(A55="","", "https://www.ssbuy.tw/detail_giftcode/dist/giftcodes/" & IF(ISNUMBER(LEFT(A55,1)*1), "game-", "") & A55 & ".html") -> https://www.ssbuy.tw/detail_giftcode/dist/giftcodes/神契氣靈師.html | H55: =IF(A55="","", "https://www.ssbuy.tw/detail_giftcode/dist/gamedetail/" & IF(ISNUMBER(LEFT(A55,1)*1), "game-", "") & A55 & ".html") -> https://www.ssbuy.tw/detail_giftcode/dist/gamedetail/神契氣靈師.html | I55: 以「氣靈師」作為其核心職業，遊戲特色包括自由選擇的玩法、BOSS挑戰、情緣系統等。 遊戲中，玩家可以與配對對象結為情緣，並在副本中携手進行挑戰，提升情緣度後更可獲得專屬同心戒和領養寶寶。 | J55: 6480元寶 | K55: 2551 | L55: 3280元寶 | M55: 1323 | N55: 1980元寶 | O55: 990 | P55: 980元寶 | Q55: 394 | R55: 300元寶 | S55: 137 | T55: 180元寶 | U55: 100 | V55: 60元寶 | W55: 40
A56: 不休旅途：繪卷世界 | F56: =IF(A56="","", "https://www.ssbuy.tw/detail_giftcode/dist/giftcodes/" & IF(ISNUMBER(LEFT(A56,1)*1), "game-", "") & A56 & ".html") -> https://www.ssbuy.tw/detail_giftcode/dist/giftcodes/不休旅途：繪卷世界.html | H56: =IF(A56="","", "https://www.ssbuy.tw/detail_giftcode/dist/gamedetail/" & IF(ISNUMBER(LEFT(A56,1)*1), "game-", "") & A56 & ".html") -> https://www.ssbuy.tw/detail_giftcode/dist/gamedetail/不休旅途：繪卷世界.html | I56: 你被神秘力量召喚，降臨這片充滿奇幻與挑戰的大地。從新手村到浮空島，從炙熱沙漠到幽深遺跡…… 每一次探索，都是一場全新的發現！這個世界大妖肆虐，動蕩不安。為了保護這個世界的和平與安寧，你召喚出繪卷中的各種夥伴，在這裡，你可以與夥伴締結羈絆，騎乘靈獸奔馳世界，一同踏上打倒大妖的冒險旅途，揭開塵封的秘密！ | J56: 3290魔晶 | K56: 2551 | L56: 1690魔晶 | M56: 1323 | N56: 670魔晶 | O56: 539 | P56: 330魔晶 | Q56: 267 | R56: 170魔晶 | S56: 137 | T56: 33魔晶 | U56: 40
A57: 別破防鴨 | F57: =IF(A57="","", "https://www.ssbuy.tw/detail_giftcode/dist/giftcodes/" & IF(ISNUMBER(LEFT(A57,1)*1), "game-", "") & A57 & ".html") -> https://www.ssbuy.tw/detail_giftcode/dist/giftcodes/別破防鴨.html | H57: =IF(A57="","", "https://www.ssbuy.tw/detail_giftcode/dist/gamedetail/" & IF(ISNUMBER(LEFT(A57,1)*1), "game-", "") & A57 & ".html") -> https://www.ssbuy.tw/detail_giftcode/dist/gamedetail/別破防鴨.html | I57: 寂靜的森林裡，鴨子弓箭手們已準備好守護森林！ 巨量怪物來襲！鴨子莊園危在旦夕！ | J57: 150000鑽 | K57: 2551 | L57: 75000鑽 | M57: 1323 | N57: 30000鑽 | O57: 539 | P57: 15000鑽 | Q57: 267 | R57: 6000鑽 | S57: 137 | T57: 1200鑽 | U57: 40
A58: 超派救星幫幫忙 | F58: =IF(A58="","", "https://www.ssbuy.tw/detail_giftcode/dist/giftcodes/" & IF(ISNUMBER(LEFT(A58,1)*1), "game-", "") & A58 & ".html") -> https://www.ssbuy.tw/detail_giftcode/dist/giftcodes/超派救星幫幫忙.html | H58: =IF(A58="","", "https://www.ssbuy.tw/detail_giftcode/dist/gamedetail/" & IF(ISNUMBER(LEFT(A58,1)*1), "game-", "") & A58 & ".html") -> https://www.ssbuy.tw/detail_giftcode/dist/gamedetail/超派救星幫幫忙.html | I58: 是一款全新世代的割草遊戲，將背包管理與彈幕射擊結合。 遊戲的目標是讓玩家在戰鬥中找到腦力與操作的平衡，最大化戰鬥力以戰勝一波波殭屍海。 玩家需要合理分配資源，並進行戰略性思考，才能在遊戲中生存下去。 | J58: 6480子彈 | K58: 2551 | L58: 3280子彈 | M58: 1323 | N58: 1980子彈 | O58: 786 | P58: 1280子彈 | Q58: 610 | R58: 680子彈 | S58: 267 | T58: 300子彈 | U58: 137 | V58: 180子彈 | W58: 90 | X58: 120子彈 | Y58: 70 | Z58: 60子彈 | AA58: 40
A59: 時光大爆炸 | F59: =IF(A59="","", "https://www.ssbuy.tw/detail_giftcode/dist/giftcodes/" & IF(ISNUMBER(LEFT(A59,1)*1), "game-", "") & A59 & ".html") -> https://www.ssbuy.tw/detail_giftcode/dist/giftcodes/時光大爆炸.html | H59: =IF(A59="","", "https://www.ssbuy.tw/detail_giftcode/dist/gamedetail/" & IF(ISNUMBER(LEFT(A59,1)*1), "game-", "") & A59 & ".html") -> https://www.ssbuy.tw/detail_giftcode/dist/gamedetail/時光大爆炸.html | I59: 穿梭燦爛文明 開啟奇幻之旅，一起體驗從石器時代、到蒸汽時代的多文明經營之路吧~ | J59: 6480玉壁 | K59: 2551 | L59: 3280玉壁 | M59: 1323 | N59: 1980玉壁 | O59: 786 | P59: 980玉壁 | Q59: 394 | R59: 680玉壁 | S59: 267 | T59: 300玉壁 | U59: 137 | V59: 60玉壁 | W59: 35
A60: 深淵：不滅者 | F60: =IF(A60="","", "https://www.ssbuy.tw/detail_giftcode/dist/giftcodes/" & IF(ISNUMBER(LEFT(A60,1)*1), "game-", "") & A60 & ".html") -> https://www.ssbuy.tw/detail_giftcode/dist/giftcodes/深淵：不滅者.html | H60: =IF(A60="","", "https://www.ssbuy.tw/detail_giftcode/dist/gamedetail/" & IF(ISNUMBER(LEFT(A60,1)*1), "game-", "") & A60 & ".html") -> https://www.ssbuy.tw/detail_giftcode/dist/gamedetail/深淵：不滅者.html | I60: 融合修仙、獸化與深淵副本的暗黑系RPG手遊。 玩家將從地獄深淵重生，透過獸化之道，一路突破地獄層級，踏上復仇之路。 遊戲特色包括：挑戰多樣深淵領主與異鬼妖獸，支援組隊擊殺Boss，孵化、馴養、進化各種強大鬼寵，以及獨特的獸化系統。 | J60: 6480仙玉 | K60: 2551 | L60: 3280仙玉 | M60: 1323 | N60: 1980仙玉 | O60: 786 | P60: 1280仙玉 | Q60: 539 | R60: 980仙玉 | S60: 394 | T60: 680仙玉 | U60: 267 | V60: 300仙玉 | W60: 137 | X60: 60仙玉 | Y60: 40
A61: Last War | F61: =IF(A61="","", "https://www.ssbuy.tw/detail_giftcode/dist/giftcodes/" & IF(ISNUMBER(LEFT(A61,1)*1), "game-", "") & A61 & ".html") -> https://www.ssbuy.tw/detail_giftcode/dist/giftcodes/Last War.html | H61: =IF(A61="","", "https://www.ssbuy.tw/detail_giftcode/dist/gamedetail/" & IF(ISNUMBER(LEFT(A61,1)*1), "game-", "") & A61 & ".html") -> https://www.ssbuy.tw/detail_giftcode/dist/gamedetail/Last War.html | I61: 生存策略遊戲，玩家在末日世界中，需要抵抗大量的殭屍，並建立基地、培養軍隊，與其他玩家合作或競爭。 這款遊戲強調團隊合作，玩家可以建立同盟，一起進行集結作戰，例如攻下高階城池或挑戰BOSS，以獲得經驗值和戰力提升。 遊戲的目標是成為世界最強的指揮官，在末日世界中存活下來並取得勝利。 | J61: 3290禮包 | K61: 2551 | L61: 1690禮包 | M61: 1320 | N61: 650禮包 | O61: 530 | P61: 330禮包 | Q61: 265 | R61: 170禮包 | S61: 137 | T61: 33禮包 | U61: 30
A62: 勇士不要停 | F62: =IF(A62="","", "https://www.ssbuy.tw/detail_giftcode/dist/giftcodes/" & IF(ISNUMBER(LEFT(A62,1)*1), "game-", "") & A62 & ".html") -> https://www.ssbuy.tw/detail_giftcode/dist/giftcodes/勇士不要停.html | H62: =IF(A62="","", "https://www.ssbuy.tw/detail_giftcode/dist/gamedetail/" & IF(ISNUMBER(LEFT(A62,1)*1), "game-", "") & A62 & ".html") -> https://www.ssbuy.tw/detail_giftcode/dist/gamedetail/勇士不要停.html | I62: 3D 放置卡牌遊戲，玩家可以在其中輕鬆掛機、躺平，享受隨玩隨停的戰鬥樂趣。 遊戲的特色包括多元的玩法、輕鬆的放置養成、以及豐富的卡牌收集和陣容搭配。 | J62: 6000鑽石 | K62: 2551 | L62: 3000鑽石 | M62: 1323 | N62: 1200鑽石 | O62: 539 | P62: 600鑽石 | Q62: 267 | R62: 300鑽石 | S62: 137 | T62: 60鑽石 | U62: 35
A63: 元氣火柴人 | F63: =IF(A63="","", "https://www.ssbuy.tw/detail_giftcode/dist/giftcodes/" & IF(ISNUMBER(LEFT(A63,1)*1), "game-", "") & A63 & ".html") -> https://www.ssbuy.tw/detail_giftcode/dist/giftcodes/元氣火柴人.html | H63: =IF(A63="","", "https://www.ssbuy.tw/detail_giftcode/dist/gamedetail/" & IF(ISNUMBER(LEFT(A63,1)*1), "game-", "") & A63 & ".html") -> https://www.ssbuy.tw/detail_giftcode/dist/gamedetail/元氣火柴人.html | I63: 它延續了火柴人經典IP，採用可愛Q萌的畫風，讓玩家在放置掛機的過程中體驗輕鬆的樂趣。 遊戲中，玩家可以選擇不同職業的角色，並透過放置掛機快速升級，自動戰鬥推圖，以及輕鬆升級裝備神器。 | J63: 6480彩鑽 | K63: 2551 | L63: 3280彩鑽 | M63: 1323 | N63: 1980彩鑽 | O63: 786 | P63: 1280彩鑽 | Q63: 630 | R63: 680彩鑽 | S63: 267 | T63: 340彩鑽 | U63: 137 | V63: 30彩鑽 | W63: 30
A64: 深淵之影 | F64: =IF(A64="","", "https://www.ssbuy.tw/detail_giftcode/dist/giftcodes/" & IF(ISNUMBER(LEFT(A64,1)*1), "game-", "") & A64 & ".html") -> https://www.ssbuy.tw/detail_giftcode/dist/giftcodes/深淵之影.html | H64: =IF(A64="","", "https://www.ssbuy.tw/detail_giftcode/dist/gamedetail/" & IF(ISNUMBER(LEFT(A64,1)*1), "game-", "") & A64 & ".html") -> https://www.ssbuy.tw/detail_giftcode/dist/gamedetail/深淵之影.html | I64: 以西方魔幻為主題的俯視角動作Roguelike遊戲。 你將在遊戲裡扮演戰士、刺客、法師等角色，深入光影交錯的地牢世界，剷除那些肆虐家園的怪物。 做好準備，走進眼前的深淵吧！ 鐵匠之子亞瑟從小居住的村莊遭到大量魔物入侵肆虐，最終被熊熊火焰所吞噬。 | J64: 4000金鑽 | K64: 170 | L64: 1900金鑽 | M64: 80 | N64: 600金鑽 | O64: 30
A65: 玩星派對 | F65: =IF(A65="","", "https://www.ssbuy.tw/detail_giftcode/dist/giftcodes/" & IF(ISNUMBER(LEFT(A65,1)*1), "game-", "") & A65 & ".html") -> https://www.ssbuy.tw/detail_giftcode/dist/giftcodes/玩星派對.html | H65: =IF(A65="","", "https://www.ssbuy.tw/detail_giftcode/dist/gamedetail/" & IF(ISNUMBER(LEFT(A65,1)*1), "game-", "") & A65 & ".html") -> https://www.ssbuy.tw/detail_giftcode/dist/gamedetail/玩星派對.html | I65: 多元化的派對樂園平台，擁有各種類型的遊戲等您來挑戰！ 不僅如此，更有豐富的養成元素，讓您可以培養自己的卡牌角色，獲得豐厚獎勵，並且與卡牌角色建立深厚的感情。 全台第一娛樂樂園，收納各種類型的派對遊戲等您來挑戰！ | J65: 6580星鑽 | K65: 12670 | L65: 3380星鑽 | M65: 1323 | N65: 1980星鑽 | O65: 786 | P65: 980星鑽 | Q65: 394 | R65: 340星鑽 | S65: 137 | T65: 66星鑽 | U65: 35
A66: 進化吧!我的人生 | F66: =IF(A66="","", "https://www.ssbuy.tw/detail_giftcode/dist/giftcodes/" & IF(ISNUMBER(LEFT(A66,1)*1), "game-", "") & A66 & ".html") -> https://www.ssbuy.tw/detail_giftcode/dist/giftcodes/進化吧!我的人生.html | H66: =IF(A66="","", "https://www.ssbuy.tw/detail_giftcode/dist/gamedetail/" & IF(ISNUMBER(LEFT(A66,1)*1), "game-", "") & A66 & ".html") -> https://www.ssbuy.tw/detail_giftcode/dist/gamedetail/進化吧!我的人生.html | I66: 本遊戲未涉及任何情節，依遊戲軟體分級辦法分類為普遍級。​本遊戲為免費軟體，另外提供付費加值服務購買虛擬物品。​長時間進行遊戲，請注意使用時間，避免沉迷於遊戲。並已於數位娛樂軟體分級登錄 | J66: 12500水晶 | K66: 2551 | L66: 6000水晶 | M66: 1323 | N66: 2300水晶 | O66: 539 | P66: 1100水晶 | Q66: 267 | R66: 525水晶 | S66: 137 | T66: 100水晶 | U66: 30
A67: 星之夢幻島 | F67: =IF(A67="","", "https://www.ssbuy.tw/detail_giftcode/dist/giftcodes/" & IF(ISNUMBER(LEFT(A67,1)*1), "game-", "") & A67 & ".html") -> https://www.ssbuy.tw/detail_giftcode/dist/giftcodes/星之夢幻島.html | H67: =IF(A67="","", "https://www.ssbuy.tw/detail_giftcode/dist/gamedetail/" & IF(ISNUMBER(LEFT(A67,1)*1), "game-", "") & A67 & ".html") -> https://www.ssbuy.tw/detail_giftcode/dist/gamedetail/星之夢幻島.html | I67: 擁有高自由度的森林系輕度冒 險MMORPG，玩家可以運用靈活切換武器的技巧，來 討伐BOSS，或是在廣闊的世界中，享受生活模式玩法 ，獲得意想不到的樂趣。 | J67: 9000卡巴拉彩晶 | K67: 2950 | L67: 4500卡巴拉彩晶 | M67: 1323 | N67: 1800卡巴拉彩晶 | O67: 539 | P67: 900卡巴拉彩晶 | Q67: 267 | R67: 450卡巴拉彩晶 | S67: 137 | T67: 180卡巴拉彩晶 | U67: 70
A68: 小冰冰傳奇：回到最初 | F68: =IF(A68="","", "https://www.ssbuy.tw/detail_giftcode/dist/giftcodes/" & IF(ISNUMBER(LEFT(A68,1)*1), "game-", "") & A68 & ".html") -> https://www.ssbuy.tw/detail_giftcode/dist/giftcodes/小冰冰傳奇：回到最初.html | H68: =IF(A68="","", "https://www.ssbuy.tw/detail_giftcode/dist/gamedetail/" & IF(ISNUMBER(LEFT(A68,1)*1), "game-", "") & A68 & ".html") -> https://www.ssbuy.tw/detail_giftcode/dist/gamedetail/小冰冰傳奇：回到最初.html | I68: 遊戲以魔幻生物橫行的傳奇大陸為背景，承載著十年青春回憶的經典英雄陸續登場。 玩家在遊戲中將透過策略搭配英雄陣容，改變戰局，體驗策略遊戲的戰鬥快感。 | J68: 6480鑽石 | K68: 2551 | L68: 3280鑽石 | M68: 2551 | N68: 1980鑽石 | O68: 786 | P68: 980鑽石 | Q68: 460 | R68: 300鑽石 | S68: 137 | T68: 60鑽石 | U68: 35
A69: 江湖風雲傳 | F69: =IF(A69="","", "https://www.ssbuy.tw/detail_giftcode/dist/giftcodes/" & IF(ISNUMBER(LEFT(A69,1)*1), "game-", "") & A69 & ".html") -> https://www.ssbuy.tw/detail_giftcode/dist/giftcodes/江湖風雲傳.html | H69: =IF(A69="","", "https://www.ssbuy.tw/detail_giftcode/dist/gamedetail/" & IF(ISNUMBER(LEFT(A69,1)*1), "game-", "") & A69 & ".html") -> https://www.ssbuy.tw/detail_giftcode/dist/gamedetail/江湖風雲傳.html | I69: 融合經典武俠與復古像素風格的手機RPG，讓玩家體驗快意恩仇的江湖世界。 | J69: 64800金錠 | K69: 2551 | L69: 32800金錠 | M69: 1323 | N69: 19800金錠 | O69: 786 | P69: 12800金錠 | Q69: 539 | R69: 9800金錠 | S69: 460 | T69: 5000金錠 | U69: 240 | V69: 3000金錠 | W69: 137 | X69: 1200金錠 | Y69: 60 | Z69: 600金錠 | AA69: 35
A70: 星願之冠：狼少女物語 | F70: =IF(A70="","", "https://www.ssbuy.tw/detail_giftcode/dist/giftcodes/" & IF(ISNUMBER(LEFT(A70,1)*1), "game-", "") & A70 & ".html") -> https://www.ssbuy.tw/detail_giftcode/dist/giftcodes/星願之冠：狼少女物語.html | H70: =IF(A70="","", "https://www.ssbuy.tw/detail_giftcode/dist/gamedetail/" & IF(ISNUMBER(LEFT(A70,1)*1), "game-", "") & A70 & ".html") -> https://www.ssbuy.tw/detail_giftcode/dist/gamedetail/星願之冠：狼少女物語.html | I70: 是一款由SuperPlanet 推出的3D 放置養成遊戲，結合了塔防元素與角色成長系統。 玩家將扮演平凡的狼少女「帕依」，在魔王統治的混亂世界中，被王冠選中，展開拯救自然樂園的冒險旅程。 | J70: 100K鑽石 | K70: 2450 | L70: 50K鑽石 | M70: 1090 | N70: 30K鑽石 | O70: 710 | P70: 10K鑽石 | Q70: 270 | R70: 5K鑽石 | S70: 137 | T70: 1K鑽石 | U70: 35
A71: 香蕉缺個芭樂 | F71: =IF(A71="","", "https://www.ssbuy.tw/detail_giftcode/dist/giftcodes/" & IF(ISNUMBER(LEFT(A71,1)*1), "game-", "") & A71 & ".html") -> https://www.ssbuy.tw/detail_giftcode/dist/giftcodes/香蕉缺個芭樂.html | H71: =IF(A71="","", "https://www.ssbuy.tw/detail_giftcode/dist/gamedetail/" & IF(ISNUMBER(LEFT(A71,1)*1), "game-", "") & A71 & ".html") -> https://www.ssbuy.tw/detail_giftcode/dist/gamedetail/香蕉缺個芭樂.html | I71: 是一款無厘頭惡搞風的植物合成塔防遊戲。 遊戲中，玩家可以操控各種可愛的水果英雄，進行合成和雜交，培育出更強大的植物。 此外，遊戲還包含塔防、組隊戰鬥等玩法，讓玩家可以體驗到不同的遊戲樂趣。 | J71: 6480鑽石 | K71: 2551 | L71: 3280鑽石 | M71: 1323 | N71: 1980鑽石 | O71: 786 | P71: 980鑽石 | Q71: 460 | R71: 300鑽石 | S71: 137 | T71: 60鑽石 | U71: 35
A72: 精靈塔塔開 | F72: =IF(A72="","", "https://www.ssbuy.tw/detail_giftcode/dist/giftcodes/" & IF(ISNUMBER(LEFT(A72,1)*1), "game-", "") & A72 & ".html") -> https://www.ssbuy.tw/detail_giftcode/dist/giftcodes/精靈塔塔開.html | H72: =IF(A72="","", "https://www.ssbuy.tw/detail_giftcode/dist/gamedetail/" & IF(ISNUMBER(LEFT(A72,1)*1), "game-", "") & A72 & ".html") -> https://www.ssbuy.tw/detail_giftcode/dist/gamedetail/精靈塔塔開.html | I72: 《精靈塔塔開》是一款結合塔防和自走棋元素的策略對戰手遊，遊戲以魔幻為主題，玩家可以選擇法師、弓箭手、戰士、牧師、召喚師等多種職業，搭配上百張卡牌組建最強戰隊，在戰場上與敵人進行對戰。 | J72: 14000鑽石 | K72: 2560 | L72: 6500鑽石 | M72: 1323 | N72: 2500鑽石 | O72: 610 | P72: 1200鑽石 | Q72: 267 | R72: 500鑽石 | S72: 137 | T72: 80鑽石 | U72: 35
A73: 終末之歌 | F73: =IF(A73="","", "https://www.ssbuy.tw/detail_giftcode/dist/giftcodes/" & IF(ISNUMBER(LEFT(A73,1)*1), "game-", "") & A73 & ".html") -> https://www.ssbuy.tw/detail_giftcode/dist/giftcodes/終末之歌.html | H73: =IF(A73="","", "https://www.ssbuy.tw/detail_giftcode/dist/gamedetail/" & IF(ISNUMBER(LEFT(A73,1)*1), "game-", "") & A73 & ".html") -> https://www.ssbuy.tw/detail_giftcode/dist/gamedetail/終末之歌.html | I73: 《終末之歌》是一款基於三國題材的豎版塔防割草遊戲，融合了roguelike 元素，提供玩家多樣化的戰鬥體驗。 遊戲將三國時期的武將以全新的方式呈現，玩家可以收集資源培養武將，並透過戰鬥和副本來體驗三國歷史。 | J73: 6480元寶 | K73: 2551 | L73: 3280元寶 | M73: 1323 | N73: 1980元寶 | O73: 786 | P73: 980元寶 | Q73: 460 | R73: 300元寶 | S73: 137 | T73: 60元寶 | U73: 30
A74: 森靈奇境 | F74: =IF(A74="","", "https://www.ssbuy.tw/detail_giftcode/dist/giftcodes/" & IF(ISNUMBER(LEFT(A74,1)*1), "game-", "") & A74 & ".html") -> https://www.ssbuy.tw/detail_giftcode/dist/giftcodes/森靈奇境.html | H74: =IF(A74="","", "https://www.ssbuy.tw/detail_giftcode/dist/gamedetail/" & IF(ISNUMBER(LEFT(A74,1)*1), "game-", "") & A74 & ".html") -> https://www.ssbuy.tw/detail_giftcode/dist/gamedetail/森靈奇境.html | I74: 「森靈奇境」是由FUNFUN TECHNOLOGU CO.,LIMITED代理發行的角色扮演類遊戲。 在這個奇幻森林中，無限自由的職業選擇讓你可以隨心轉職，沒有任何限制！ 透過最尖端的次世代技術和全開放式全景大地圖，以全3D視角自由運作，滿足你對大世界的一切幻想。 本文將給各位玩家介紹初學者在電腦上的玩法。 | J74: 64800鑽石 | K74: 2551 | L74: 32800鑽石 | M74: 1323 | N74: 19800鑽石 | O74: 786 | P74: 12800鑽石 | Q74: 539 | R74: 6800鑽石 | S74: 267 | T74: 3000鑽石 | U74: 137 | V74: 600鑽石 | W74: 35
A75: 鬥破蒼穹：蕭門篇 | F75: =IF(A75="","", "https://www.ssbuy.tw/detail_giftcode/dist/giftcodes/" & IF(ISNUMBER(LEFT(A75,1)*1), "game-", "") & A75 & ".html") -> https://www.ssbuy.tw/detail_giftcode/dist/giftcodes/鬥破蒼穹：蕭門篇.html | H75: =IF(A75="","", "https://www.ssbuy.tw/detail_giftcode/dist/gamedetail/" & IF(ISNUMBER(LEFT(A75,1)*1), "game-", "") & A75 & ".html") -> https://www.ssbuy.tw/detail_giftcode/dist/gamedetail/鬥破蒼穹：蕭門篇.html | I75: 《鬥破蒼穹：蕭門篇》是一款由Flyburst發行的角色扮演手遊，改編自同名經典玄幻小說。 遊戲完美還原了小說中的斗氣大陸，玩家將扮演主角蕭炎，從一個默默無聞的少年，一步步成長為強大的鬥帝。 | J75: 9999蕭門券 | K75: 2551 | L75: 4999蕭門券 | M75: 1323 | N75: 2999蕭門券 | O75: 786 | P75: 1490蕭門券 | Q75: 394 | R75: 999蕭門券 | S75: 267 | T75: 499蕭門券 | U75: 137 | V75: 99蕭門券 | W75: 35
A76: 無畏的狼煙 | F76: =IF(A76="","", "https://www.ssbuy.tw/detail_giftcode/dist/giftcodes/" & IF(ISNUMBER(LEFT(A76,1)*1), "game-", "") & A76 & ".html") -> https://www.ssbuy.tw/detail_giftcode/dist/giftcodes/無畏的狼煙.html | H76: =IF(A76="","", "https://www.ssbuy.tw/detail_giftcode/dist/gamedetail/" & IF(ISNUMBER(LEFT(A76,1)*1), "game-", "") & A76 & ".html") -> https://www.ssbuy.tw/detail_giftcode/dist/gamedetail/無畏的狼煙.html | I76: 《無畏的狼煙》（Fearless Signals）是一款2D放置卡牌遊戲，以歐美潮流塗鴉風格呈現魔幻世界觀。 遊戲中，玩家將扮演領主，率領各族英雄與邪惡勢力作戰，重建大陸，擊退黑暗女神的入侵。 | J76: 6480鑽石 | K76: 2551 | L76: 3280鑽石 | M76: 1323 | N76: 1980鑽石 | O76: 786 | P76: 1280鑽石 | Q76: 539 | R76: 680鑽石 | S76: 267 | T76: 340鑽石 | U76: 137 | V76: 60鑽石 | W76: 35
A77: 代號：無頭 | F77: =IF(A77="","", "https://www.ssbuy.tw/detail_giftcode/dist/giftcodes/" & IF(ISNUMBER(LEFT(A77,1)*1), "game-", "") & A77 & ".html") -> https://www.ssbuy.tw/detail_giftcode/dist/giftcodes/代號：無頭.html | H77: =IF(A77="","", "https://www.ssbuy.tw/detail_giftcode/dist/gamedetail/" & IF(ISNUMBER(LEFT(A77,1)*1), "game-", "") & A77 & ".html") -> https://www.ssbuy.tw/detail_giftcode/dist/gamedetail/代號：無頭.html | I77: 《代號：無頭》是由HZ Game 代理發行的角色扮演遊戲。 這款遊戲將您帶入前所未有的奇幻冒險，成為失去頭顱的魔王，與S級女性角色後援團攜手啟程。 遊戲巧妙融合多元副本挑戰、全球玩家對戰和自動戰鬥系統，帶給您極致的遊戲樂趣。 | J77: 10080鑽石 | K77: 2551 | L77: 4620鑽石 | M77: 1323 | N77: 1660鑽石 | O77: 539 | P77: 820鑽石 | Q77: 267 | R77: 340鑽石 | S77: 137 | T77: 60鑽石 | U77: 30
A78: 牛頭人GO | F78: =IF(A78="","", "https://www.ssbuy.tw/detail_giftcode/dist/giftcodes/" & IF(ISNUMBER(LEFT(A78,1)*1), "game-", "") & A78 & ".html") -> https://www.ssbuy.tw/detail_giftcode/dist/giftcodes/牛頭人GO.html | H78: =IF(A78="","", "https://www.ssbuy.tw/detail_giftcode/dist/gamedetail/" & IF(ISNUMBER(LEFT(A78,1)*1), "game-", "") & A78 & ".html") -> https://www.ssbuy.tw/detail_giftcode/dist/gamedetail/牛頭人GO.html | I78: 《牛頭人GO》是一款由娜瓦遊戲股份有限公司推出的mini英雄進化消除塔防手遊。 玩家將扮演流放者，率領以牛頭人为首的英雄們，與各界域的魔獸戰鬥。 遊戲特色是「消除」和「塔防」的結合，玩家透過消除相同英雄來進化角色，提升實力，抵禦敵人的進攻。 | J78: 3290禮包 | K78: 2551 | L78: 1690禮包 | M78: 1323 | N78: 660禮包 | O78: 539 | P78: 330禮包 | Q78: 267 | R78: 170禮包 | S78: 137 | T78: 100禮包 | U78: 90 | V78: 33禮包 | W78: 35
A79: 派對吧三國 | F79: =IF(A79="","", "https://www.ssbuy.tw/detail_giftcode/dist/giftcodes/" & IF(ISNUMBER(LEFT(A79,1)*1), "game-", "") & A79 & ".html") -> https://www.ssbuy.tw/detail_giftcode/dist/giftcodes/派對吧三國.html | H79: =IF(A79="","", "https://www.ssbuy.tw/detail_giftcode/dist/gamedetail/" & IF(ISNUMBER(LEFT(A79,1)*1), "game-", "") & A79 & ".html") -> https://www.ssbuy.tw/detail_giftcode/dist/gamedetail/派對吧三國.html | I79: 《派對吧三國》——上線送1000抽穿越時空的派對，三國化作派對不夜城，帶你進入一個充滿霓虹燈與奇跡的三國世界！ 告別傳統，迎接派對風格的三國世界！ 在霓虹燈下的戰鬥中，幻想的加持讓每位名將展現出前所未有的魅力。 每一次戰鬥都是一場視覺和節奏的盛宴，讓你體驗一個與眾不同的三國戰場。 | J79: 9999通寶 | K79: 2551 | L79: 6999通寶 | M79: 1960 | N79: 4999通寶 | O79: 1323 | P79: 2999通寶 | Q79: 786 | R79: 1999通寶 | S79: 539 | T79: 1499通寶 | U79: 394 | V79: 999通寶 | W79: 267 | X79: 899通寶 | Y79: 260 | Z79: 499通寶 | AA79: 137 | AB79: 299通寶 | AC79: 90 | AD79: 199通寶 | AE79: 60 | AF79: 99通寶 | AG79: 35
A80: 酒酒大俠 | F80: =IF(A80="","", "https://www.ssbuy.tw/detail_giftcode/dist/giftcodes/" & IF(ISNUMBER(LEFT(A80,1)*1), "game-", "") & A80 & ".html") -> https://www.ssbuy.tw/detail_giftcode/dist/giftcodes/酒酒大俠.html | H80: =IF(A80="","", "https://www.ssbuy.tw/detail_giftcode/dist/gamedetail/" & IF(ISNUMBER(LEFT(A80,1)*1), "game-", "") & A80 & ".html") -> https://www.ssbuy.tw/detail_giftcode/dist/gamedetail/酒酒大俠.html | I80: 《酒酒大俠》是一款由HK FOREVER99 TECHNOLOGY CO., LIMITED開發的角色扮演遊戲。 遊戲以武俠世界為背景，玩家可以體驗如小說般的沉浸劇情，重現武林恩怨情仇，挑戰各門派秘境，並揭開隱藏的江湖秘密，在遊戲中成為主角，引領主線劇情發展，參與武俠世界的各種冒險。 | J80: 6480元寶 | K80: 2551 | L80: 3280元寶 | M80: 1323 | N80: 1980元寶 | O80: 786 | P80: 980元寶 | Q80: 394 | R80: 680元寶 | S80: 267 | T80: 300元寶 | U80: 137 | V80: 60元寶 | W80: 35
A81: 鼠衛家園 | F81: =IF(A81="","", "https://www.ssbuy.tw/detail_giftcode/dist/giftcodes/" & IF(ISNUMBER(LEFT(A81,1)*1), "game-", "") & A81 & ".html") -> https://www.ssbuy.tw/detail_giftcode/dist/giftcodes/鼠衛家園.html | H81: =IF(A81="","", "https://www.ssbuy.tw/detail_giftcode/dist/gamedetail/" & IF(ISNUMBER(LEFT(A81,1)*1), "game-", "") & A81 & ".html") -> https://www.ssbuy.tw/detail_giftcode/dist/gamedetail/鼠衛家園.html | I81: 《鼠衛家園》是一款結合了塔防和Roguelike 元素的行動遊戲，玩家將化身為鼠鼠英雄，守護家園並抵抗來自各方的怪物攻擊。 遊戲玩法強調策略佈置和英雄搭配，玩家需要根據怪物的進攻路線，靈活安排防禦塔和英雄位置，增加防守效率。 | J81: 6480寶石 | K81: 2551 | L81: 3280寶石 | M81: 1280 | N81: 1280寶石 | O81: 539 | P81: 680寶石 | Q81: 267 | R81: 300寶石 | S81: 137
A82: 未頌者之歌：異世界冒險奇譚 | F82: =IF(A82="","", "https://www.ssbuy.tw/detail_giftcode/dist/giftcodes/" & IF(ISNUMBER(LEFT(A82,1)*1), "game-", "") & A82 & ".html") -> https://www.ssbuy.tw/detail_giftcode/dist/giftcodes/未頌者之歌：異世界冒險奇譚.html | H82: =IF(A82="","", "https://www.ssbuy.tw/detail_giftcode/dist/gamedetail/" & IF(ISNUMBER(LEFT(A82,1)*1), "game-", "") & A82 & ".html") -> https://www.ssbuy.tw/detail_giftcode/dist/gamedetail/未頌者之歌：異世界冒險奇譚.html | I82: 在陷入不斷毀滅與重生輪迴的九界之中，你將化身女武神瓦爾基里，集結未被歌頌的英雄們，於命運洪流中穿越迷霧，追尋破碎神話背後的真相，譜寫抗爭與希望的頌歌，踏上拯救九界眾生的史詩旅程。 | J82: 6480鑽石 | K82: 2551 | L82: 3280鑽石 | M82: 1323 | N82: 1280鑽石 | O82: 539 | P82: 680鑽石 | Q82: 267 | R82: 300鑽石 | S82: 137 | T82: 60鑽石 | U82: 35
A83: 熱練戰士 | F83: =IF(A83="","", "https://www.ssbuy.tw/detail_giftcode/dist/giftcodes/" & IF(ISNUMBER(LEFT(A83,1)*1), "game-", "") & A83 & ".html") -> https://www.ssbuy.tw/detail_giftcode/dist/giftcodes/熱練戰士.html | H83: =IF(A83="","", "https://www.ssbuy.tw/detail_giftcode/dist/gamedetail/" & IF(ISNUMBER(LEFT(A83,1)*1), "game-", "") & A83 & ".html") -> https://www.ssbuy.tw/detail_giftcode/dist/gamedetail/熱練戰士.html | I83: 《熱練戰士》是任何人都可以輕鬆享受的2D 動作角色扮演類遊戲，和各種吸引人的英雄在清醒夢大冒險的世界背景下進行愉快的冒險。 以四個遊戲角色來組建起屬於自己的隊伍，擊退一波又一波的怪物後完成遊戲劇情。 除主線故事外，還可以在噩夢入侵、PVP 競技場、地下副本、神的遺物等模式中感受樂趣。 | J83: 1300紅寶石 | K83: 2590 | L83: 350紅寶石 | M83: 740 | N83: 65紅寶石 | O83: 137
A84: 聯盟戰棋 | F84: =IF(A84="","", "https://www.ssbuy.tw/detail_giftcode/dist/giftcodes/" & IF(ISNUMBER(LEFT(A84,1)*1), "game-", "") & A84 & ".html") -> https://www.ssbuy.tw/detail_giftcode/dist/giftcodes/聯盟戰棋.html | H84: =IF(A84="","", "https://www.ssbuy.tw/detail_giftcode/dist/gamedetail/" & IF(ISNUMBER(LEFT(A84,1)*1), "game-", "") & A84 & ".html") -> https://www.ssbuy.tw/detail_giftcode/dist/gamedetail/聯盟戰棋.html | I84: 《聯盟戰棋》（或稱《雲頂之弈》）是由Riot Games 開發的自走棋類電子遊戲，建立在《英雄聯盟》的世界觀之上。 玩家與七名對手競爭，在回合制的戰鬥中組建隊伍，最終爭奪勝利。 遊戲玩法與《刀塔自走棋》類似，玩家從輪流出現的《英雄聯盟》角色中招募棋子，佈置棋位，並在戰鬥中與對手戰鬥。 | J84: 11525戰棋幣 | K84: 2430 | L84: 5750戰棋幣 | M84: 1220 | N84: 4025戰棋幣 | O84: 850 | P84: 2525戰棋幣 | Q84: 539 | R84: 1275戰棋幣 | S84: 270 | T84: 575戰棋幣 | U84: 137
A85: 劍客物語 | F85: =IF(A85="","", "https://www.ssbuy.tw/detail_giftcode/dist/giftcodes/" & IF(ISNUMBER(LEFT(A85,1)*1), "game-", "") & A85 & ".html") -> https://www.ssbuy.tw/detail_giftcode/dist/giftcodes/劍客物語.html | H85: =IF(A85="","", "https://www.ssbuy.tw/detail_giftcode/dist/gamedetail/" & IF(ISNUMBER(LEFT(A85,1)*1), "game-", "") & A85 & ".html") -> https://www.ssbuy.tw/detail_giftcode/dist/gamedetail/劍客物語.html | I85: 《劍客物語》是一款由SuperPlanet代理的角色扮演遊戲，屬於動作RPG類型，以「該隱」這個平凡學生穿越到異世界後，成為大劍客，與神話英雄組隊，一起冒險和戰鬥，並揭開隱藏的真相為故事核心。 遊戲特色包括華麗技能、高速連擊、二刀流戰鬥系統、裝備強化、角色成長系統、公會合作以及獨特的故事和冒險模式。 | J85: 9000紅寶石 | K85: 2551 | L85: 4500紅寶石 | M85: 1300 | N85: 2700紅寶石 | O85: 786 | P85: 9000紅寶石 | Q85: 270 | R85: 450紅寶石 | S85: 137 | T85: 270紅寶石 | U85: 90
A86: 人在塔在 | F86: =IF(A86="","", "https://www.ssbuy.tw/detail_giftcode/dist/giftcodes/" & IF(ISNUMBER(LEFT(A86,1)*1), "game-", "") & A86 & ".html") -> https://www.ssbuy.tw/detail_giftcode/dist/giftcodes/人在塔在.html | H86: =IF(A86="","", "https://www.ssbuy.tw/detail_giftcode/dist/gamedetail/" & IF(ISNUMBER(LEFT(A86,1)*1), "game-", "") & A86 & ".html") -> https://www.ssbuy.tw/detail_giftcode/dist/gamedetail/人在塔在.html | I86: 對抗無情的敵人：野蠻的獸人、高聳的巨魔、邪惡的死靈法師、惡魔大軍以及各種史詩級首領。每個敵人都帶來新的挑戰和獨特的戰鬥能力，為這個類型增添了新維度！召喚強大的援軍，指揮你的弓箭手，釋放毀滅性的技能，並通過遊戲內選項升級你的弓箭手和塔樓，以保護王國免受黑暗的侵害！ | J86: 14000鑽石 | K86: 2551 | L86: 6500鑽石 | M86: 1390 | N86: 2500鑽石 | O86: 539 | P86: 1200鑽石 | Q86: 267 | R86: 500鑽石 | S86: 137 | T86: 80鑽石 | U86: 40
A87: 龍語霜城 | F87: =IF(A87="","", "https://www.ssbuy.tw/detail_giftcode/dist/giftcodes/" & IF(ISNUMBER(LEFT(A87,1)*1), "game-", "") & A87 & ".html") -> https://www.ssbuy.tw/detail_giftcode/dist/giftcodes/龍語霜城.html | H87: =IF(A87="","", "https://www.ssbuy.tw/detail_giftcode/dist/gamedetail/" & IF(ISNUMBER(LEFT(A87,1)*1), "game-", "") & A87 & ".html") -> https://www.ssbuy.tw/detail_giftcode/dist/gamedetail/龍語霜城.html | I87: 《龍語霜城-元素魔域》是由純白之境發行的西方魔幻題材三消策略手機遊戲，於2023年12月7日正式上線。 遊戲將魔幻大世界與三消策略玩法融合，玩家可以在冰天雪地中冒險，喚醒巨龍，拯救被冰封的家園。 | J87: 30000鑽石 | K87: 2551 | L87: 14000鑽石 | M87: 1323 | N87: 11000鑽石 | O87: 1100 | P87: 8000鑽石 | Q87: 820 | R87: 5200鑽石 | S87: 539 | T87: 3800鑽石 | U87: 420 | V87: 2400鑽石 | W87: 320 | X87: 1100鑽石 | Y87: 180
A88: 洛伊的移動要塞 | F88: =IF(A88="","", "https://www.ssbuy.tw/detail_giftcode/dist/giftcodes/" & IF(ISNUMBER(LEFT(A88,1)*1), "game-", "") & A88 & ".html") -> https://www.ssbuy.tw/detail_giftcode/dist/giftcodes/洛伊的移動要塞.html | H88: =IF(A88="","", "https://www.ssbuy.tw/detail_giftcode/dist/gamedetail/" & IF(ISNUMBER(LEFT(A88,1)*1), "game-", "") & A88 & ".html") -> https://www.ssbuy.tw/detail_giftcode/dist/gamedetail/洛伊的移動要塞.html | I88: 《洛伊的移動要塞》是韓國開發商Cookapps推出的放置型城堡養成遊戲。 在一個魔王肆虐的世界裡，英雄們利用世界樹的力量對抗邪惡。 玩家將扮演這些英雄，利用世界樹的種子來建造並培養自己的移動城堡。 | J88: 2990禮包 | K88: 2551 | L88: 2490禮包 | M88: 2150 | N88: 2290禮包 | O88: 2000 | P88: 1990禮包 | Q88: 1700 | R88: 1490禮包 | S88: 1323 | T88: 1290禮包 | U88: 1100 | V88: 990禮包 | W88: 786 | X88: 790禮包 | Y88: 700 | Z88: 690禮包 | AA88: 620 | AB88: 525禮包 | AC88: 490 | AD88: 490禮包 | AE88: 450 | AF88: 320禮包 | AG88: 267 | AH88: 190禮包 | AI88: 180 | AJ88: 150禮包 | AK88: 137
A89: 喵喵王國 | F89: =IF(A89="","", "https://www.ssbuy.tw/detail_giftcode/dist/giftcodes/" & IF(ISNUMBER(LEFT(A89,1)*1), "game-", "") & A89 & ".html") -> https://www.ssbuy.tw/detail_giftcode/dist/giftcodes/喵喵王國.html | H89: =IF(A89="","", "https://www.ssbuy.tw/detail_giftcode/dist/gamedetail/" & IF(ISNUMBER(LEFT(A89,1)*1), "game-", "") & A89 & ".html") -> https://www.ssbuy.tw/detail_giftcode/dist/gamedetail/喵喵王國.html | I89: 《喵喵王國：貓咪放置rpg》的大體玩法結構為，家園養成+放置對戰，家園養成方面，就是透過放置設施與可愛的貓咪，產出各種道具來培養貓咪（當然也可以只是為了好看養眼），其中你還可以培養貓咪們的好感度，好感度的提升對戰鬥有所加成。 | J89: 13500寶石 | K89: 2300 | L89: 6800寶石 | M89: 1150 | N89: 3500寶石 | O89: 650 | P89: 1500寶石 | Q89: 267 | R89: 620寶石 | S89: 120 | T89: 150寶石 | U89: 30
A90: 東京謎影者 | F90: =IF(A90="","", "https://www.ssbuy.tw/detail_giftcode/dist/giftcodes/" & IF(ISNUMBER(LEFT(A90,1)*1), "game-", "") & A90 & ".html") -> https://www.ssbuy.tw/detail_giftcode/dist/giftcodes/東京謎影者.html | H90: =IF(A90="","", "https://www.ssbuy.tw/detail_giftcode/dist/gamedetail/" & IF(ISNUMBER(LEFT(A90,1)*1), "game-", "") & A90 & ".html") -> https://www.ssbuy.tw/detail_giftcode/dist/gamedetail/東京謎影者.html | I90: 遊戲故事以Live2D 與漫畫交織展開，講述女主角因被怪異襲擊，遇見將自身出賣給惡魔的「噬魔人」，並被帶至「黑蕊學園」。 在這裡被宣告壽命只剩一年的女主角，為了解開詛咒，將與噬魔人一同調查潛藏於東京市區的怪異事件。 | J90: 5000鑽石 | K90: 2700 | L90: 2100鑽石 | M90: 1100 | N90: 1100鑽石 | O90: 539 | P90: 500鑽石 | Q90: 267 | R90: 325鑽石 | S90: 200 | T90: 80鑽石 | U90: 60
A91: 戰極死遊 | F91: =IF(A91="","", "https://www.ssbuy.tw/detail_giftcode/dist/giftcodes/" & IF(ISNUMBER(LEFT(A91,1)*1), "game-", "") & A91 & ".html") -> https://www.ssbuy.tw/detail_giftcode/dist/giftcodes/戰極死遊.html | H91: =IF(A91="","", "https://www.ssbuy.tw/detail_giftcode/dist/gamedetail/" & IF(ISNUMBER(LEFT(A91,1)*1), "game-", "") & A91 & ".html") -> https://www.ssbuy.tw/detail_giftcode/dist/gamedetail/戰極死遊.html | I91: 時間來到20XX年。主宰著新東京國、臉戴面具的謎樣男子「ZERO」宣布，在全國的城市裡「所有事情將以遊戲來做定奪」。自此他便透過「戰極遊戲（Extreme Games）」，通稱「XG」 來統治新東京。 | J91: 4955神秘粒子結晶 | K91: 1900 | L91: 2793神秘粒子結晶 | M91: 1050 | N91: 1396神秘粒子結晶 | O91: 540 | P91: 486神秘粒子結晶 | Q91: 190 | R91: 207神秘粒子結晶 | S91: 90 | T91: 68神秘粒子結晶 | U91: 35
A92: 進擊的蝸牛 | F92: =IF(A92="","", "https://www.ssbuy.tw/detail_giftcode/dist/giftcodes/" & IF(ISNUMBER(LEFT(A92,1)*1), "game-", "") & A92 & ".html") -> https://www.ssbuy.tw/detail_giftcode/dist/giftcodes/進擊的蝸牛.html | H92: =IF(A92="","", "https://www.ssbuy.tw/detail_giftcode/dist/gamedetail/" & IF(ISNUMBER(LEFT(A92,1)*1), "game-", "") & A92 & ".html") -> https://www.ssbuy.tw/detail_giftcode/dist/gamedetail/進擊的蝸牛.html | I92: 《進擊的蝸牛》是一款放置類手遊，玩家可以輕鬆進行強化和升級，即使在工作或閒暇時也能享受遊戲樂趣。 遊戲中，玩家可以和夥伴一起探索、爬塔，進行自由遠征。 | J92: 3290彩鑽 | K92: 2551 | L92: 1690彩鑽 | M92: 1323 | N92: 670彩鑽 | O92: 539 | P92: 330彩鑽 | Q92: 267 | R92: 170彩鑽 | S92: 137 | T92: 33彩鑽 | U92: 40
A93: 純白大作戰 | F93: =IF(A93="","", "https://www.ssbuy.tw/detail_giftcode/dist/giftcodes/" & IF(ISNUMBER(LEFT(A93,1)*1), "game-", "") & A93 & ".html") -> https://www.ssbuy.tw/detail_giftcode/dist/giftcodes/純白大作戰.html | H93: =IF(A93="","", "https://www.ssbuy.tw/detail_giftcode/dist/gamedetail/" & IF(ISNUMBER(LEFT(A93,1)*1), "game-", "") & A93 & ".html") -> https://www.ssbuy.tw/detail_giftcode/dist/gamedetail/純白大作戰.html | I93: 本作強調二次元動漫畫風的人物立繪和流暢的動畫表現，玩家將能遇到眾多風格迥異的美少女角色，每一位都擁有獨特而絢麗的技能。 同時將輕鬆的放置玩法與多變的策略相結合。 玩家可以在最小投入下享受遊戲進程，透過精心策劃的策略來克服挑戰。 《純白大作戰》現已開啟預先註冊。 | J93: 668寶石 | K93: 2551 | L93: 328寶石 | M93: 1323 | N93: 198寶石 | O93: 786 | P93: 98寶石 | Q93: 450 | R93: 30寶石 | S93: 137 | T93: 60寶石 | U93: 60
A94: 黑星勇者 | F94: =IF(A94="","", "https://www.ssbuy.tw/detail_giftcode/dist/giftcodes/" & IF(ISNUMBER(LEFT(A94,1)*1), "game-", "") & A94 & ".html") -> https://www.ssbuy.tw/detail_giftcode/dist/giftcodes/黑星勇者.html | H94: =IF(A94="","", "https://www.ssbuy.tw/detail_giftcode/dist/gamedetail/" & IF(ISNUMBER(LEFT(A94,1)*1), "game-", "") & A94 & ".html") -> https://www.ssbuy.tw/detail_giftcode/dist/gamedetail/黑星勇者.html | I94: 黑星勇者是一款象素風格的超自由ＲＰＧ手遊，他與手遊伊洛納製作團隊是同一個，也因此在許多地方是相似或熟悉的。 雖然遊戲是傳統的勇者地下城ＲＰＧ模式，但是他也有許多家園生產體系。 不過最為經典重要的是它是一款養成非常自由的手遊。 | J94: 6480鑽石 | K94: 2551 | L94: 3880鑽石 | M94: 1323 | N94: 1280鑽石 | O94: 630 | P94: 680鑽石 | Q94: 267 | R94: 300鑽石 | S94: 137 | T94: 60鑽石 | U94: 40
A95: 龍之谷：經典再現 | F95: =IF(A95="","", "https://www.ssbuy.tw/detail_giftcode/dist/giftcodes/" & IF(ISNUMBER(LEFT(A95,1)*1), "game-", "") & A95 & ".html") -> https://www.ssbuy.tw/detail_giftcode/dist/giftcodes/龍之谷：經典再現.html | H95: =IF(A95="","", "https://www.ssbuy.tw/detail_giftcode/dist/gamedetail/" & IF(ISNUMBER(LEFT(A95,1)*1), "game-", "") & A95 & ".html") -> https://www.ssbuy.tw/detail_giftcode/dist/gamedetail/龍之谷：經典再現.html | I95: 《龍之谷：經典再現》是韓國原廠正版授權，復刻經典的龍之谷遊戲。 這款遊戲以其精緻的畫風、豐富的職業系統、獨特的遊戲機制以及多樣的內容，讓玩家重溫經典的遊戲體驗。 遊戲中，玩家可以扮演不同的職業，例如牧師，體驗不同角色的獨特魅力與戰鬥風格。 | J95: 60000龍券 | K95: 2551 | L95: 30000龍券 | M95: 1323 | N95: 18000龍券 | O95: 990 | P95: 12000龍券 | Q95: 540 | R95: 6000龍券 | S95: 270 | T95: 3000龍券 | U95: 137 | V95: 600龍券 | W95: 40
A96: 楓之谷Artale | F96: =IF(A96="","", "https://www.ssbuy.tw/detail_giftcode/dist/giftcodes/" & IF(ISNUMBER(LEFT(A96,1)*1), "game-", "") & A96 & ".html") -> https://www.ssbuy.tw/detail_giftcode/dist/giftcodes/楓之谷Artale.html | H96: =IF(A96="","", "https://www.ssbuy.tw/detail_giftcode/dist/gamedetail/" & IF(ISNUMBER(LEFT(A96,1)*1), "game-", "") & A96 & ".html") -> https://www.ssbuy.tw/detail_giftcode/dist/gamedetail/楓之谷Artale.html | I96: Artale 繁體中文版的懷舊版本其遊戲系統MapleStory Worlds 是Nexon 在2022 年年底推出的一款玩家跟開發者能夠自由運用數千萬個楓之谷物件製作遊戲進行遊戲的一個平台，因此吸引了創作者們開始建立最初楓之谷的設定，打造了這款名為《Artale懷舊楓之谷》的版本 | J96: 13200金幣 | K96: 1580
A97: 出發吧麥芬 | F97: =IF(A97="","", "https://www.ssbuy.tw/detail_giftcode/dist/giftcodes/" & IF(ISNUMBER(LEFT(A97,1)*1), "game-", "") & A97 & ".html") -> https://www.ssbuy.tw/detail_giftcode/dist/giftcodes/出發吧麥芬.html | H97: =IF(A97="","", "https://www.ssbuy.tw/detail_giftcode/dist/gamedetail/" & IF(ISNUMBER(LEFT(A97,1)*1), "game-", "") & A97 & ".html") -> https://www.ssbuy.tw/detail_giftcode/dist/gamedetail/出發吧麥芬.html | I97: 《出發吧麥芬》讓你整天可可愛愛掛機就能成長領被動收入。 只需在空閒時進入遊戲，查看行囊裡多了什麼新裝備，摸頭並餵食一下麥樂獸，就能使其變強大。 當然在駕車兜風途中的Q萌百景、奇珍異獸、帥氣BOSS，也是讓眾多冒險家流連忘返的！ | J97: 6480星鑽 | K97: 2390 | L97: 3280星鑽 | M97: 1380 | N97: 1980星鑽 | O97: 810 | P97: 980星鑽 | Q97: 410 | R97: 300星鑽 | S97: 270 | T97: 60星鑽 | U97: 40
A98: RO仙境傳說：守護永恆的愛 Classic | F98: =IF(A98="","", "https://www.ssbuy.tw/detail_giftcode/dist/giftcodes/" & IF(ISNUMBER(LEFT(A98,1)*1), "game-", "") & A98 & ".html") -> https://www.ssbuy.tw/detail_giftcode/dist/giftcodes/RO仙境傳說：守護永恆的愛 Classic.html | H98: =IF(A98="","", "https://www.ssbuy.tw/detail_giftcode/dist/gamedetail/" & IF(ISNUMBER(LEFT(A98,1)*1), "game-", "") & A98 & ".html") -> https://www.ssbuy.tw/detail_giftcode/dist/gamedetail/RO仙境傳說：守護永恆的愛 Classic.html | I98: 《RO仙境傳說：守護永恆的愛Classic》是RO守愛的返璞歸真版本。 在這裡沒有商城、沒有抽卡要素、沒有各種儲值貨幣，只有擊敗怪物就可掉落的單一貨幣「Zeny」。 在這裡只有大家熟悉的RO六大基礎職業：劍士、魔法師、盜賊、弓箭手、服事、商人。 | J98: 6480萬zeny | K98: 2320 | L98: 3280萬zeny | M98: 1330 | N98: 1280萬zeny | O98: 520 | P98: 680萬zeny | Q98: 267 | R98: 300萬zeny | S98: 137 | T98: 180萬zeny | U98: 90
A99: 魔力寶貝：復興 | F99: =IF(A99="","", "https://www.ssbuy.tw/detail_giftcode/dist/giftcodes/" & IF(ISNUMBER(LEFT(A99,1)*1), "game-", "") & A99 & ".html") -> https://www.ssbuy.tw/detail_giftcode/dist/giftcodes/魔力寶貝：復興.html | H99: =IF(A99="","", "https://www.ssbuy.tw/detail_giftcode/dist/gamedetail/" & IF(ISNUMBER(LEFT(A99,1)*1), "game-", "") & A99 & ".html") -> https://www.ssbuy.tw/detail_giftcode/dist/gamedetail/魔力寶貝：復興.html | I99: 《魔力寶貝：復興》是一款由 SQUARE ENIX 正版授權GNN 新聞網 的手機遊戲，它採用了3D引擎提升畫面，同時保留了《魔力寶貝》系列的45度角戰鬥畫面。 遊戲保留了《魔力寶貝》的經典元素，讓玩家體驗橫跨24年IP的魅力，並提供多樣化的寵物培養系統，讓玩家可以培養心儀的寵物。 | J99: 6480鑽石 | K99: 2290 | L99: 4880鑽石 | M99: 2000 | N99: 2980鑽石 | O99: 1150 | P99: 1980鑽石 | Q99: 786 | R99: 980鑽石 | S99: 450 | T99: 500鑽石 | U99: 260 | V99: 300鑽石 | W99: 137 | X99: 60鑽石 | Y99: 50
A100: 東京喰種Awakening | F100: =IF(A100="","", "https://www.ssbuy.tw/detail_giftcode/dist/giftcodes/" & IF(ISNUMBER(LEFT(A100,1)*1), "game-", "") & A100 & ".html") -> https://www.ssbuy.tw/detail_giftcode/dist/giftcodes/東京喰種Awakening.html | H100: =IF(A100="","", "https://www.ssbuy.tw/detail_giftcode/dist/gamedetail/" & IF(ISNUMBER(LEFT(A100,1)*1), "game-", "") & A100 & ".html") -> https://www.ssbuy.tw/detail_giftcode/dist/gamedetail/東京喰種Awakening.html | I100: 《東京喰種：Awakening》手遊官網 是一名喜愛讀書、就讀于上井大學的學生。 因移植了“喰種” 利世的部分器官，身體成為了“喰種” ，被迫在“喰種” 的世界中生存。 雖身處絕望的深淵，但在與性格和境遇迥異的“喰種” 相處過程中，他的意識逐漸發生了改變，想要斬斷這個世界悲哀的連鎖。 | J100: 8000鑽石 | K100: 2551 | L100: 4000鑽石 | M100: 1370 | N100: 2000鑽石 | O100: 740 | P100: 1200鑽石 | Q100: 394 | R100: 400鑽石 | S100: 137 | T100: 80鑽石 | U100: 40
...

Sheet gift_codes
A1: 遊戲名稱 | B1: 橫幅圖片 | C1: 橫幅圖片檔名 | D1: canonical_url | E1: 介紹 | F1: 兌換方式1 | G1: 兌換方式3 | H1: 兌換方式4 | I1: 兌換方式5 | J1: 兌換方式6 | K1: 禮包碼1 | L1: 內容物1 | M1: 禮包碼2 | N1: 內容物2 | O1: 禮包碼3 | P1: 內容物3 | Q1: 禮包碼4 | R1: 內容物4 | S1: 禮包碼5 | T1: 內容物5 | U1: 禮包碼6 | V1: 內容物6 | W1: 禮包碼7 | X1: 內容物7 | Y1: 禮包碼8 | Z1: 內容物8 | AA1: 禮包碼9 | AB1: 內容物9 | AC1: 禮包碼10 | AD1: 內容物10 | AE1: 禮包碼11 | AF1: 內容物11 | AG1: 禮包碼12 | AH1: 內容物12 | AI1: 禮包碼13 | AJ1: 內容物13 | AK1: 禮包碼14 | AL1: 內容物14 | AM1: 禮包碼15 | AN1: 內容物15 | AO1: 禮包碼16 | AP1: 內容物16 | AQ1: 禮包碼17 | AR1: 內容物17 | AS1: 禮包碼18 | AT1: 內容物18 | AU1: 禮包碼19 | AV1: 內容物19 | AW1: 禮包碼20 | AX1: 內容物20 | AY1: 禮包碼21 | AZ1: 內容物21 | BA1: 禮包碼22 | BB1: 內容物22 | BC1: 禮包碼23 | BD1: 內容物23 | BE1: 禮包碼24 | BF1: 內容物24 | BG1: 禮包碼25 | BH1: 內容物25 | BI1: 禮包碼26 | BJ1: 內容物26 | BK1: 禮包碼27 | BL1: 內容物27 | BM1: 禮包碼28 | BN1: 內容物28 | BO1: 禮包碼29 | BP1: 內容物29 | BQ1: 禮包碼30 | BR1: 內容物30
A2: 巔峰極速 | B2: ="giftcodesbanner/" & A2 & "-bar.jpg" -> giftcodesbanner/巔峰極速-bar.jpg | D2: =IF(A2="","", "https://www.ssbuy.tw/detail_giftcode/dist/giftcodes/" & IF(ISNUMBER(LEFT(A2,1)*1), "game-", "") & A2 & ".html") -> https://www.ssbuy.tw/detail_giftcode/dist/giftcodes/巔峰極速.html | E2: 《巔峰極速》是與Codemasters®深度合作, 3A級巔峰品質擬真競速遊戲。 玩家可以自由收集、改裝超過100款正版授權的豪華車輛，馳騁在全世界的街道與專業賽道上，感受極致光影與真實轟鳴聲帶來的沉浸體驗，更擁有豐富的競速玩法，立即加入與其他玩家進行即時競速對決，突破賽車的速度極限！ | F2: 進入主畫面，點選個人頭像 | G2: 進入設定（齒輪） | H2: 輸入禮包碼 → 確認兌換 | K2: 10000racers | L2: 2025商城元寶鑽石禮包 | M2: VIP777 | N2: 2025商城元寶鑽石禮包 | O2: VIP888 | P2: 2025商城元寶鑽石禮包 | Q2: KINGO1019 | R2: 2025商城元寶鑽石禮包 | S2: BEBE888 | T2: 2025商城元寶鑽石禮包 | U2: TEAMRACE666 | V2: 2025商城元寶鑽石禮包 | W2: RACING777 | X2: 2025商城元寶鑽石禮包 | Y2: POST00 | Z2: 2025商城元寶鑽石禮包 | AA2: RACING888 | AB2: 2025商城元寶鑽石禮包 | AC2: NEAL888 | AD2: 2025商城元寶鑽石禮包 | AE2: RKUI666 | AF2: 2025商城元寶鑽石禮包 | AG2: LETSGO168 | AH2: 2025商城元寶鑽石禮包 | AI2: DRIVER666 | AJ2: 2025商城元寶鑽石禮包 | AK2: MASTER777 | AL2: 2025商城元寶鑽石禮包 | AM2: AHHINS | AN2: 2025商城元寶鑽石禮包 | AO2: RACING666 | AP2: 2025商城元寶鑽石禮包 | AQ2: WINWIN888 | AR2: 2025商城元寶鑽石禮包 | AS2: GOGORACING | AT2: 2025商城元寶鑽石禮包 | AU2: GG1019 | AV2: 2025商城元寶鑽石禮包
A3: 原神 | B3: ="giftcodesbanner/" & A3 & "-bar.jpg" -> giftcodesbanner/原神-bar.jpg | D3: =IF(A3="","", "https://www.ssbuy.tw/detail_giftcode/dist/giftcodes/" & IF(ISNUMBER(LEFT(A3,1)*1), "game-", "") & A3 & ".html") -> https://www.ssbuy.tw/detail_giftcode/dist/giftcodes/原神.html | E3: 原神，啟動! | F3: 進入主畫面，點選個人頭像 | G3: 進入設定（齒輪） | H3: 輸入禮包碼 → 確認兌換 | K3: GS57YTSNLJ | L3: 原神素材兌換專用 | M3: LWKC638ULB16 | N3: 摩拉 x10,000、冒險家的經驗 x10、精鍛用雜礦 x5、香嫩椒椒雞 x5、乾炒魚河 x5 | O3: ZT5RJ4AX4WYV | P3: 原石 x60、冒險家的經驗 x5 | Q3: GenshinGIFT | R3: 原石 x50、大英雄的經驗 x3
A4: 極速快感 | B4: ="giftcodesbanner/" & A4 & "-bar.jpg" -> giftcodesbanner/極速快感-bar.jpg | D4: =IF(A4="","", "https://www.ssbuy.tw/detail_giftcode/dist/giftcodes/" & IF(ISNUMBER(LEFT(A4,1)*1), "game-", "") & A4 & ".html") -> https://www.ssbuy.tw/detail_giftcode/dist/giftcodes/極速快感.html | F4: 進入主畫面，點選個人頭像 | G4: 進入設定（齒輪） | H4: 輸入禮包碼 → 確認兌換 | K4: 極速快感集結666 | L4: 100鑽石、500熱彎幣 | M4: 極速快感沖刺測試 | N4: 50鑽石、300熱彎幣 | O4: NFSM7EUV49 | P4: 2025商城元寶鑽石禮包 | Q4: NEEDFORSPEEDNOX | R4: 2025商城元寶鑽石禮包
A5: 俠客傳說：小小英雄 | B5: ="giftcodesbanner/" & A5 & "-bar.jpg" -> giftcodesbanner/俠客傳說：小小英雄-bar.jpg | D5: =IF(A5="","", "https://www.ssbuy.tw/detail_giftcode/dist/giftcodes/" & IF(ISNUMBER(LEFT(A5,1)*1), "game-", "") & A5 & ".html") -> https://www.ssbuy.tw/detail_giftcode/dist/giftcodes/俠客傳說：小小英雄.html | E5: 有你的地方，就有江湖。 | F5: 進入主畫面，點選個人頭像 | G5: 進入設定（齒輪） | H5: 輸入禮包碼 → 確認兌換 | K5: sshero | L5: 2025商城元寶鑽石禮包 | M5: sshero66 | N5: 2025商城元寶鑽石禮包 | O5: tiger666 | P5: 2025商城元寶鑽石禮包 | Q5: tiger777 | R5: 2025商城元寶鑽石禮包 | S5: iu216yrtm4bn | T5: 2025商城元寶鑽石禮包 | U5: 4d9xnyukxwsn | V5: 2025商城元寶鑽石禮包 | W5: x4ixkxaqglaq | X5: 2025商城元寶鑽石禮包 | Y5: zbetdmodzxpj | Z5: 2025商城元寶鑽石禮包 | AA5: fp4rg7gq1g3a | AB5: 2025商城元寶鑽石禮包 | AC5: ox3olzfmkl1d | AD5: 2025商城元寶鑽石禮包 | AE5: ivqjvbqs4r7r | AF5: 2025商城元寶鑽石禮包 | AG5: bx523bo9c678 | AH5: 2025商城元寶鑽石禮包 | AI5: vdpppx11t12n | AJ5: 2025商城元寶鑽石禮包
A6: 逆水寒 | B6: ="giftcodesbanner/" & A6 & "-bar.jpg" -> giftcodesbanner/逆水寒-bar.jpg | D6: =IF(A6="","", "https://www.ssbuy.tw/detail_giftcode/dist/giftcodes/" & IF(ISNUMBER(LEFT(A6,1)*1), "game-", "") & A6 & ".html") -> https://www.ssbuy.tw/detail_giftcode/dist/giftcodes/逆水寒.html | E6: 新武俠大世界冒險RPG《俠客傳說：小小英雄》 | F6: 進入主畫面，點選個人頭像 | G6: 進入設定（齒輪） | H6: 輸入禮包碼 → 確認兌換 | K6: MMOKING | L6: 66綁定紋玉、28,888交子
A7: RO仙境傳說：一定要可愛 | B7: ="giftcodesbanner/" & A7 & "-bar.jpg" -> giftcodesbanner/RO仙境傳說：一定要可愛-bar.jpg | D7: =IF(A7="","", "https://www.ssbuy.tw/detail_giftcode/dist/giftcodes/" & IF(ISNUMBER(LEFT(A7,1)*1), "game-", "") & A7 & ".html") -> https://www.ssbuy.tw/detail_giftcode/dist/giftcodes/RO仙境傳說：一定要可愛.html | E7: 可不可愛？我們說了算！ | F7: 進入主畫面，點選個人頭像 | G7: 進入設定（齒輪） | H7: 輸入禮包碼 → 確認兌換 | K7: BahamutNO1 | L7: 懸賞通緝掃蕩權 × 4 | M7: fanpage3000 | N7: ZENY*30,000 | O7: NOVICE01 | P7: 地城入場補充卷*1 | Q7: SWORDSMAN02 | R7: 地城入場補充卷*1 | S7: BahamutNO1 | T7: 懸賞通緝掃蕩權* 4 | U7: ARCHER03 | V7: 十字搞*2 | W7: ACOLYTE04 | X7: 蜂蜜*5
A8: RO新世代 | B8: ="giftcodesbanner/" & A8 & "-bar.jpg" -> giftcodesbanner/RO新世代-bar.jpg | D8: =IF(A8="","", "https://www.ssbuy.tw/detail_giftcode/dist/giftcodes/" & IF(ISNUMBER(LEFT(A8,1)*1), "game-", "") & A8 & ".html") -> https://www.ssbuy.tw/detail_giftcode/dist/giftcodes/RO新世代.html | E8: 官方正版RO最新作「RO仙境傳説：新世代的誕生」，煥新啓航！不刪檔公測開啟！ | F8: 進入主畫面，點選個人頭像 | G8: 進入設定（齒輪） | H8: 輸入禮包碼 → 確認兌換 | K8: pfyloveroxictop4 | L8: 2025商城元寶鑽石禮包 | M8: ROXIC666J | N8: 2025商城元寶鑽石禮包 | O8: ROXIC636J | P8: 2025商城元寶鑽石禮包 | Q8: ROXIC973J | R8: 2025商城元寶鑽石禮包 | S8: ROXIC562J | T8: 2025商城元寶鑽石禮包 | U8: FPCPAJIE2624 | V8: 2025商城元寶鑽石禮包
A9: 上古：龍神覺醒 | B9: ="giftcodesbanner/" & A9 & "-bar.jpg" -> giftcodesbanner/上古：龍神覺醒-bar.jpg | D9: =IF(A9="","", "https://www.ssbuy.tw/detail_giftcode/dist/giftcodes/" & IF(ISNUMBER(LEFT(A9,1)*1), "game-", "") & A9 & ".html") -> https://www.ssbuy.tw/detail_giftcode/dist/giftcodes/上古：龍神覺醒.html | E9: 首款龍主題MMO鉅作！ | F9: 進入主畫面，點選個人頭像 | G9: 進入設定（齒輪） | H9: 輸入禮包碼 → 確認兌換 | K9: DG666 | L9: 2025商城元寶鑽石禮包 | M9: DG777 | N9: 2025商城元寶鑽石禮包 | O9: DG888 | P9: 2025商城元寶鑽石禮包 | Q9: VIP666 | R9: 2025商城元寶鑽石禮包 | S9: VIP777 | T9: 2025商城元寶鑽石禮包 | U9: VIP888 | V9: 2025商城元寶鑽石禮包 | W9: SVIP666 | X9: 2025商城元寶鑽石禮包 | Y9: SVIP777 | Z9: 2025商城元寶鑽石禮包 | AA9: SVIP888 | AB9: 2025商城元寶鑽石禮包 | AC9: EVE209 | AD9: 2025商城元寶鑽石禮包 | AE9: NEW2024 | AF9: 2025商城元寶鑽石禮包 | AG9: LF2233 | AH9: 2025商城元寶鑽石禮包
A10: 小艦艦超勇 | B10: ="giftcodesbanner/" & A10 & "-bar.jpg" -> giftcodesbanner/小艦艦超勇-bar.jpg | D10: =IF(A10="","", "https://www.ssbuy.tw/detail_giftcode/dist/giftcodes/" & IF(ISNUMBER(LEFT(A10,1)*1), "game-", "") & A10 & ".html") -> https://www.ssbuy.tw/detail_giftcode/dist/giftcodes/小艦艦超勇.html | E10: 無止境的武器升級，打造你的最強艦隊！ | F10: 進入主畫面，點選個人頭像 | G10: 進入設定（齒輪） | H10: 輸入禮包碼 → 確認兌換 | K10: OUTLANDER777 | L10: 2025商城元寶鑽石禮包 | M10: ABBY01011 | N10: 2025商城元寶鑽石禮包 | O10: MIMI01021 | P10: 2025商城元寶鑽石禮包 | Q10: HIGHSEASHEROGO | R10: 2025商城元寶鑽石禮包 | S10: HAPPYHSH777 | T10: 2025商城元寶鑽石禮包 | U10: VIP777 | V10: 2025商城元寶鑽石禮包 | W10: VIP888 | X10: 2025商城元寶鑽石禮包 | Y10: HSHLAUNCH0109 | Z10: 2025商城元寶鑽石禮包
A11: 天使軍團 | B11: ="giftcodesbanner/" & A11 & "-bar.jpg" -> giftcodesbanner/天使軍團-bar.jpg | D11: =IF(A11="","", "https://www.ssbuy.tw/detail_giftcode/dist/giftcodes/" & IF(ISNUMBER(LEFT(A11,1)*1), "game-", "") & A11 & ".html") -> https://www.ssbuy.tw/detail_giftcode/dist/giftcodes/天使軍團.html | E11: 天使軍團是最新推出的3D天使銀河冒險RPG手遊。 希拉星系，深邃而瑰麗……這裡曾存在著古老時期的文明。 | F11: 進入主畫面，點選個人頭像 | G11: 進入設定（齒輪） | H11: 輸入禮包碼 → 確認兌換 | K11: DscdRetrom43zw | L11: 2025商城元寶鑽石禮包 | M11: Mkjptfjlny8j31 | N11: 2025商城元寶鑽石禮包 | O11: ALFacebook | P11: 2025商城元寶鑽石禮包
A12: 天堂W | B12: ="giftcodesbanner/" & A12 & "-bar.jpg" -> giftcodesbanner/天堂W-bar.jpg | D12: =IF(A12="","", "https://www.ssbuy.tw/detail_giftcode/dist/giftcodes/" & IF(ISNUMBER(LEFT(A12,1)*1), "game-", "") & A12 & ".html") -> https://www.ssbuy.tw/detail_giftcode/dist/giftcodes/天堂W.html | E12: 《天堂W》是繼承PC MMORPG天堂正統性的跨平台遊戲，全球單一版本服務，即時AI翻譯；Full 3D畫面和斜45度視角開發的暗黑奇幻世界；將天堂的核心內容戰鬥社群延伸到世界。 | F12: 進入主畫面，點選個人頭像 | G12: 進入設定（齒輪） | H12: 輸入禮包碼 → 確認兌換 | K12: HOTNEWYEARADEN24 | L12: 2025商城元寶鑽石禮包 | M12: BLUEDRAGONW | N12: 2025商城元寶鑽石禮包
A13: 少女前線2：追放 | B13: ="giftcodesbanner/" & A13 & "-bar.jpg" -> giftcodesbanner/少女前線2：追放-bar.jpg | D13: =IF(A13="","", "https://www.ssbuy.tw/detail_giftcode/dist/giftcodes/" & IF(ISNUMBER(LEFT(A13,1)*1), "game-", "") & A13 & ".html") -> https://www.ssbuy.tw/detail_giftcode/dist/giftcodes/少女前線2：追放.html | E13: 講述了指揮官與格里芬之間無法調和的理念衝突，導致指揮官選擇自我流放，成為賞金獵人。 | F13: 進入主畫面，點選個人頭像 | G13: 進入設定（齒輪） | H13: 輸入禮包碼 → 確認兌換 | K13: ULLRID1205 | L13: 戰場報告*5000、解析圖紙*5000 | M13: SUOMI1205 | N13: 戰場報告*5000、解析圖紙*5000 | O13: ELMO1205 | P13: 坍塌晶條*150、薩狄斯金*5000 | Q13: EXILIUMDC | R13: 戰場報告*5000、解析圖紙*5000 | S13: GLASSISLE | T13: 2025商城元寶鑽石禮包 | U13: ELMOLIVE | V13: 坍塌晶條*50、戰場報告*5000、解析圖紙*5000 | W13: OMNGKTWN | X13: 坍塌晶條*150、薩狄斯金*3000、接入密鑰*2 | Y13: GFL2LAUNCH | Z13: 接入密鑰*1、大容量記憶體*2
A14: 幻獸傳說Ｍ | B14: ="giftcodesbanner/" & A14 & "-bar.jpg" -> giftcodesbanner/幻獸傳說Ｍ-bar.jpg | D14: =IF(A14="","", "https://www.ssbuy.tw/detail_giftcode/dist/giftcodes/" & IF(ISNUMBER(LEFT(A14,1)*1), "game-", "") & A14 & ".html") -> https://www.ssbuy.tw/detail_giftcode/dist/giftcodes/幻獸傳說Ｍ.html | E14: 2025年萬眾期待的幻獸手遊來啦！異世界捉獸育獸RPG《幻獸傳說M》現已上市！豆花蔡黃汝可愛代言，演繹疾海兔！ | F14: 進入主畫面，點選個人頭像 | G14: 進入設定（齒輪） | H14: 輸入禮包碼 → 確認兌換 | K14: FAFA666 | L14: 2025商城元寶鑽石禮包 | M14: FAFA777 | N14: 2025商城元寶鑽石禮包 | O14: FAFA888 | P14: 2025商城元寶鑽石禮包 | Q14: SSSVIP333 | R14: 2025商城元寶鑽石禮包 | S14: SSSVIP444 | T14: 2025商城元寶鑽石禮包 | U14: SSSVIP555 | V14: 2025商城元寶鑽石禮包 | W14: VIP555 | X14: 2025商城元寶鑽石禮包 | Y14: VIP666 | Z14: 2025商城元寶鑽石禮包 | AA14: VIP777 | AB14: 2025商城元寶鑽石禮包 | AC14: VIP888 | AD14: 2025商城元寶鑽石禮包 | AE14: VIP999 | AF14: 2025商城元寶鑽石禮包 | AG14: INSTALL | AH14: 2025商城元寶鑽石禮包
A15: 未定事件簿 | B15: ="giftcodesbanner/" & A15 & "-bar.jpg" -> giftcodesbanner/未定事件簿-bar.jpg | D15: =IF(A15="","", "https://www.ssbuy.tw/detail_giftcode/dist/giftcodes/" & IF(ISNUMBER(LEFT(A15,1)*1), "game-", "") & A15 & ".html") -> https://www.ssbuy.tw/detail_giftcode/dist/giftcodes/未定事件簿.html | E15: 當正義與邪惡的界定越來越模糊，妳手中的天平將會傾向何方？一場戀愛與推理的冒險，此刻，邀妳共赴。 | F15: 進入主畫面，點選個人頭像 | G15: 進入設定（齒輪） | H15: 輸入禮包碼 → 確認兌換 | K15: HAPPY38WOMENSDAY | L15: 未名晶片*60+未名幣*3800+法理之諭III*8 | M15: 520FALLINLOVE | N15: 未名晶片×100+友誼徽章×520+未名幣×13140 | O15: SUMMERGIFT | P15: 未名晶片×60+未名幣×10000+能量飲料普通裝×1 | Q15: DRAGONBOAT | R15: 未名晶片×60+法理之諭III×20 | S15: HappyDragonBoat2025 | T15: 未名晶片×60、未名幣 ×5500、能量飲料普通裝 ×1
A16: 永恆靈魂 | B16: ="giftcodesbanner/" & A16 & "-bar.jpg" -> giftcodesbanner/永恆靈魂-bar.jpg | D16: =IF(A16="","", "https://www.ssbuy.tw/detail_giftcode/dist/giftcodes/" & IF(ISNUMBER(LEFT(A16,1)*1), "game-", "") & A16 & ".html") -> https://www.ssbuy.tw/detail_giftcode/dist/giftcodes/永恆靈魂.html | E16: 末日的今天，精靈們等候您的指示…救援者，帶領著她們的靈魂活下去吧。 | F16: 進入主畫面，點選個人頭像 | G16: 進入設定（齒輪） | H16: 輸入禮包碼 → 確認兌換 | K16: 2Qgift0325 | L16: 1,000個永恆石
A17: 守住呀主公 | B17: ="giftcodesbanner/" & A17 & "-bar.jpg" -> giftcodesbanner/守住呀主公-bar.jpg | D17: =IF(A17="","", "https://www.ssbuy.tw/detail_giftcode/dist/giftcodes/" & IF(ISNUMBER(LEFT(A17,1)*1), "game-", "") & A17 & ".html") -> https://www.ssbuy.tw/detail_giftcode/dist/giftcodes/守住呀主公.html | E17: 喜歡策略塔防、鍾愛三國名將的你，絕對不容錯過這款高畫質3D塔防力作！豐富的塔防玩法、酷炫的技能特效，讓你盡享爽快的遊戲體驗。 | F17: 進入主畫面，點選個人頭像 | G17: 進入設定（齒輪） | H17: 輸入禮包碼 → 確認兌換 | K17: VIP666 | L17: 2025商城元寶鑽石禮包 | M17: VIP888 | N17: 2025商城元寶鑽石禮包 | O17: WEEKGIFT | P17: 2025商城元寶鑽石禮包 | Q17: KH26UB56P | R17: 2025商城元寶鑽石禮包 | S17: UYJH658YY | T17: 2025商城元寶鑽石禮包 | U17: VIP6699 | V17: 2025商城元寶鑽石禮包 | W17: NOVGIHT | X17: 2025商城元寶鑽石禮包
A18: 吟遊戰記 | B18: ="giftcodesbanner/" & A18 & "-bar.jpg" -> giftcodesbanner/吟遊戰記-bar.jpg | D18: =IF(A18="","", "https://www.ssbuy.tw/detail_giftcode/dist/giftcodes/" & IF(ISNUMBER(LEFT(A18,1)*1), "game-", "") & A18 & ".html") -> https://www.ssbuy.tw/detail_giftcode/dist/giftcodes/吟遊戰記.html | E18: 新感覺放置型勇者冒險RPG，登入即可獲得免費9999連抽！輕鬆休閒的冒險，來一場解放雙手的戰鬥吧！ | F18: 進入主畫面，點選個人頭像 | G18: 進入設定（齒輪） | H18: 輸入禮包碼 → 確認兌換 | K18: VIP666 | L18: 2025商城元寶鑽石禮包 | M18: VIP777 | N18: 2025商城元寶鑽石禮包 | O18: VIP888 | P18: 2025商城元寶鑽石禮包 | Q18: VIP999 | R18: 2025商城元寶鑽石禮包
A19: 我獨自升級：ARISE | B19: ="giftcodesbanner/" & A19 & "-bar.jpg" -> giftcodesbanner/我獨自升級：ARISE-bar.jpg | D19: =IF(A19="","", "https://www.ssbuy.tw/detail_giftcode/dist/giftcodes/" & IF(ISNUMBER(LEFT(A19,1)*1), "game-", "") & A19 & ".html") -> https://www.ssbuy.tw/detail_giftcode/dist/giftcodes/我獨自升級：ARISE.html | E19: 德國最強的獵人，也是世界獵人排名第12名的S級「萊納德．尼爾曼」已加入完成！ | F19: 進入主畫面，點選個人頭像 | G19: 進入設定（齒輪） | H19: 輸入禮包碼 → 確認兌換 | K19: SLALIVESTREAM | L19: 2025商城元寶鑽石禮包 | M19: JULYUPDATELIVE | N19: 2025商城元寶鑽石禮包 | O19: SEEYOUSOON | P19: 2025商城元寶鑽石禮包 | Q19: SURPRISEGIFT | R19: 2025商城元寶鑽石禮包 | S19: THXSLVARISETHX | T19: 2025商城元寶鑽石禮包 | U19: WORLD1STLEVELUP | V19: 2025商城元寶鑽石禮包 | W19: SOLOLEVELING2025商城元寶鑽石禮包0508 | X19: 2025商城元寶鑽石禮包 | Y19: STAYSHARP | Z19: 2025商城元寶鑽石禮包
A20: 命運聖契：少女的羈絆 | B20: ="giftcodesbanner/" & A20 & "-bar.jpg" -> giftcodesbanner/命運聖契：少女的羈絆-bar.jpg | D20: =IF(A20="","", "https://www.ssbuy.tw/detail_giftcode/dist/giftcodes/" & IF(ISNUMBER(LEFT(A20,1)*1), "game-", "") & A20 & ".html") -> https://www.ssbuy.tw/detail_giftcode/dist/giftcodes/命運聖契：少女的羈絆.html | E20: 2025首款命運少女輕放置RPG手遊《命運聖契：少女的羈絆》霜糖奇典活动開啟！登錄可得自選SSR、限定頭像框及海量高價值虛寶。 | F20: 進入主畫面，點選個人頭像 | G20: 進入設定（齒輪） | H20: 輸入禮包碼 → 確認兌換 | K20: FEEL666 | L20: 2025商城元寶鑽石禮包 | M20: PEACH520 | N20: 2025商城元寶鑽石禮包 | O20: SEX000 | P20: 2025商城元寶鑽石禮包 | Q20: SEX666 | R20: 2025商城元寶鑽石禮包 | S20: SEX777 | T20: 2025商城元寶鑽石禮包 | U20: SEX888 | V20: 2025商城元寶鑽石禮包 | W20: SEX999 | X20: 2025商城元寶鑽石禮包 | Y20: FEEL001 | Z20: 2025商城元寶鑽石禮包 | AA20: FEEL003 | AB20: 2025商城元寶鑽石禮包 | AC20: FEEL888 | AD20: 2025商城元寶鑽石禮包 | AE20: FEEL999 | AF20: 2025商城元寶鑽石禮包
A21: 放置軍團 | B21: ="giftcodesbanner/" & A21 & "-bar.jpg" -> giftcodesbanner/放置軍團-bar.jpg | D21: =IF(A21="","", "https://www.ssbuy.tw/detail_giftcode/dist/giftcodes/" & IF(ISNUMBER(LEFT(A21,1)*1), "game-", "") & A21 & ".html") -> https://www.ssbuy.tw/detail_giftcode/dist/giftcodes/放置軍團.html | E21: 我們敬愛的魔王大人在與人類的決戰中，因為死亡騎士臨陣倒戈，被人類打碎成了渣渣。我們三個忠心耿耿的小鬼抬著魔王的靈魂碎片，躲進了一座廢棄的地下城。在這裡我們要重新建立地下城，儲備物資，集結軍團！ | F21: 進入主畫面，點選個人頭像 | G21: 進入設定（齒輪） | H21: 輸入禮包碼 → 確認兌換 | K21: 放置军团666 | L21: 氪晶*200 | M21: FZJT666 | N21: 魔晶*10000 | O21: 可靠的布道者 | P21: 氪晶*500 | Q21: 头秃古卜林们 | R21: 魔晶*20000 | S21: 我会回来的啊 | T21: 契约筹码*2
A22: 明日方舟 | B22: ="giftcodesbanner/" & A22 & "-bar.jpg" -> giftcodesbanner/明日方舟-bar.jpg | D22: =IF(A22="","", "https://www.ssbuy.tw/detail_giftcode/dist/giftcodes/" & IF(ISNUMBER(LEFT(A22,1)*1), "game-", "") & A22 & ".html") -> https://www.ssbuy.tw/detail_giftcode/dist/giftcodes/明日方舟.html | E22: 迷宮裡……竟然存在這樣的地方？準備好刀劍和法杖，也別忘了鍋、鏟和調味料！準備好了嗎，我們要開動了喔！ | F22: 進入主畫面，點選個人頭像 | G22: 進入設定（齒輪） | H22: 輸入禮包碼 → 確認兌換 | K22: 5VVK6LN5BM3GLFA6 | L22: 理智*60、中級作戰紀錄*20、龍門幣*20000
A23: 屍鬼三國 | B23: ="giftcodesbanner/" & A23 & "-bar.jpg" -> giftcodesbanner/屍鬼三國-bar.jpg | D23: =IF(A23="","", "https://www.ssbuy.tw/detail_giftcode/dist/giftcodes/" & IF(ISNUMBER(LEFT(A23,1)*1), "game-", "") & A23 & ".html") -> https://www.ssbuy.tw/detail_giftcode/dist/giftcodes/屍鬼三國.html | E23: 獨一款屍鬼化的三國卡牌手遊上市啦！新世代三國卡牌鉅作，融合了ARPG的開放世界設計，你可以在屍鬼橫行的三國亂世中自由探索。 | F23: 進入主畫面，點選個人頭像 | G23: 進入設定（齒輪） | H23: 輸入禮包碼 → 確認兌換 | K23: VIP666 | L23: 2025商城元寶鑽石禮包 | M23: VIP777 | N23: 2025商城元寶鑽石禮包 | O23: VIP888 | P23: 2025商城元寶鑽石禮包 | Q23: SG444 | R23: 2025商城元寶鑽石禮包 | S23: SG666 | T23: 2025商城元寶鑽石禮包 | U23: SG888 | V23: 2025商城元寶鑽石禮包 | W23: SSSVIP | X23: 2025商城元寶鑽石禮包 | Y23: 開服大吉 | Z23: 2025商城元寶鑽石禮包 | AA23: 屍鬼關羽 | AB23: 2025商城元寶鑽石禮包 | AC23: EGAMEPAY | AD23: 2025商城元寶鑽石禮包
A24: 星鏈計畫：未來少女 | B24: ="giftcodesbanner/" & A24 & "-bar.jpg" -> giftcodesbanner/星鏈計畫：未來少女-bar.jpg | D24: =IF(A24="","", "https://www.ssbuy.tw/detail_giftcode/dist/giftcodes/" & IF(ISNUMBER(LEFT(A24,1)*1), "game-", "") & A24 & ".html") -> https://www.ssbuy.tw/detail_giftcode/dist/giftcodes/星鏈計畫：未來少女.html | E24: 在無盡的絕望中，為少女們構築希望藍圖！ | F24: 進入主畫面，點選個人頭像 | G24: 進入設定（齒輪） | H24: 輸入禮包碼 → 確認兌換 | K24: TGS24STARSEED | L24: 10張綠券 | M24: CHASINGLEINSTARS | N24: 5張綠券 | O24: STARSEEDFREEGIFT | P24: 200星際比特 | Q24: GET5STARSEEDGIRLS | R24: 5張綠券 | S24: SIAXFREYJA | T24: 5張金券 | U24: 2024STARMAS | V24: 5張綠券
A25: 英雄之王 | B25: ="giftcodesbanner/" & A25 & "-bar.jpg" -> giftcodesbanner/英雄之王-bar.jpg | D25: =IF(A25="","", "https://www.ssbuy.tw/detail_giftcode/dist/giftcodes/" & IF(ISNUMBER(LEFT(A25,1)*1), "game-", "") & A25 & ".html") -> https://www.ssbuy.tw/detail_giftcode/dist/giftcodes/英雄之王.html | E25: 除了我們分享的遊戲畫面、影片和其他細節之外，我還想讓大家了解我們對遊戲的期望與願景。 我們希望能藉由《英雄之王》捕捉遊戲的本質。 | F25: 進入主畫面，點選個人頭像 | G25: 進入設定（齒輪） | H25: 輸入禮包碼 → 確認兌換 | K25: FORUM4U | L25: 2025商城元寶鑽石禮包 | M25: THXKAKAO | N25: 2025商城元寶鑽石禮包 | O25: WELCOMELOH | P25: 2025商城元寶鑽石禮包 | Q25: GOOGLEBEST | R25: 2025商城元寶鑽石禮包 | S25: LOHFORTUNE | T25: 2025商城元寶鑽石禮包 | U25: JPGOOGLE1 | V25: 2025商城元寶鑽石禮包 | W25: LEVELUPUP | X25: 2025商城元寶鑽石禮包 | Y25: GOOGLEFAME | Z25: 2025商城元寶鑽石禮包 | AA25: THANKSLORD | AB25: 2025商城元寶鑽石禮包
A26: 英雄聯盟 | B26: ="giftcodesbanner/" & A26 & "-bar.jpg" -> giftcodesbanner/英雄聯盟-bar.jpg | D26: =IF(A26="","", "https://www.ssbuy.tw/detail_giftcode/dist/giftcodes/" & IF(ISNUMBER(LEFT(A26,1)*1), "game-", "") & A26 & ".html") -> https://www.ssbuy.tw/detail_giftcode/dist/giftcodes/英雄聯盟.html | F26: 進入主畫面，點選個人頭像 | G26: 進入設定（齒輪） | H26: 輸入禮包碼 → 確認兌換 | K26: G9TGAS2024 | L26: 英雄六選一 + 流星頭像 | M26: G9FB888 | N26: 3000金幣
A27: 恐龍突變 | B27: ="giftcodesbanner/" & A27 & "-bar.jpg" -> giftcodesbanner/恐龍突變-bar.jpg | D27: =IF(A27="","", "https://www.ssbuy.tw/detail_giftcode/dist/giftcodes/" & IF(ISNUMBER(LEFT(A27,1)*1), "game-", "") & A27 & ".html") -> https://www.ssbuy.tw/detail_giftcode/dist/giftcodes/恐龍突變.html | E27: » 配對以產生受精卵: 進行戰略性交配以創造更強大的恐龍。» 點擊孵化無限的蛋: 不斷擴展你的恐龍收藏。 | F27: 進入主畫面，點選個人頭像 | G27: 進入設定（齒輪） | H27: 輸入禮包碼 → 確認兌換
A28: 神域 | B28: ="giftcodesbanner/" & A28 & "-bar.jpg" -> giftcodesbanner/神域-bar.jpg | D28: =IF(A28="","", "https://www.ssbuy.tw/detail_giftcode/dist/giftcodes/" & IF(ISNUMBER(LEFT(A28,1)*1), "game-", "") & A28 & ".html") -> https://www.ssbuy.tw/detail_giftcode/dist/giftcodes/神域.html | E28: 對抗邪惡勢力，策略過人的您並非孤軍奮戰，來自世界各地且為數眾多的神話英雄，正等待您的召喚！透過遊戲掛機得到的寶石、材料及各種資源，一支強而有力且技能靈活的自訂專屬軍團，就在您的股掌之間！ | F28: 進入主畫面，點選個人頭像 | G28: 進入設定（齒輪） | H28: 輸入禮包碼 → 確認兌換 | K28: MH8888 | L28: 永久兌換碼 | M28: MH7777 | N28: 永久兌換碼
A29: 崩壞：星穹鐵道 | B29: ="giftcodesbanner/" & A29 & "-bar.jpg" -> giftcodesbanner/崩壞：星穹鐵道-bar.jpg | D29: =IF(A29="","", "https://www.ssbuy.tw/detail_giftcode/dist/giftcodes/" & IF(ISNUMBER(LEFT(A29,1)*1), "game-", "") & A29 & ".html") -> https://www.ssbuy.tw/detail_giftcode/dist/giftcodes/崩壞：星穹鐵道.html | E29: 這片銀河中有名為「星神」的存在，祂們造就現實，抹消星辰，在無數「世界」中留下祂們的痕跡。你——一名特殊的旅客，將偕同繼承「開拓」意志的同伴們，乘坐星穹列車穿越銀河，沿著某位「星神」曾經所行之途前進。你將由此探索新的文明、結識新的夥伴、在無數光怪陸離的「世界」之間展開新的冒險。所有你想知道的，都將在群星中找到解答。 那麼，準備好開始這段「開拓」之旅了嗎？ | F29: 進入主畫面，點選個人頭像 | G29: 進入設定（齒輪） | H29: 輸入禮包碼 → 確認兌換 | K29: WAJ7CVBC4SG3 | L29: 星瓊x50、信用點x10k
A30: 救世者之樹：新世界 | B30: ="giftcodesbanner/" & A30 & "-bar.jpg" -> giftcodesbanner/救世者之樹：新世界-bar.jpg | D30: =IF(A30="","", "https://www.ssbuy.tw/detail_giftcode/dist/giftcodes/" & IF(ISNUMBER(LEFT(A30,1)*1), "game-", "") & A30 & ".html") -> https://www.ssbuy.tw/detail_giftcode/dist/giftcodes/救世者之樹：新世界.html | E30: 在重磅上線的樹緣系統中，舉行浪漫的樹緣典禮；集結戰友做好準備，迎戰魔神副本BOSS！ 新手可領取70抽、金色時裝4件套還有限定自選坐騎！ 讓我們來看看來自亞洲11地區的勇者們的留言！ -「日本韓國泰國的妹妹都搶著跟我結緣…好難選哦！」 --來自世界頻道的建巨集007號 樹緣系統重磅上線，在全服玩家的見證和祝福下，完成盛大浪漫的樹緣典禮！還會擁有一個共同的家園，一起創造美好生活！ | F30: 進入主畫面，點選個人頭像 | G30: 進入設定（齒輪） | H30: 輸入禮包碼 → 確認兌換 | K30: TOSNASIAN | L30: 貓靈扭蛋券 × 1、銀花 × 50000、強化卷軸 × 20 | M30: TOSN30DAYS | N30: 光珀 × 500、福袋禮票 × 10 | O30: LVVHKXYMBWPZ | P30: 貓票 × 2、光珀 × 100 | Q30: TOSNGIFT | R30: 2025商城元寶鑽石禮包 | S30: TOSN666 | T30: 2025商城元寶鑽石禮包 | U30: 2025GIFT | V30: 2025商城元寶鑽石禮包 | W30: TOSNNEKO | X30: 2025商城元寶鑽石禮包 | Y30: hello2025 | Z30: 2025商城元寶鑽石禮包
A31: 球球英雄 | B31: ="giftcodesbanner/" & A31 & "-bar.jpg" -> giftcodesbanner/球球英雄-bar.jpg | D31: =IF(A31="","", "https://www.ssbuy.tw/detail_giftcode/dist/giftcodes/" & IF(ISNUMBER(LEFT(A31,1)*1), "game-", "") & A31 & ".html") -> https://www.ssbuy.tw/detail_giftcode/dist/giftcodes/球球英雄.html | E31: 怪物們在這一天毫無預兆地突然降臨，城市與家園都籠罩在猙獰與陰霾中。 我們需要你，勇士！為我們抵禦黑暗勢力！ 來吧！和我們一起，召喚出賦有神奇力量的球球，與黑暗勢力戰鬥！ | F31: 進入主畫面，點選個人頭像 | G31: 進入設定（齒輪） | H31: 輸入禮包碼 → 確認兌換 | K31: E94LNYAM | L31: 2025商城元寶鑽石禮包 | M31: RM6G7HF4 | N31: 2025商城元寶鑽石禮包 | O31: VBGEW5JZ | P31: 2025商城元寶鑽石禮包
A32: 第七史詩 | B32: ="giftcodesbanner/" & A32 & "-bar.jpg" -> giftcodesbanner/第七史詩-bar.jpg | D32: =IF(A32="","", "https://www.ssbuy.tw/detail_giftcode/dist/giftcodes/" & IF(ISNUMBER(LEFT(A32,1)*1), "game-", "") & A32 & ".html") -> https://www.ssbuy.tw/detail_giftcode/dist/giftcodes/第七史詩.html | E32: 第七個世界的故事...生命的女神迪彩將自己的權勢瓜分，創造出聖約的繼承者及神獸 | F32: 進入主畫面，點選個人頭像 | G32: 進入設定（齒輪） | H32: 輸入禮包碼 → 確認兌換 | K32: THANKSHEIRALL | L32: 10片生命之葉 & 1,000,000金幣
A33: 創世紀戰M：阿修羅計畫 | B33: ="giftcodesbanner/" & A33 & "-bar.jpg" -> giftcodesbanner/創世紀戰M：阿修羅計畫-bar.jpg | D33: =IF(A33="","", "https://www.ssbuy.tw/detail_giftcode/dist/giftcodes/" & IF(ISNUMBER(LEFT(A33,1)*1), "game-", "") & A33 & ".html") -> https://www.ssbuy.tw/detail_giftcode/dist/giftcodes/創世紀戰M：阿修羅計畫.html | E33: 富饒廣闊的安塔利亞大陸，因戰爭爆發一切風雲變色，飽受戰爭欺凌， 王女伊歐林帶著王國騎士團，憑藉勇氣與智慧復國，對抗艱難命運。 面對強大武力的蓋席勒帝國，也絕不屈服！ | F33: 進入主畫面，點選個人頭像 | G33: 進入設定（齒輪） | H33: 輸入禮包碼 → 確認兌換 | K33: SHASHA77 | L33: 2025商城元寶鑽石禮包 | M33: HOWHOW | N33: 2025商城元寶鑽石禮包 | O33: GENESIS | P33: 2025商城元寶鑽石禮包 | Q33: Kr1stw | R33: 2025商城元寶鑽石禮包 | S33: GenesisGoogleHOT | T33: 2025商城元寶鑽石禮包 | U33: jazlatte | V33: 2025商城元寶鑽石禮包 | W33: roger9527 | X33: 2025商城元寶鑽石禮包 | Y33: greentea | Z33: 2025商城元寶鑽石禮包 | AA33: pudding1223xd | AB33: 2025商城元寶鑽石禮包 | AC33: COMMUTE | AD33: 2025商城元寶鑽石禮包 | AE33: ennaouii | AF33: 2025商城元寶鑽石禮包
A34: 最強宗師 | B34: ="giftcodesbanner/" & A34 & "-bar.jpg" -> giftcodesbanner/最強宗師-bar.jpg | D34: =IF(A34="","", "https://www.ssbuy.tw/detail_giftcode/dist/giftcodes/" & IF(ISNUMBER(LEFT(A34,1)*1), "game-", "") & A34 & ".html") -> https://www.ssbuy.tw/detail_giftcode/dist/giftcodes/最強宗師.html | E34: 《最強宗師》是一款最強卡牌策略RPG，在這裡，每位角色都有獨特特質，不存在廢卡，所有資源都能無損傳承，讓你輕鬆成為最強宗師！躺平掛機也能生產材料，輕鬆實現戰力飆升。策略搭配、多樣玩法，帶你領略充滿熱血與智慧的宗門修煉之路！在這裡，人人都可以是主角，天選之人，唯我最強！ | F34: 進入主畫面，點選個人頭像 | G34: 進入設定（齒輪） | H34: 輸入禮包碼 → 確認兌換 | K34: master111 | L34: 2025商城元寶鑽石禮包 | M34: top111 | N34: 2025商城元寶鑽石禮包 | O34: top666 | P34: 2025商城元寶鑽石禮包 | Q34: top777 | R34: 2025商城元寶鑽石禮包 | S34: top888 | T34: 2025商城元寶鑽石禮包 | U34: Ldtop666 | V34: 2025商城元寶鑽石禮包 | W34: Noxtop666 | X34: 2025商城元寶鑽石禮包 | Y34: Bluetop666 | Z34: 2025商城元寶鑽石禮包 | AA34: master666 | AB34: 2025商城元寶鑽石禮包 | AC34: master777 | AD34: 2025商城元寶鑽石禮包 | AE34: master888 | AF34: 2025商城元寶鑽石禮包 | AG34: master999 | AH34: 2025商城元寶鑽石禮包
A35: 無期迷途 | B35: ="giftcodesbanner/" & A35 & "-bar.jpg" -> giftcodesbanner/無期迷途-bar.jpg | D35: =IF(A35="","", "https://www.ssbuy.tw/detail_giftcode/dist/giftcodes/" & IF(ISNUMBER(LEFT(A35,1)*1), "game-", "") & A35 & ".html") -> https://www.ssbuy.tw/detail_giftcode/dist/giftcodes/無期迷途.html | E35: 《無期迷途》是款以混沌都市為主題的RPG即時策略攻防手遊。身為【米諾斯危機管理局】局長的你，將親手追蹤並收容擁有特殊力量的異能使者——禁閉者們。使用禁閉者的禁忌力量，揭開隱藏在這個世界的真相！ 「您好，新任的局長，我們一直都在等你。」這裡是米諾斯危機管理局，一座收容禁閉者的隱密場所。而您——令人尊敬的局長，將在此釋放其中最強大的禁閉者們。他們或舉止優雅，或性情乖張，或美艷狡猾；唯一的共同點他們都有不為人知的過去，以及超越常人的超凡之力。 局長，請盡情使用他們的力量，深入狄斯城的禁區，尋找讓世界異變的源頭，解開瘋狂恐怖謎團，去扭轉命運吧！ | F35: 進入主畫面，點選個人頭像 | G35: 進入設定（齒輪） | H35: 輸入禮包碼 → 確認兌換 | K35: 二週年快樂 | L35: 2025商城元寶鑽石禮包 | M35: 幽零風暴 | N35: 2025商城元寶鑽石禮包 | O35: 感謝一路相伴 | P35: 2025商城元寶鑽石禮包 | Q35: 白記實業發大財 | R35: 2025商城元寶鑽石禮包
A36: 絕區零 | B36: ="giftcodesbanner/" & A36 & "-bar.jpg" -> giftcodesbanner/絕區零-bar.jpg | D36: =IF(A36="","", "https://www.ssbuy.tw/detail_giftcode/dist/giftcodes/" & IF(ISNUMBER(LEFT(A36,1)*1), "game-", "") & A36 & ".html") -> https://www.ssbuy.tw/detail_giftcode/dist/giftcodes/絕區零.html | E36: 遊戲故事發生在被神秘災害「空洞」所侵襲的後世界末日世界中，主角是一位名為「繩匠」的角色，負責引導人們進入「空洞」並與怪物「以骸」戰鬥。 | F36: 進入主畫面，點選個人頭像 | G36: 進入設定（齒輪） | H36: 輸入禮包碼 → 確認兌換 | K36: HARUMASAGIFTALL | L36: 2025年可用兌換碼 | M36: ZZZ4PC | N36: 2024 PC 限定兌換碼 | O36: ZZZFM | P36: 2024 日本全家合作兌換碼 | Q36: ZZZGFN24 | R36: 2024 GeForce NOW x 絕區零 兌換碼 | S36: HSAHLWFEFE | T36: 2024年推出，仍可使用 | U36: ZENLESSGIFT | V36: 2024年推出，仍可使用 | W36: ZZZ15MINA | X36: 2025 1.5 版兌換碼
A37: 傳說對決 | B37: ="giftcodesbanner/" & A37 & "-bar.jpg" -> giftcodesbanner/傳說對決-bar.jpg | D37: =IF(A37="","", "https://www.ssbuy.tw/detail_giftcode/dist/giftcodes/" & IF(ISNUMBER(LEFT(A37,1)*1), "game-", "") & A37 & ".html") -> https://www.ssbuy.tw/detail_giftcode/dist/giftcodes/傳說對決.html | E37: Garena 傳說對決是一款節奏快速、輕鬆又不失競技成分的MOBA 手遊，經典玩法加上獨特的輪盤指向施法的直覺操作模式，輕鬆競技於指掌之間！ | F37: 進入主畫面，點選個人頭像 | G37: 進入設定（齒輪） | H37: 輸入禮包碼 → 確認兌換 | K37: HAPPY2025 | L37: 造型20選一 | M37: 2025AOV777 | N37: 光暗擊殺特效永久
A38: 楓之谷M | B38: ="giftcodesbanner/" & A38 & "-bar.jpg" -> giftcodesbanner/楓之谷M-bar.jpg | D38: =IF(A38="","", "https://www.ssbuy.tw/detail_giftcode/dist/giftcodes/" & IF(ISNUMBER(LEFT(A38,1)*1), "game-", "") & A38 & ".html") -> https://www.ssbuy.tw/detail_giftcode/dist/giftcodes/楓之谷M.html | E38: 《楓之谷M》是一款由Nexon開發的免費大型多人線上角色扮演遊戲，是基於《楓之谷》的移動版。 遊戲中玩家可以扮演來自各地的角色，進行冒險、戰鬥、任務、以及和其他玩家互動。 | F38: 進入主畫面，點選個人頭像 | G38: 進入設定（齒輪） | H38: 輸入禮包碼 → 確認兌換 | K38: 202501EREL | L38: 橘色經驗值增加券X5、自動戰鬥補充券X3、地城入場券組合 | M38: M2025NEWYEAR | N38: 蛇湯X2、自動戰鬥補充券X4、弄蛇人椅子X1 | O38: 202502ARCHON | P38: 2025商城元寶鑽石禮包 | Q38: AGAINHASTE | R38: 2025商城元寶鑽石禮包
A39: 鳴潮 | B39: ="giftcodesbanner/" & A39 & "-bar.jpg" -> giftcodesbanner/鳴潮-bar.jpg | D39: =IF(A39="","", "https://www.ssbuy.tw/detail_giftcode/dist/giftcodes/" & IF(ISNUMBER(LEFT(A39,1)*1), "game-", "") & A39 & ".html") -> https://www.ssbuy.tw/detail_giftcode/dist/giftcodes/鳴潮.html | E39: 《鳴潮》是一款末世題材的開放世界遊戲，具有高自由度且豐富的內容。 遊戲玩法包括攀爬、滑翔、採集等開放世界要素，還新增了「跑牆」的元素。 本作動作方面採用玩家能夠「閃避」和「彈刀」兩種招架方式。 | F39: 進入主畫面，點選個人頭像 | G39: 進入設定（齒輪） | H39: 輸入禮包碼 → 確認兌換 | K39: VCN9R5JONA6F | L39: 咪咪蛋 | M39: 8EHD24I802UP | N39: 大丸 | O39: QZ05OKNOB8FW | P39: 璐洛洛 | Q39: K82WZ34HXSJK | R39: 懶貓
A40: 劍與遠征：啟程 | B40: ="giftcodesbanner/" & A40 & "-bar.jpg" -> giftcodesbanner/劍與遠征：啟程-bar.jpg | D40: =IF(A40="","", "https://www.ssbuy.tw/detail_giftcode/dist/giftcodes/" & IF(ISNUMBER(LEFT(A40,1)*1), "game-", "") & A40 & ".html") -> https://www.ssbuy.tw/detail_giftcode/dist/giftcodes/劍與遠征：啟程.html | E40: 《劍與遠征：啟程》是一款全球多平台的輕鬆放置大世界RPG遊戲，由放置始祖《劍與遠征》開發團隊所打造。 玩家將集結超過百位不同能力、各具魅力的英雄夥伴，與他們一起探索名為「伊索米亞」的廣闊大世界，並逐漸揭開其中秘辛 | F40: 進入主畫面，點選個人頭像 | G40: 進入設定（齒輪） | H40: 輸入禮包碼 → 確認兌換 | K40: afkjoshikatsu | L40: 200鑽石和金幣 | M40: MAGICAFKJOURNEY | N40: 200鑽石+金幣 | O40: AFKJomedetou | P40: 1000鑽和20000金幣 | Q40: AFKJCREATOR | R40: 100鑽和18888金幣 | S40: AFKJCOMMUNITY | T40: 100鑽和10000金幣
A41: 熱血大作戰 | B41: ="giftcodesbanner/" & A41 & "-bar.jpg" -> giftcodesbanner/熱血大作戰-bar.jpg | D41: =IF(A41="","", "https://www.ssbuy.tw/detail_giftcode/dist/giftcodes/" & IF(ISNUMBER(LEFT(A41,1)*1), "game-", "") & A41 & ".html") -> https://www.ssbuy.tw/detail_giftcode/dist/giftcodes/熱血大作戰.html | E41: 《熱血大作戰》是一款輕策略街機放置型RPG遊戲，它結合了經典復古的畫風和無厘頭的搞怪元素。 遊戲以熱血沸騰的戰鬥和獨特的玩法，讓玩家重溫經典遊戲的感動，並與朋友一同體驗遊戲的樂趣。 | F41: 進入主畫面，點選個人頭像 | G41: 進入設定（齒輪） | H41: 輸入禮包碼 → 確認兌換 | K41: rabbit2024 | L41: 三色寶箱 | M41: PREDLOPEN | N41: 綠寶箱、藍寶箱、四星碎片 | O41: NEKKETSU888 | P41: 綠色、藍色寶箱 | Q41: NEKKETSUBTL | R41: 三色寶箱、四星碎片 | S41: RANKTOP1 | T41: 包子箱*5、木材箱*3、銅幣箱*1、求賢令*1 | U41: NEKKETSU777 | V41: 2025商城元寶鑽石禮包 | W41: NEKKETSU666 | X41: 綠寶箱、藍寶箱
A42: 骷髏傳說：戰神崛起 | B42: ="giftcodesbanner/" & A42 & "-bar.jpg" -> giftcodesbanner/骷髏傳說：戰神崛起-bar.jpg | D42: =IF(A42="","", "https://www.ssbuy.tw/detail_giftcode/dist/giftcodes/" & IF(ISNUMBER(LEFT(A42,1)*1), "game-", "") & A42 & ".html") -> https://www.ssbuy.tw/detail_giftcode/dist/giftcodes/骷髏傳說：戰神崛起.html | E42: MMORPG遊戲，擁有英雄系統、豐富的戰鬥玩法、打寶交易機制，以及沙城爭霸等特色內容. 玩家可以自由搭配英雄，參與野外PK、奪寶、領地戰等活動，並透過交易系統進行道具和裝備的交易. | F42: 進入主畫面，點選個人頭像 | G42: 進入設定（齒輪） | H42: 輸入禮包碼 → 確認兌換 | K42: VIP666 | L42: 2025商城元寶鑽石禮包 | M42: VIP777 | N42: 2025商城元寶鑽石禮包 | O42: VIP888 | P42: 2025商城元寶鑽石禮包 | Q42: OpeningGift | R42: 2025商城元寶鑽石禮包 | S42: free777 | T42: 2025商城元寶鑽石禮包 | U42: code777 | V42: 2025商城元寶鑽石禮包 | W42: gift777 | X42: 2025商城元寶鑽石禮包 | Y42: mg777 | Z42: 2025商城元寶鑽石禮包 | AA42: SK777 | AB42: 2025商城元寶鑽石禮包 | AC42: Sol777 | AD42: 2025商城元寶鑽石禮包 | AE42: Loki777 | AF42: 2025商城元寶鑽石禮包 | AG42: Odin777 | AH42: 2025商城元寶鑽石禮包 | AI42: Freya777 | AJ42: 2025商城元寶鑽石禮包
A43: 黎明：血色魔女 | B43: ="giftcodesbanner/" & A43 & "-bar.jpg" -> giftcodesbanner/黎明：血色魔女-bar.jpg | D43: =IF(A43="","", "https://www.ssbuy.tw/detail_giftcode/dist/giftcodes/" & IF(ISNUMBER(LEFT(A43,1)*1), "game-", "") & A43 & ".html") -> https://www.ssbuy.tw/detail_giftcode/dist/giftcodes/黎明：血色魔女.html | E43: 隨著《黎明：血色魔女》的正式上線，遊戲內的五大職業特色也逐漸明朗。 擁有雙面形態的血色魔女，白天為聖潔修女，擅長偽裝偵查等末世生存技巧，而入夜則化身為手持大鐮刀的血色魔女，肆意收割魔物獲取血液，貫徹永恆的生存之道。 | F43: 進入主畫面，點選個人頭像 | G43: 進入設定（齒輪） | H43: 輸入禮包碼 → 確認兌換 | K43: reddawngo | L43: 2025商城元寶鑽石禮包 | M43: milestone100 | N43: 2025商城元寶鑽石禮包 | O43: reddawn0107 | P43: 2025商城元寶鑽石禮包 | Q43: reddawn666 | R43: 2025商城元寶鑽石禮包 | S43: milestone80 | T43: 2025商城元寶鑽石禮包 | U43: milestone50 | V43: 2025商城元寶鑽石禮包 | W43: milestone30 | X43: 2025商城元寶鑽石禮包 | Y43: milestone20 | Z43: 2025商城元寶鑽石禮包 | AA43: svip666 | AB43: 2025商城元寶鑽石禮包 | AC43: svip777 | AD43: 2025商城元寶鑽石禮包 | AE43: svip888 | AF43: 2025商城元寶鑽石禮包 | AG43: maze666 | AH43: 2025商城元寶鑽石禮包 | AI43: maze888 | AJ43: 2025商城元寶鑽石禮包
A44: 黎明啟示錄 | B44: ="giftcodesbanner/" & A44 & "-bar.jpg" -> giftcodesbanner/黎明啟示錄-bar.jpg | D44: =IF(A44="","", "https://www.ssbuy.tw/detail_giftcode/dist/giftcodes/" & IF(ISNUMBER(LEFT(A44,1)*1), "game-", "") & A44 & ".html") -> https://www.ssbuy.tw/detail_giftcode/dist/giftcodes/黎明啟示錄.html | E44: 有聲有色不俗套的英雄設定，超過90名來源於世界各地的神話人物與歷史大家齊聚一堂，不同信仰的夥伴助力你的異世界之旅！ | F44: 進入主畫面，點選個人頭像 | G44: 進入設定（齒輪） | H44: 輸入禮包碼 → 確認兌換 | K44: 888888 | L44: 2025商城元寶鑽石禮包 | M44: VJ5ZS6222M2 | N44: 2025商城元寶鑽石禮包 | O44: WANEQQ222MP | P44: 2025商城元寶鑽石禮包 | Q44: GTTBMN222MQ | R44: 2025商城元寶鑽石禮包 | S44: HCTACF222MR | T44: 2025商城元寶鑽石禮包 | U44: KFV6RJ222MV | V44: 2025商城元寶鑽石禮包 | W44: HATW3U222P2 | X44: 2025商城元寶鑽石禮包 | Y44: EJMGC7222P3 | Z44: 2025商城元寶鑽石禮包 | AA44: VAyuec222fc | AB44: 2025商城元寶鑽石禮包
A45: 龍魂旅人 | B45: ="giftcodesbanner/" & A45 & "-bar.jpg" -> giftcodesbanner/龍魂旅人-bar.jpg | D45: =IF(A45="","", "https://www.ssbuy.tw/detail_giftcode/dist/giftcodes/" & IF(ISNUMBER(LEFT(A45,1)*1), "game-", "") & A45 & ".html") -> https://www.ssbuy.tw/detail_giftcode/dist/giftcodes/龍魂旅人.html | E45: 一款日系輕鬆番RPG遊戲，玩家將作為失去力量的傳說之龍法夫納，與尋求幫助的傲嬌公主兼屠龍勇士齊格菲，一同穿梭在奇幻世界的相愛相殺之旅。 | F45: 進入主畫面，點選個人頭像 | G45: 進入設定（齒輪） | H45: 輸入禮包碼 → 確認兌換 | K45: SODGOGO250109 | L45: 2025商城元寶鑽石禮包 | M45: LETSPLAY250110 | N45: 2025商城元寶鑽石禮包 | O45: PRINCESS999 | P45: 2025商城元寶鑽石禮包 | Q45: KEEPGOING2511 | R45: 2025商城元寶鑽石禮包 | S45: ILOVESOD2512 | T45: 2025商城元寶鑽石禮包 | U45: SSRHERO888 | V45: 2025商城元寶鑽石禮包 | W45: opensod | X45: 2025商城元寶鑽石禮包 | Y45: HERO666 | Z45: 2025商城元寶鑽石禮包 | AA45: HERO777 | AB45: 2025商城元寶鑽石禮包 | AC45: HERO888 | AD45: 2025商城元寶鑽石禮包 | AE45: HERO999 | AF45: 2025商城元寶鑽石禮包 | AG45: LDP777 | AH45: 2025商城元寶鑽石禮包 | AI45: NOXSOD777 | AJ45: 2025商城元寶鑽石禮包
A46: 戀與深空 | B46: ="giftcodesbanner/" & A46 & "-bar.jpg" -> giftcodesbanner/戀與深空-bar.jpg | D46: =IF(A46="","", "https://www.ssbuy.tw/detail_giftcode/dist/giftcodes/" & IF(ISNUMBER(LEFT(A46,1)*1), "game-", "") & A46 & ".html") -> https://www.ssbuy.tw/detail_giftcode/dist/giftcodes/戀與深空.html | E46: 《戀與深空》以「︁愛無界限」︁為核心理念，在科幻宇宙背景下融合緊張刺激的怪物狩獵玩法。 玩家可與五位男主——秦徹，祁煜，黎深、沈星回以及夏以晝——建立情感羈絆。 玩家化身深空獵人，運用名為"Evol"的超能力對抗宇宙生命體"流浪體"。 | F46: 進入主畫面，點選個人頭像 | G46: 進入設定（齒輪） | H46: 輸入禮包碼 → 確認兌換 | K46: 3DLOVE | L46: 100粉鑽+一張極空許願券 | M46: love2024 | N46: 2025商城元寶鑽石禮包 | O46: LnDxLuca | P46: 2025商城元寶鑽石禮包 | Q46: LnDxUki | R46: 2025商城元寶鑽石禮包 | S46: 2025WOMENSDAY | T46: 2025商城元寶鑽石禮包 | U46: ZONGZI2025 | V46: 2025商城元寶鑽石禮包 | W46: DEEPSPACE4 | X46: 極空許願券 ×10 | Y46: HAPPINESS | Z46: 鑽石×200＋體力×200＋心願之瓶·稀有×520＋訂製頭飾·「全宇宙最幸福的人」 | AA46: 3DLOVE | AB46: 100粉鑽+一張極空許願券 | AC46: love2024 | AD46: 加速魔方*1+銀砂磁石*1 | AE46: LnDxUki | AF46: 心願之瓶·珍貴*5+金幣*20000+體力*50 | AG46: LnDxIke | AH46: 心願之瓶·珍貴*5+金幣*20000+體力*50 | AI46: LnDxLuca | AJ46: 心願之瓶·珍貴*5+金幣*20000+體力*50 | AK46: LnDxFulgur | AL46: 心願之瓶·珍貴*5+金幣*20000+體力*50 | AM46: LOVEDEEP1004 | AN46: 隨機虛寶或鑽石獎勵 | AO46: 100000FOLLOW | AP46: 隨機虛寶或鑽石獎勵
A47: 靈魂衝擊：無限放置 | B47: ="giftcodesbanner/" & A47 & "-bar.jpg" -> giftcodesbanner/靈魂衝擊：無限放置-bar.jpg | D47: =IF(A47="","", "https://www.ssbuy.tw/detail_giftcode/dist/giftcodes/" & IF(ISNUMBER(LEFT(A47,1)*1), "game-", "") & A47 & ".html") -> https://www.ssbuy.tw/detail_giftcode/dist/giftcodes/靈魂衝擊：無限放置.html | E47: 玩家將透過召喚職業與技能來殲滅蜂擁而至的怪物，稀有的職業將額外擁有特殊的被動技能屬性，可增加角色的暴擊傷害量或是閃避效果等 | F47: 進入主畫面，點選個人頭像 | G47: 進入設定（齒輪） | H47: 輸入禮包碼 → 確認兌換 | K47: WELCOME31 | L47: 2025商城元寶鑽石禮包 | M47: CONGRATS59 | N47: 2025商城元寶鑽石禮包 | O47: MASTERS29 | P47: 2025商城元寶鑽石禮包 | Q47: HAPPY2CU9 | R47: 2025商城元寶鑽石禮包 | S47: 100CLASS | T47: 2025商城元寶鑽石禮包
A48: 楓葉島 | B48: ="giftcodesbanner/" & A48 & "-bar.jpg" -> giftcodesbanner/楓葉島-bar.jpg | D48: =IF(A48="","", "https://www.ssbuy.tw/detail_giftcode/dist/giftcodes/" & IF(ISNUMBER(LEFT(A48,1)*1), "game-", "") & A48 & ".html") -> https://www.ssbuy.tw/detail_giftcode/dist/giftcodes/楓葉島.html | E48: 在一個叫礁石鎮的小鎮中，你緩緩醒來，走出門找到了本地村民，才知道是一個叫“米娜”的小姑娘救了你，得知礁石鎮是由有著同樣遭遇的冒險者們建立。 | F48: 進入主畫面，點選個人頭像 | G48: 進入設定（齒輪） | H48: 輸入禮包碼 → 確認兌換 | K48: laugh3 | L48: 2025商城元寶鑽石禮包 | M48: sleep3 | N48: 2025商城元寶鑽石禮包 | O48: rest2 | P48: 2025商城元寶鑽石禮包 | Q48: Spring | R48: 2025商城元寶鑽石禮包 | S48: Holiday | T48: 2025商城元寶鑽石禮包 | U48: 1month | V48: 2025商城元寶鑽石禮包 | W48: sweekend | X48: 2025商城元寶鑽石禮包 | Y48: onemore | Z48: 2025商城元寶鑽石禮包 | AA48: weekend | AB48: 2025商城元寶鑽石禮包 | AC48: guess1 | AD48: 2025商城元寶鑽石禮包
A49: 無名江湖 | B49: ="giftcodesbanner/" & A49 & "-bar.jpg" -> giftcodesbanner/無名江湖-bar.jpg | D49: =IF(A49="","", "https://www.ssbuy.tw/detail_giftcode/dist/giftcodes/" & IF(ISNUMBER(LEFT(A49,1)*1), "game-", "") & A49 & ".html") -> https://www.ssbuy.tw/detail_giftcode/dist/giftcodes/無名江湖.html | E49: 以收集百家武學為目標的放置類卡牌遊戲。 遊戲中，玩家可以體驗完整的俠客人生，拜師學藝，闖蕩江湖，一步步成為一代大俠的傳奇故事。 | F49: 進入主畫面，點選個人頭像 | G49: 進入設定（齒輪） | H49: 輸入禮包碼 → 確認兌換 | K49: SZFIZWJPFT | L49: 千機券*2+銅幣*10000 | M49: 5GCN93VZA8 | N49: 千機券:2+絕學武學殘卷:5 | O49: DTSDQ4RCQG | P49: 千機券:2+銅幣:10000 | Q49: FWWRM8E6I6 | R49: 千機券:2+絕學武學殘卷:5
A50: 萬妖領域 | B50: ="giftcodesbanner/" & A50 & "-bar.jpg" -> giftcodesbanner/萬妖領域-bar.jpg | D50: =IF(A50="","", "https://www.ssbuy.tw/detail_giftcode/dist/giftcodes/" & IF(ISNUMBER(LEFT(A50,1)*1), "game-", "") & A50 & ".html") -> https://www.ssbuy.tw/detail_giftcode/dist/giftcodes/萬妖領域.html | E50: 終身每日送10連抽，無限策略搭配，無損養成神將，帶給你前所未有的卡牌樂趣，獸戰到底，作妖捉妖隨你意！ 還在精打細算規劃資源，為抽不到喜歡的角色而發愁？ 史上最佛心的《萬妖領域》為您送上終生每日送10連抽，一年3650抽，讓你抽到嫑嫑！ | F50: 進入主畫面，點選個人頭像 | G50: 進入設定（齒輪） | H50: 輸入禮包碼 → 確認兌換 | K50: VIP666 | L50: 2025商城元寶鑽石禮包 | M50: VIP777 | N50: 2025商城元寶鑽石禮包 | O50: VIP888 | P50: 2025商城元寶鑽石禮包 | Q50: VIP999 | R50: 2025商城元寶鑽石禮包 | S50: hsu888 | T50: 2025商城元寶鑽石禮包 | U50: barry987 | V50: 2025商城元寶鑽石禮包 | W50: 3sg87 | X50: 2025商城元寶鑽石禮包 | Y50: cyuu | Z50: 2025商城元寶鑽石禮包
A51: 一姬當千TD | B51: ="giftcodesbanner/" & A51 & "-bar.jpg" -> giftcodesbanner/一姬當千TD-bar.jpg | D51: =IF(A51="","", "https://www.ssbuy.tw/detail_giftcode/dist/giftcodes/" & IF(ISNUMBER(LEFT(A51,1)*1), "game-", "") & A51 & ".html") -> https://www.ssbuy.tw/detail_giftcode/dist/giftcodes/一姬當千TD.html | E51: 這裡是一姬當千TD的官方中心，歡迎follow我們獲取最新的遊戲訊息。這是一款輕鬆趣味策略塔防遊戲，在遊戲中您將運用策略來合理佈局，通關不同難度的關卡。 | F51: 進入主畫面，點選個人頭像 | G51: 進入設定（齒輪） | H51: 輸入禮包碼 → 確認兌換 | K51: VIP666 | L51: 2025商城元寶鑽石禮包 | M51: VIP888 | N51: 2025商城元寶鑽石禮包 | O51: SSS66 | P51: 2025商城元寶鑽石禮包 | Q51: SSS88 | R51: 2025商城元寶鑽石禮包
A52: 劍客行 | B52: ="giftcodesbanner/" & A52 & "-bar.jpg" -> giftcodesbanner/劍客行-bar.jpg | D52: =IF(A52="","", "https://www.ssbuy.tw/detail_giftcode/dist/giftcodes/" & IF(ISNUMBER(LEFT(A52,1)*1), "game-", "") & A52 & ".html") -> https://www.ssbuy.tw/detail_giftcode/dist/giftcodes/劍客行.html | E52: 故事大綱 展白背負父親「霹雷劍」展雲天被五個結義兄弟以奸計密謀殺害的血海深仇，闖蕩江湖，學成天下第一奇書《鎖骨銷魂天佛卷》，終報父仇，並獨力對抗企圖一統中原武林的強大惡勢力「南海門」，除「三煞」，誅「四凶」，力挽狂瀾，創下赫赫聲名，最終與五個美艷動人的嬌妻隱居洞庭湖畔，成就武林傳奇，一時傳為佳話。 | F52: 進入主畫面，點選個人頭像 | G52: 進入設定（齒輪） | H52: 輸入禮包碼 → 確認兌換 | K52: 3PU7C5ROI | L52: 元寶x200、閱歷x2000 | M52: HRXY4LH1K | N52: 元寶x200、閱歷x2000
A53: 時之樹少女 | B53: ="giftcodesbanner/" & A53 & "-bar.jpg" -> giftcodesbanner/時之樹少女-bar.jpg | D53: =IF(A53="","", "https://www.ssbuy.tw/detail_giftcode/dist/giftcodes/" & IF(ISNUMBER(LEFT(A53,1)*1), "game-", "") & A53 & ".html") -> https://www.ssbuy.tw/detail_giftcode/dist/giftcodes/時之樹少女.html | E53: ❤ 殿下，你回來了!❤ | F53: 進入主畫面，點選個人頭像 | G53: 進入設定（齒輪） | H53: 輸入禮包碼 → 確認兌換 | K53: OPJS741 | L53: 龍玉*50 | 火焰果*5 | M53: QWSF852 | N53: 龍玉*50 | 地心蓮*5 | O53: MOKL789 | P53: 龍玉*50 | 黃土捲軸*5 | Q53: CVBN456 | R53: 龍玉*50 | 雷霆捲軸*5
A54: 錨點降臨Re：Code | B54: ="giftcodesbanner/" & A54 & "-bar.jpg" -> giftcodesbanner/錨點降臨Re：Code-bar.jpg | D54: =IF(A54="","", "https://www.ssbuy.tw/detail_giftcode/dist/giftcodes/" & IF(ISNUMBER(LEFT(A54,1)*1), "game-", "") & A54 & ".html") -> https://www.ssbuy.tw/detail_giftcode/dist/giftcodes/錨點降臨Re：Code.html | E54: 結合了半即時戰鬥和深度戰略玩法。 遊戲的背景設定在一場名為「修格爾戰爭」的異空間入侵戰爭之後，人類重建並復甦過來，並建立「空天星鏈」來防禦，利用「安比斯—鏈接系統」打造「戰員」。 玩家可以透過組成戰隊，利用技能與敵人屬性制定戰略，並透過源能技發動連攜攻擊，享受自由搭建的冒險旅程。 | F54: 進入主畫面，點選個人頭像 | G54: 進入設定（齒輪） | H54: 輸入禮包碼 → 確認兌換 | K54: 755B5Z53 | L54: 常規鏈接許可 ×1、泰諾幣 ×6000 | M54: GNNUJCU5 | N54: 高級作戰報告 ×6、汙染中和酊(小) ×1 | O54: 4NPMAMZ5 | P54: 常規鏈接許可 ×1、泰諾幣 ×6000 | Q54: 7NJTHNPW | R54: 常規鏈接許可 ×1、泰諾幣 ×6000 | S54: ENMBWTEM | T54: 源晶輝錠 ×30、汙染中和酊(中) ×1 | U54: EWB39Z5C | V54: 神血試劑α ×1、烙痕強化劑α ×8 | W54: FNVU2MGW | X54: 常規鏈接許可 ×1、泰諾幣 ×6000 | Y54: WNRM5BZU | Z54: 常規鏈接許可 ×1、泰諾幣 ×6000 | AA54: MNHCW5SZ | AB54: 源晶輝錠 ×30、汙染中和酊(中) ×1 | AC54: DU3UHBZ3 | AD54: 源晶輝錠 ×100 | AE54: PUMWGZ7W | AF54: 源晶輝錠 ×100 | AG54: AUUT858U | AH54: 源晶輝錠 ×100 | AI54: BUG5XNXT | AJ54: 源晶輝錠 ×100 | AK54: PU5MBCR5 | AL54: 源晶輝錠 ×100 | AM54: AUBNSW6M | AN54: 源晶輝錠 ×100 | AO54: MUGM935B | AP54: 源晶輝錠 ×100 | AQ54: 2TUBGU9W | AR54: 源晶輝錠 ×100 | AS54: RUMUYTAT | AT54: 源晶輝錠 ×100
A55: 神契氣靈師 | B55: ="giftcodesbanner/" & A55 & "-bar.jpg" -> giftcodesbanner/神契氣靈師-bar.jpg | D55: =IF(A55="","", "https://www.ssbuy.tw/detail_giftcode/dist/giftcodes/" & IF(ISNUMBER(LEFT(A55,1)*1), "game-", "") & A55 & ".html") -> https://www.ssbuy.tw/detail_giftcode/dist/giftcodes/神契氣靈師.html | E55: 以「氣靈師」作為其核心職業，遊戲特色包括自由選擇的玩法、BOSS挑戰、情緣系統等。 遊戲中，玩家可以與配對對象結為情緣，並在副本中携手進行挑戰，提升情緣度後更可獲得專屬同心戒和領養寶寶。 | F55: 進入主畫面，點選個人頭像 | G55: 進入設定（齒輪） | H55: 輸入禮包碼 → 確認兌換 | K55: VIP666 | L55: 坐騎進階丹*10、銅錢*100000 | M55: VIP777 | N55: 寵物進階丹*10、銅錢*200000 | O55: VIP888 | P55: 坐騎靈魄*2、寵物靈魄*2、銅錢*300000 | Q55: SVIP666 | R55: 坐騎靈魄*3、寵物靈魄*3 | S55: SVIP777 | T55: 坐騎祝福卷軸*1、寵物祝福卷軸*1 | U55: SVIP888 | V55: 綁定元寶*500 | W55: JUDY888 | X55: 綁定元寶*500 | Y55: QQ666 | Z55: 2倍經驗符、銅幣200W | AA55: QQ777 | AB55: 翅膀升級丹·初級*10、裝備尋寶鑰匙*10 | AC55: QQ888 | AD55: 綁定元寶*300 | AE55: DOG777 | AF55: 寵物進階丹*20、世界BOSS挑戰令*2 | AG55: LUCKY177 | AH55: 銅錢*100萬 | AI55: LUCKY577 | AJ55: 寶石禮包Lv.4*1 | AK55: LUCKY777 | AL55: 2倍經驗符*2 | AM55: LUCKY977 | AN55: 寵物-忍者兔俠*1 | AO55: LUCKY888 | AP55: 100億鑽石
A56: 不休旅途：繪卷世界 | B56: ="giftcodesbanner/" & A56 & "-bar.jpg" -> giftcodesbanner/不休旅途：繪卷世界-bar.jpg | D56: =IF(A56="","", "https://www.ssbuy.tw/detail_giftcode/dist/giftcodes/" & IF(ISNUMBER(LEFT(A56,1)*1), "game-", "") & A56 & ".html") -> https://www.ssbuy.tw/detail_giftcode/dist/giftcodes/不休旅途：繪卷世界.html | E56: 你被神秘力量召喚，降臨這片充滿奇幻與挑戰的大地。從新手村到浮空島，從炙熱沙漠到幽深遺跡…… 每一次探索，都是一場全新的發現！這個世界大妖肆虐，動蕩不安。為了保護這個世界的和平與安寧，你召喚出繪卷中的各種夥伴，在這裡，你可以與夥伴締結羈絆，騎乘靈獸奔馳世界，一同踏上打倒大妖的冒險旅途，揭開塵封的秘密！ | F56: 進入主畫面，點選個人頭像 | G56: 進入設定（齒輪） | H56: 輸入禮包碼 → 確認兌換 | K56: storeno1 | L56: 魔晶*388、召喚铃*5、玉蝉子*3、裝備鍛造石*30、裝備強化石*30 | M56: ALEX888 | O56: CONYSU888 | Q56: NICK888 | R56: 2025商城元寶鑽石禮包 | S56: BX666 | T56: 魔晶*100、裝備鍛造石*50 | U56: BX2025 | V56: 魔晶*50、裝備鍛造石*30、裝備強化石*30 | W56: PMBX888 | X56: 魔晶*50、裝備鍛造石*30、裝備強化石*30 | Y56: TCXJ888 | Z56: 魔晶*50、裝備鍛造石*30、裝備強化石*30 | AA56: welcomeline | AB56: 魔晶*100、裝備鍛造石*30、裝備強化石*30 | AC56: YUNSII888 | AD56: 魔晶*50、裝備鍛造石*30、裝備強化石*30
A57: 別破防鴨 | B57: ="giftcodesbanner/" & A57 & "-bar.jpg" -> giftcodesbanner/別破防鴨-bar.jpg | D57: =IF(A57="","", "https://www.ssbuy.tw/detail_giftcode/dist/giftcodes/" & IF(ISNUMBER(LEFT(A57,1)*1), "game-", "") & A57 & ".html") -> https://www.ssbuy.tw/detail_giftcode/dist/giftcodes/別破防鴨.html | E57: 寂靜的森林裡，鴨子弓箭手們已準備好守護森林！ 巨量怪物來襲！鴨子莊園危在旦夕！ | F57: 進入主畫面，點選個人頭像 | G57: 進入設定（齒輪） | H57: 輸入禮包碼 → 確認兌換 | K57: springgift | L57: 💎 3000 鑽石 | M57: happyonline2025 | N57: 💎 2000 鑽石🎫 2 張首領挑戰卷 | O57: duckk | P57: 💎 3000 鑽石 | Q57: ducky | R57: 💎 3000 鑽石 | S57: duck2025 | T57: 💎 500 鑽石、🏹 10 箭矢補給石 | U57: DUCK666 | V57: 💎 1000 鑽石 | W57: DUCK777 | X57: 🏹 20 箭矢補給石 | Y57: DUCK888 | Z57: 🎟 5 首領挑戰券 | AA57: DUCK999 | AB57: 🎟 5 首領挑戰券 | AC57: DUCK555 | AD57: 🎟 5 首領挑戰券 | AE57: DUCK333 | AF57: 💎 1000 鑽石 | AG57: GUAGUA888 | AH57: 🏹 20 箭矢補給石
A58: 超派救星幫幫忙 | B58: ="giftcodesbanner/" & A58 & "-bar.jpg" -> giftcodesbanner/超派救星幫幫忙-bar.jpg | D58: =IF(A58="","", "https://www.ssbuy.tw/detail_giftcode/dist/giftcodes/" & IF(ISNUMBER(LEFT(A58,1)*1), "game-", "") & A58 & ".html") -> https://www.ssbuy.tw/detail_giftcode/dist/giftcodes/超派救星幫幫忙.html | E58: 是一款全新世代的割草遊戲，將背包管理與彈幕射擊結合。 遊戲的目標是讓玩家在戰鬥中找到腦力與操作的平衡，最大化戰鬥力以戰勝一波波殭屍海。 玩家需要合理分配資源，並進行戰略性思考，才能在遊戲中生存下去。 | F58: 進入主畫面，點選個人頭像 | G58: 進入設定（齒輪） | H58: 輸入禮包碼 → 確認兌換 | K58: VIP666 | L58: 強大物資 | M58: VIP777 | N58: 強大物資 | O58: VIP888 | P58: 強大物資
A59: 時光大爆炸 | B59: ="giftcodesbanner/" & A59 & "-bar.jpg" -> giftcodesbanner/時光大爆炸-bar.jpg | D59: =IF(A59="","", "https://www.ssbuy.tw/detail_giftcode/dist/giftcodes/" & IF(ISNUMBER(LEFT(A59,1)*1), "game-", "") & A59 & ".html") -> https://www.ssbuy.tw/detail_giftcode/dist/giftcodes/時光大爆炸.html | E59: 穿梭燦爛文明 開啟奇幻之旅，一起體驗從石器時代、到蒸汽時代的多文明經營之路吧~ | F59: 進入主畫面，點選個人頭像 | G59: 進入設定（齒輪） | H59: 輸入禮包碼 → 確認兌換 | K59: AAFB5000 | L59: 2025商城元寶鑽石禮包 | M59: AFBA10K | N59: 2025商城元寶鑽石禮包 | O59: AFB25KA | P59: 2025商城元寶鑽石禮包 | Q59: BOOM888 | R59: 2025商城元寶鑽石禮包 | S59: POWER666 | T59: 2025商城元寶鑽石禮包 | U59: HUZI888 | V59: 2025商城元寶鑽石禮包 | W59: PINK000 | X59: 2025商城元寶鑽石禮包 | Y59: AJH777 | Z59: 2025商城元寶鑽石禮包 | AA59: BIG999 | AB59: 2025商城元寶鑽石禮包
A60: 深淵：不滅者 | B60: ="giftcodesbanner/" & A60 & "-bar.jpg" -> giftcodesbanner/深淵：不滅者-bar.jpg | D60: =IF(A60="","", "https://www.ssbuy.tw/detail_giftcode/dist/giftcodes/" & IF(ISNUMBER(LEFT(A60,1)*1), "game-", "") & A60 & ".html") -> https://www.ssbuy.tw/detail_giftcode/dist/giftcodes/深淵：不滅者.html | E60: 融合修仙、獸化與深淵副本的暗黑系RPG手遊。 玩家將從地獄深淵重生，透過獸化之道，一路突破地獄層級，踏上復仇之路。 遊戲特色包括：挑戰多樣深淵領主與異鬼妖獸，支援組隊擊殺Boss，孵化、馴養、進化各種強大鬼寵，以及獨特的獸化系統。 | F60: 進入主畫面，點選個人頭像 | G60: 進入設定（齒輪） | H60: 輸入禮包碼 → 確認兌換 | K60: HAPPYFOOL | L60: 綁定仙玉×50、赤雷劍靈×1 | M60: PLAYNOW | N60: 綁定仙玉×50、中級神兵精華×2 | O60: wk467 | P60: 坐騎進階丹×5、2級長生寶石×1 | Q60: BLESS44 | R60: 坐騎進階丹×5、護送令×5 | S60: VIP555 | T60: 綁定仙玉×50、洗鍊凝露×5 | U60: VIP666 | V60: 綁定仙玉×50、洗鍊凝露×5 | W60: VIP777 | X60: 綁定仙玉×50、神魔通行證×1 | Y60: VIP888 | Z60: 綁定仙玉×50、神魔通行證×1 | AA60: VIP999 | AB60: 綁定仙玉×50、神魔通行證×1 | AC60: SVIP666 | AD60: 綁定仙玉×50、神魔通行證×1 | AE60: SVIP777 | AF60: 綁定仙玉×50、神魔通行證×1 | AG60: SVIP888 | AH60: 綁定仙玉×50、神魔通行證×1 | AI60: SVIP999 | AJ60: 綁定仙玉×50、神魔通行證×1
A61: Last War | B61: ="giftcodesbanner/" & A61 & "-bar.jpg" -> giftcodesbanner/Last War-bar.jpg | D61: =IF(A61="","", "https://www.ssbuy.tw/detail_giftcode/dist/giftcodes/" & IF(ISNUMBER(LEFT(A61,1)*1), "game-", "") & A61 & ".html") -> https://www.ssbuy.tw/detail_giftcode/dist/giftcodes/Last War.html | E61: 生存策略遊戲，玩家在末日世界中，需要抵抗大量的殭屍，並建立基地、培養軍隊，與其他玩家合作或競爭。 這款遊戲強調團隊合作，玩家可以建立同盟，一起進行集結作戰，例如攻下高階城池或挑戰BOSS，以獲得經驗值和戰力提升。 遊戲的目標是成為世界最強的指揮官，在末日世界中存活下來並取得勝利。 | F61: 進入主畫面，點選個人頭像 | G61: 進入設定（齒輪） | H61: 輸入禮包碼 → 確認兌換 | K61: LWDC400K | L61: 隨機虛寶或鑽石獎勵
A62: 勇士不要停 | B62: ="giftcodesbanner/" & A62 & "-bar.jpg" -> giftcodesbanner/勇士不要停-bar.jpg | D62: =IF(A62="","", "https://www.ssbuy.tw/detail_giftcode/dist/giftcodes/" & IF(ISNUMBER(LEFT(A62,1)*1), "game-", "") & A62 & ".html") -> https://www.ssbuy.tw/detail_giftcode/dist/giftcodes/勇士不要停.html | E62: 3D 放置卡牌遊戲，玩家可以在其中輕鬆掛機、躺平，享受隨玩隨停的戰鬥樂趣。 遊戲的特色包括多元的玩法、輕鬆的放置養成、以及豐富的卡牌收集和陣容搭配。 | F62: 進入主畫面，點選個人頭像 | G62: 進入設定（齒輪） | H62: 輸入禮包碼 → 確認兌換 | K62: SAN777 | L62: 隨機虛寶或鑽石獎勵 | M62: SAN888 | N62: 隨機虛寶或鑽石獎勵 | O62: SAN999 | P62: 隨機虛寶或鑽石獎勵 | Q62: HERO666 | R62: 隨機虛寶或鑽石獎勵 | S62: HERO777 | T62: 隨機虛寶或鑽石獎勵 | U62: HERO888 | V62: 隨機虛寶或鑽石獎勵 | W62: HERO2025 | X62: 隨機虛寶或鑽石獎勵 | Y62: VIP666 | Z62: 隨機虛寶或鑽石獎勵 | AA62: VIP777 | AB62: 隨機虛寶或鑽石獎勵 | AC62: VIP888 | AD62: 隨機虛寶或鑽石獎勵 | AE62: VIP2025 | AF62: 隨機虛寶或鑽石獎勵 | AG62: LINDA666 | AH62: 隨機虛寶或鑽石獎勵 | AI62: LINDA777 | AJ62: 隨機虛寶或鑽石獎勵 | AK62: LINDA888 | AL62: 隨機虛寶或鑽石獎勵 | AM62: LINDA999 | AN62: 隨機虛寶或鑽石獎勵
A63: 元氣火柴人 | B63: ="giftcodesbanner/" & A63 & "-bar.jpg" -> giftcodesbanner/元氣火柴人-bar.jpg | D63: =IF(A63="","", "https://www.ssbuy.tw/detail_giftcode/dist/giftcodes/" & IF(ISNUMBER(LEFT(A63,1)*1), "game-", "") & A63 & ".html") -> https://www.ssbuy.tw/detail_giftcode/dist/giftcodes/元氣火柴人.html | E63: 它延續了火柴人經典IP，採用可愛Q萌的畫風，讓玩家在放置掛機的過程中體驗輕鬆的樂趣。 遊戲中，玩家可以選擇不同職業的角色，並透過放置掛機快速升級，自動戰鬥推圖，以及輕鬆升級裝備神器。 | F63: 進入主畫面，點選個人頭像 | G63: 進入設定（齒輪） | H63: 輸入禮包碼 → 確認兌換 | K63: VIP666 | L63: 隨機虛寶或鑽石獎勵 | M63: VIP777 | N63: 隨機虛寶或鑽石獎勵 | O63: VIP888 | P63: 隨機虛寶或鑽石獎勵 | Q63: VIP999 | R63: 隨機虛寶或鑽石獎勵 | S63: Honey666 | T63: 隨機虛寶或鑽石獎勵 | U63: ET666 | V63: 隨機虛寶或鑽石獎勵 | W63: ET888 | X63: 隨機虛寶或鑽石獎勵 | Y63: PDLOPEN | Z63: 隨機虛寶或鑽石獎勵 | AA63: Vinson666 | AB63: 隨機虛寶或鑽石獎勵 | AC63: STM1212 | AD63: 隨機虛寶或鑽石獎勵 | AE63: K7666 | AF63: 隨機虛寶或鑽石獎勵 | AG63: LINDA666 | AH63: 隨機虛寶或鑽石獎勵 | AI63: LINDA888 | AJ63: 隨機虛寶或鑽石獎勵 | AK63: HL666 | AL63: 隨機虛寶或鑽石獎勵 | AM63: HL888 | AN63: 隨機虛寶或鑽石獎勵 | AO63: GENKISTM | AP63: 隨機虛寶或鑽石獎勵 | AQ63: MintCat666 | AR63: 隨機虛寶或鑽石獎勵 | AS63: Kzee666 | AT63: 隨機虛寶或鑽石獎勵 | AU63: JIGG666 | AV63: 隨機虛寶或鑽石獎勵 | AW63: BAXUAN666 | AX63: 隨機虛寶或鑽石獎勵
A64: 深淵之影 | B64: ="giftcodesbanner/" & A64 & "-bar.jpg" -> giftcodesbanner/深淵之影-bar.jpg | D64: =IF(A64="","", "https://www.ssbuy.tw/detail_giftcode/dist/giftcodes/" & IF(ISNUMBER(LEFT(A64,1)*1), "game-", "") & A64 & ".html") -> https://www.ssbuy.tw/detail_giftcode/dist/giftcodes/深淵之影.html | E64: 以西方魔幻為主題的俯視角動作Roguelike遊戲。 你將在遊戲裡扮演戰士、刺客、法師等角色，深入光影交錯的地牢世界，剷除那些肆虐家園的怪物。 做好準備，走進眼前的深淵吧！ 鐵匠之子亞瑟從小居住的村莊遭到大量魔物入侵肆虐，最終被熊熊火焰所吞噬。 | F64: 進入主畫面，點選個人頭像 | G64: 進入設定（齒輪） | H64: 輸入禮包碼 → 確認兌換 | K64: SOTDGIFT | L64: 1k 鑽石 | M64: shadow2024 | N64: 隨機虛寶或鑽石獎勵
A65: 玩星派對 | B65: ="giftcodesbanner/" & A65 & "-bar.jpg" -> giftcodesbanner/玩星派對-bar.jpg | D65: =IF(A65="","", "https://www.ssbuy.tw/detail_giftcode/dist/giftcodes/" & IF(ISNUMBER(LEFT(A65,1)*1), "game-", "") & A65 & ".html") -> https://www.ssbuy.tw/detail_giftcode/dist/giftcodes/玩星派對.html | E65: 多元化的派對樂園平台，擁有各種類型的遊戲等您來挑戰！ 不僅如此，更有豐富的養成元素，讓您可以培養自己的卡牌角色，獲得豐厚獎勵，並且與卡牌角色建立深厚的感情。 全台第一娛樂樂園，收納各種類型的派對遊戲等您來挑戰！ | F65: 進入主畫面，點選個人頭像 | G65: 進入設定（齒輪） | H65: 輸入禮包碼 → 確認兌換 | K65: helloline | L65: 隨機虛寶或鑽石獎勵 | M65: 200linefans | N65: 隨機虛寶或鑽石獎勵 | O65: LINE0294 | P65: 隨機虛寶或鑽石獎勵 | Q65: 400LINEFANS | R65: 隨機虛寶或鑽石獎勵 | S65: 500LINEFANS | T65: 隨機虛寶或鑽石獎勵 | U65: 600LINEFANS | V65: 隨機虛寶或鑽石獎勵
A66: 進化吧!我的人生 | B66: ="giftcodesbanner/" & A66 & "-bar.jpg" -> giftcodesbanner/進化吧!我的人生-bar.jpg | D66: =IF(A66="","", "https://www.ssbuy.tw/detail_giftcode/dist/giftcodes/" & IF(ISNUMBER(LEFT(A66,1)*1), "game-", "") & A66 & ".html") -> https://www.ssbuy.tw/detail_giftcode/dist/giftcodes/進化吧!我的人生.html | E66: 本遊戲未涉及任何情節，依遊戲軟體分級辦法分類為普遍級。​本遊戲為免費軟體，另外提供付費加值服務購買虛擬物品。​長時間進行遊戲，請注意使用時間，避免沉迷於遊戲。並已於數位娛樂軟體分級登錄 | F66: 進入主畫面，點選個人頭像 | G66: 進入設定（齒輪） | H66: 輸入禮包碼 → 確認兌換 | K66: BEAUTYEYE1 | L66: 經典造型美瞳券 * 1 | M66: EYEBROW3 | N66: 經典造型眉毛券 * 3 | O66: DESS2566 | P66: 技能召喚券 x36 | Q66: TAKECARE61 | R66: 寶箱x200 | S66: DRAGON666 | T66: 水晶 x450 | U66: VIP666 | V66: 隨機虛寶或鑽石獎勵 | W66: SORRY2512 | X66: 水晶*2000 | Y66: 520MOM2026 | Z66: 寶箱 x520
A67: 星之夢幻島 | B67: ="giftcodesbanner/" & A67 & "-bar.jpg" -> giftcodesbanner/星之夢幻島-bar.jpg | D67: =IF(A67="","", "https://www.ssbuy.tw/detail_giftcode/dist/giftcodes/" & IF(ISNUMBER(LEFT(A67,1)*1), "game-", "") & A67 & ".html") -> https://www.ssbuy.tw/detail_giftcode/dist/giftcodes/星之夢幻島.html | E67: 擁有高自由度的森林系輕度冒 險MMORPG，玩家可以運用靈活切換武器的技巧，來 討伐BOSS，或是在廣闊的世界中，享受生活模式玩法 ，獲得意想不到的樂趣。 | F67: 進入主畫面，點選個人頭像 | G67: 進入設定（齒輪） | H67: 輸入禮包碼 → 確認兌換 | K67: Lucky66 | L67: 隨機虛寶或鑽石獎勵 | M67: Lucky666 | N67: 隨機虛寶或鑽石獎勵 | O67: Lucky777 | P67: 隨機虛寶或鑽石獎勵 | Q67: Lucky168 | R67: 隨機虛寶或鑽石獎勵 | S67: Star9527 | T67: 隨機虛寶或鑽石獎勵 | U67: Lucky88 | V67: 隨機虛寶或鑽石獎勵 | W67: GameOn | X67: 隨機虛寶或鑽石獎勵
A68: 小冰冰傳奇：回到最初 | B68: ="giftcodesbanner/" & A68 & "-bar.jpg" -> giftcodesbanner/小冰冰傳奇：回到最初-bar.jpg | D68: =IF(A68="","", "https://www.ssbuy.tw/detail_giftcode/dist/giftcodes/" & IF(ISNUMBER(LEFT(A68,1)*1), "game-", "") & A68 & ".html") -> https://www.ssbuy.tw/detail_giftcode/dist/giftcodes/小冰冰傳奇：回到最初.html | E68: 遊戲以魔幻生物橫行的傳奇大陸為背景，承載著十年青春回憶的經典英雄陸續登場。 玩家在遊戲中將透過策略搭配英雄陣容，改變戰局，體驗策略遊戲的戰鬥快感。 | F68: 進入主畫面，點選個人頭像 | G68: 進入設定（齒輪） | H68: 輸入禮包碼 → 確認兌換 | K68: greedisgood | L68: 隨機虛寶或鑽石獎勵 | M68: randomdraft | N68: 隨機虛寶或鑽石獎勵 | O68: whosyourdaddy | P68: 隨機虛寶或鑽石獎勵 | Q68: showmethemoney | R68: 隨機虛寶或鑽石獎勵 | S68: snipergogo | T68: 隨機虛寶或鑽石獎勵 | U68: VIP666 | V68: 隨機虛寶或鑽石獎勵 | W68: VIP777 | X68: 隨機虛寶或鑽石獎勵 | Y68: VIP888 | Z68: 隨機虛寶或鑽石獎勵 | AA68: w5jwurfznd | AB68: 隨機虛寶或鑽石獎勵
A69: 江湖風雲傳 | B69: ="giftcodesbanner/" & A69 & "-bar.jpg" -> giftcodesbanner/江湖風雲傳-bar.jpg | D69: =IF(A69="","", "https://www.ssbuy.tw/detail_giftcode/dist/giftcodes/" & IF(ISNUMBER(LEFT(A69,1)*1), "game-", "") & A69 & ".html") -> https://www.ssbuy.tw/detail_giftcode/dist/giftcodes/江湖風雲傳.html | E69: 融合經典武俠與復古像素風格的手機RPG，讓玩家體驗快意恩仇的江湖世界。 | F69: 進入主畫面，點選個人頭像 | G69: 進入設定（齒輪） | H69: 輸入禮包碼 → 確認兌換 | K69: MAOBT1 | L69: 金幣 10,000 + 鑽石 100 | M69: MAOBT22 | N69: 隨機裝備寶箱 x1 | O69: TOJ777 | P69: 每日獎勵加倍
A70: 星願之冠：狼少女物語 | B70: ="giftcodesbanner/" & A70 & "-bar.jpg" -> giftcodesbanner/星願之冠：狼少女物語-bar.jpg | D70: =IF(A70="","", "https://www.ssbuy.tw/detail_giftcode/dist/giftcodes/" & IF(ISNUMBER(LEFT(A70,1)*1), "game-", "") & A70 & ".html") -> https://www.ssbuy.tw/detail_giftcode/dist/giftcodes/星願之冠：狼少女物語.html | E70: 是一款由SuperPlanet 推出的3D 放置養成遊戲，結合了塔防元素與角色成長系統。 玩家將扮演平凡的狼少女「帕依」，在魔王統治的混亂世界中，被王冠選中，展開拯救自然樂園的冒險旅程。 | F70: 進入主畫面，點選個人頭像 | G70: 進入設定（齒輪） | H70: 輸入禮包碼 → 確認兌換 | K70: CROWN888 | L70: 大量寶石和金幣 | M70: WOLFGIRL777 | N70: 強化道具和高級裝備材料 | O70: KNIGHT500 | P70: 角色經驗加成道具
A71: 香蕉缺個芭樂 | B71: ="giftcodesbanner/" & A71 & "-bar.jpg" -> giftcodesbanner/香蕉缺個芭樂-bar.jpg | D71: =IF(A71="","", "https://www.ssbuy.tw/detail_giftcode/dist/giftcodes/" & IF(ISNUMBER(LEFT(A71,1)*1), "game-", "") & A71 & ".html") -> https://www.ssbuy.tw/detail_giftcode/dist/giftcodes/香蕉缺個芭樂.html | E71: 是一款無厘頭惡搞風的植物合成塔防遊戲。 遊戲中，玩家可以操控各種可愛的水果英雄，進行合成和雜交，培育出更強大的植物。 此外，遊戲還包含塔防、組隊戰鬥等玩法，讓玩家可以體驗到不同的遊戲樂趣。 | F71: 進入主畫面，點選個人頭像 | G71: 進入設定（齒輪） | H71: 輸入禮包碼 → 確認兌換 | K71: SUNFLOWERTD | L71: 生命之種x1, 物理植物精華 | M71: BANANA666 | N71: 隨機虛寶或鑽石獎勵 | O71: APPLE777 | P71: 隨機虛寶或鑽石獎勵 | Q71: PEACH888 | R71: 隨機虛寶或鑽石獎勵 | S71: SFGROUP | T71: 植物材料鑰匙x1, 體力x20 | U71: B5D9SF | V71: 隨機虛寶或鑽石獎勵 | W71: VWX9HT | X71: 隨機虛寶或鑽石獎勵 | Y71: VALENTINESF | Z71: 隨機虛寶或鑽石獎勵 | AA71: SFT25E | AB71: 隨機虛寶或鑽石獎勵 | AC71: SFWP2S | AD71: 隨機虛寶或鑽石獎勵 | AE71: SFNYEAR25 | AF71: 隨機虛寶或鑽石獎勵 | AG71: WSF128 | AH71: 隨機虛寶或鑽石獎勵 | AI71: WDK121 | AJ71: 隨機虛寶或鑽石獎勵 | AK71: SFJWK1 | AL71: 隨機虛寶或鑽石獎勵 | AM71: WKSF31 | AN71: 隨機虛寶或鑽石獎勵 | AO71: SFNewYear25 | AP71: 高級裝備鑰匙x1, 生命之種x1, 體力x10 | AQ71: WEEKEND1 | AR71: 隨機虛寶或鑽石獎勵 | AS71: SFXMAS | AT71: 隨機虛寶或鑽石獎勵
A72: 精靈塔塔開 | B72: ="giftcodesbanner/" & A72 & "-bar.jpg" -> giftcodesbanner/精靈塔塔開-bar.jpg | D72: =IF(A72="","", "https://www.ssbuy.tw/detail_giftcode/dist/giftcodes/" & IF(ISNUMBER(LEFT(A72,1)*1), "game-", "") & A72 & ".html") -> https://www.ssbuy.tw/detail_giftcode/dist/giftcodes/精靈塔塔開.html | E72: 《精靈塔塔開》是一款結合塔防和自走棋元素的策略對戰手遊，遊戲以魔幻為主題，玩家可以選擇法師、弓箭手、戰士、牧師、召喚師等多種職業，搭配上百張卡牌組建最強戰隊，在戰場上與敵人進行對戰。 | F72: 進入主畫面，點選個人頭像 | G72: 進入設定（齒輪） | H72: 輸入禮包碼 → 確認兌換 | K72: ChristmasGift | L72: 隨機虛寶或鑽石獎勵
A73: 終末之歌 | B73: ="giftcodesbanner/" & A73 & "-bar.jpg" -> giftcodesbanner/終末之歌-bar.jpg | D73: =IF(A73="","", "https://www.ssbuy.tw/detail_giftcode/dist/giftcodes/" & IF(ISNUMBER(LEFT(A73,1)*1), "game-", "") & A73 & ".html") -> https://www.ssbuy.tw/detail_giftcode/dist/giftcodes/終末之歌.html | E73: 《終末之歌》是一款基於三國題材的豎版塔防割草遊戲，融合了roguelike 元素，提供玩家多樣化的戰鬥體驗。 遊戲將三國時期的武將以全新的方式呈現，玩家可以收集資源培養武將，並透過戰鬥和副本來體驗三國歷史。 | F73: 進入主畫面，點選個人頭像 | G73: 進入設定（齒輪） | H73: 輸入禮包碼 → 確認兌換 | K73: ESG1234 | L73: 名將招募令*3 | M73: ESG5678 | N73: 武將突破丹*5 | O73: ESG9999 | P73: 隨機虛寶或鑽石獎勵
A74: 森靈奇境 | B74: ="giftcodesbanner/" & A74 & "-bar.jpg" -> giftcodesbanner/森靈奇境-bar.jpg | D74: =IF(A74="","", "https://www.ssbuy.tw/detail_giftcode/dist/giftcodes/" & IF(ISNUMBER(LEFT(A74,1)*1), "game-", "") & A74 & ".html") -> https://www.ssbuy.tw/detail_giftcode/dist/giftcodes/森靈奇境.html | E74: 「森靈奇境」是由FUNFUN TECHNOLOGU CO.,LIMITED代理發行的角色扮演類遊戲。 在這個奇幻森林中，無限自由的職業選擇讓你可以隨心轉職，沒有任何限制！ 透過最尖端的次世代技術和全開放式全景大地圖，以全3D視角自由運作，滿足你對大世界的一切幻想。 本文將給各位玩家介紹初學者在電腦上的玩法。 | F74: 進入主畫面，點選個人頭像 | G74: 進入設定（齒輪） | H74: 輸入禮包碼 → 確認兌換 | K74: VIP666 | L74: 金幣500、藍色裝備捲軸5 | M74: VIP777 | N74: 體力20、金幣200 | O74: VIP888 | P74: 白銀寶箱鑰匙*3 | Q74: LDPLAYER2025 | R74: 元寶75、坐騎進階石10、10萬金幣*5 | S74: SLQJ2025 | T74: 元寶100、坐騎進階石20、金幣*50萬 | U74: FORESTGIFT | V74: 稀有裝備寶箱1、經驗藥水5 | W74: DEERSPIRIT | X74: 幻獸召喚券2、技能點數10 | Y74: group2024 | Z74: 隨機虛寶或鑽石獎勵 | AA74: SSSVIP666 | AB74: 隨機虛寶或鑽石獎勵 | AC74: NewYear666 | AD74: 隨機虛寶或鑽石獎勵 | AE74: Merry888 | AF74: 隨機虛寶或鑽石獎勵
A75: 鬥破蒼穹：蕭門篇 | B75: ="giftcodesbanner/" & A75 & "-bar.jpg" -> giftcodesbanner/鬥破蒼穹：蕭門篇-bar.jpg | D75: =IF(A75="","", "https://www.ssbuy.tw/detail_giftcode/dist/giftcodes/" & IF(ISNUMBER(LEFT(A75,1)*1), "game-", "") & A75 & ".html") -> https://www.ssbuy.tw/detail_giftcode/dist/giftcodes/鬥破蒼穹：蕭門篇.html | E75: 《鬥破蒼穹：蕭門篇》是一款由Flyburst發行的角色扮演手遊，改編自同名經典玄幻小說。 遊戲完美還原了小說中的斗氣大陸，玩家將扮演主角蕭炎，從一個默默無聞的少年，一步步成長為強大的鬥帝。 | F75: 進入主畫面，點選個人頭像 | G75: 進入設定（齒輪） | H75: 輸入禮包碼 → 確認兌換 | K75: elfds0106 | L75: 隨機虛寶或鑽石獎勵 | M75: Fight1226 | N75: 隨機虛寶或鑽石獎勵 | O75: Fight1week | P75: 隨機虛寶或鑽石獎勵 | Q75: Happy2025 | R75: 靈石*2025；異火種子*888；鳳羽*66 | S75: NewYear25 | T75: 靈石*800；夥伴抽獎券*20；挑戰狀*3 | U75: wpefs1230 | V75: 隨機虛寶或鑽石獎勵 | W75: DAY01 | X75: 隨機虛寶或鑽石獎勵 | Y75: DAY02 | Z75: 隨機虛寶或鑽石獎勵 | AA75: DP666 | AB75: 靈石*300；轉蛋券*5 | AC75: DP777 | AD75: 隨機虛寶或鑽石獎勵 | AE75: DP888 | AF75: 隨機虛寶或鑽石獎勵
A76: 無畏的狼煙 | B76: ="giftcodesbanner/" & A76 & "-bar.jpg" -> giftcodesbanner/無畏的狼煙-bar.jpg | D76: =IF(A76="","", "https://www.ssbuy.tw/detail_giftcode/dist/giftcodes/" & IF(ISNUMBER(LEFT(A76,1)*1), "game-", "") & A76 & ".html") -> https://www.ssbuy.tw/detail_giftcode/dist/giftcodes/無畏的狼煙.html | E76: 《無畏的狼煙》（Fearless Signals）是一款2D放置卡牌遊戲，以歐美潮流塗鴉風格呈現魔幻世界觀。 遊戲中，玩家將扮演領主，率領各族英雄與邪惡勢力作戰，重建大陸，擊退黑暗女神的入侵。 | F76: 進入主畫面，點選個人頭像 | G76: 進入設定（齒輪） | H76: 輸入禮包碼 → 確認兌換 | K76: FEARLESS2024 | L76: 500鑽石，5個高級召喚卷 | M76: WELCOMEFS | N76: 300鑽石，3個高級召喚卷 | O76: NEWPLAYER | P76: 200鑽石，2個高級召喚卷
A77: 代號：無頭 | B77: ="giftcodesbanner/" & A77 & "-bar.jpg" -> giftcodesbanner/代號：無頭-bar.jpg | D77: =IF(A77="","", "https://www.ssbuy.tw/detail_giftcode/dist/giftcodes/" & IF(ISNUMBER(LEFT(A77,1)*1), "game-", "") & A77 & ".html") -> https://www.ssbuy.tw/detail_giftcode/dist/giftcodes/代號：無頭.html | E77: 《代號：無頭》是由HZ Game 代理發行的角色扮演遊戲。 這款遊戲將您帶入前所未有的奇幻冒險，成為失去頭顱的魔王，與S級女性角色後援團攜手啟程。 遊戲巧妙融合多元副本挑戰、全球玩家對戰和自動戰鬥系統，帶給您極致的遊戲樂趣。 | F77: 進入主畫面，點選個人頭像 | G77: 進入設定（齒輪） | H77: 輸入禮包碼 → 確認兌換 | K77: HIMARCH | L77: 200普通箱子與20k藍鑽 | M77: WOMAN | N77: 200普通箱子與20k藍鑽 | O77: LAST3 | P77: 33333藍鑽與3333紅鑽 | Q77: IOSNEW | R77: 20000藍鑽與1000紅鑽 | S77: FB1000 | T77: 300普通箱子與2000藍鑽 | U77: VIP111 | V77: 隨機虛寶或鑽石獎勵 | W77: VIP777 | X77: 隨機虛寶或鑽石獎勵 | Y77: VIP999 | Z77: 隨機虛寶或鑽石獎勵
A78: 牛頭人GO | B78: ="giftcodesbanner/" & A78 & "-bar.jpg" -> giftcodesbanner/牛頭人GO-bar.jpg | D78: =IF(A78="","", "https://www.ssbuy.tw/detail_giftcode/dist/giftcodes/" & IF(ISNUMBER(LEFT(A78,1)*1), "game-", "") & A78 & ".html") -> https://www.ssbuy.tw/detail_giftcode/dist/giftcodes/牛頭人GO.html | E78: 《牛頭人GO》是一款由娜瓦遊戲股份有限公司推出的mini英雄進化消除塔防手遊。 玩家將扮演流放者，率領以牛頭人为首的英雄們，與各界域的魔獸戰鬥。 遊戲特色是「消除」和「塔防」的結合，玩家透過消除相同英雄來進化角色，提升實力，抵禦敵人的進攻。 | F78: 進入主畫面，點選個人頭像 | G78: 進入設定（齒輪） | H78: 輸入禮包碼 → 確認兌換 | K78: vip666 | L78: 隨機虛寶或鑽石獎勵 | M78: wow999 | N78: 隨機虛寶或鑽石獎勵 | O78: Taurentgo | P78: 隨機虛寶或鑽石獎勵 | Q78: ntrgo666 | R78: 隨機虛寶或鑽石獎勵 | S78: ntrgo777 | T78: 隨機虛寶或鑽石獎勵 | U78: ntrgo888 | V78: 隨機虛寶或鑽石獎勵 | W78: RYAN666 | X78: 隨機虛寶或鑽石獎勵 | Y78: Sora2025 | Z78: 隨機虛寶或鑽石獎勵
A79: 派對吧三國 | B79: ="giftcodesbanner/" & A79 & "-bar.jpg" -> giftcodesbanner/派對吧三國-bar.jpg | D79: =IF(A79="","", "https://www.ssbuy.tw/detail_giftcode/dist/giftcodes/" & IF(ISNUMBER(LEFT(A79,1)*1), "game-", "") & A79 & ".html") -> https://www.ssbuy.tw/detail_giftcode/dist/giftcodes/派對吧三國.html | E79: 《派對吧三國》——上線送1000抽穿越時空的派對，三國化作派對不夜城，帶你進入一個充滿霓虹燈與奇跡的三國世界！ 告別傳統，迎接派對風格的三國世界！ 在霓虹燈下的戰鬥中，幻想的加持讓每位名將展現出前所未有的魅力。 每一次戰鬥都是一場視覺和節奏的盛宴，讓你體驗一個與眾不同的三國戰場。 | F79: 進入主畫面，點選個人頭像 | G79: 進入設定（齒輪） | H79: 輸入禮包碼 → 確認兌換 | K79: WK118 | L79: 隨機虛寶或鑽石獎勵 | M79: MONDAY1 | N79: 隨機虛寶或鑽石獎勵 | O79: PDBSG666 | P79: 隨機虛寶或鑽石獎勵 | Q79: VIP8888 | R79: 隨機虛寶或鑽石獎勵 | S79: VIP7777 | T79: 隨機虛寶或鑽石獎勵 | U79: VIP6666 | V79: 隨機虛寶或鑽石獎勵 | W79: Svip888 | X79: 隨機虛寶或鑽石獎勵 | Y79: Svip777 | Z79: 隨機虛寶或鑽石獎勵 | AA79: Svip666 | AB79: 隨機虛寶或鑽石獎勵 | AC79: Study111 | AD79: 隨機虛寶或鑽石獎勵
A80: 酒酒大俠 | B80: ="giftcodesbanner/" & A80 & "-bar.jpg" -> giftcodesbanner/酒酒大俠-bar.jpg | D80: =IF(A80="","", "https://www.ssbuy.tw/detail_giftcode/dist/giftcodes/" & IF(ISNUMBER(LEFT(A80,1)*1), "game-", "") & A80 & ".html") -> https://www.ssbuy.tw/detail_giftcode/dist/giftcodes/酒酒大俠.html | E80: 《酒酒大俠》是一款由HK FOREVER99 TECHNOLOGY CO., LIMITED開發的角色扮演遊戲。 遊戲以武俠世界為背景，玩家可以體驗如小說般的沉浸劇情，重現武林恩怨情仇，挑戰各門派秘境，並揭開隱藏的江湖秘密，在遊戲中成為主角，引領主線劇情發展，參與武俠世界的各種冒險。 | F80: 進入主畫面，點選個人頭像 | G80: 進入設定（齒輪） | H80: 輸入禮包碼 → 確認兌換 | K80: FTRQG | L80: 隨機虛寶或鑽石獎勵 | M80: ONLINE | N80: 隨機虛寶或鑽石獎勵 | O80: FUXGK | P80: 隨機虛寶或鑽石獎勵 | Q80: ZIYOJ | R80: 隨機虛寶或鑽石獎勵 | S80: TISPH | T80: 隨機虛寶或鑽石獎勵 | U80: TSBGF | V80: 隨機虛寶或鑽石獎勵 | W80: YY0108 | X80: 隨機虛寶或鑽石獎勵
A81: 鼠衛家園 | B81: ="giftcodesbanner/" & A81 & "-bar.jpg" -> giftcodesbanner/鼠衛家園-bar.jpg | D81: =IF(A81="","", "https://www.ssbuy.tw/detail_giftcode/dist/giftcodes/" & IF(ISNUMBER(LEFT(A81,1)*1), "game-", "") & A81 & ".html") -> https://www.ssbuy.tw/detail_giftcode/dist/giftcodes/鼠衛家園.html | E81: 《鼠衛家園》是一款結合了塔防和Roguelike 元素的行動遊戲，玩家將化身為鼠鼠英雄，守護家園並抵抗來自各方的怪物攻擊。 遊戲玩法強調策略佈置和英雄搭配，玩家需要根據怪物的進攻路線，靈活安排防禦塔和英雄位置，增加防守效率。 | F81: 進入主畫面，點選個人頭像 | G81: 進入設定（齒輪） | H81: 輸入禮包碼 → 確認兌換 | K81: UISPWJLL | L81: 隨機虛寶或鑽石獎勵 | M81: SHUWEIDW2025 | N81: 隨機虛寶或鑽石獎勵 | O81: WEOQKAMN | P81: 隨機虛寶或鑽石獎勵 | Q81: OIWPSLQA | R81: 隨機虛寶或鑽石獎勵 | S81: YUSQLAPI | T81: 隨機虛寶或鑽石獎勵
A82: 未頌者之歌：異世界冒險奇譚 | B82: ="giftcodesbanner/" & A82 & "-bar.jpg" -> giftcodesbanner/未頌者之歌：異世界冒險奇譚-bar.jpg | D82: =IF(A82="","", "https://www.ssbuy.tw/detail_giftcode/dist/giftcodes/" & IF(ISNUMBER(LEFT(A82,1)*1), "game-", "") & A82 & ".html") -> https://www.ssbuy.tw/detail_giftcode/dist/giftcodes/未頌者之歌：異世界冒險奇譚.html | E82: 在陷入不斷毀滅與重生輪迴的九界之中，你將化身女武神瓦爾基里，集結未被歌頌的英雄們，於命運洪流中穿越迷霧，追尋破碎神話背後的真相，譜寫抗爭與希望的頌歌，踏上拯救九界眾生的史詩旅程。 | F82: 進入主畫面，點選個人頭像 | G82: 進入設定（齒輪） | H82: 輸入禮包碼 → 確認兌換 | K82: chitui | L82: 隨機虛寶或鑽石獎勵 | M82: OPENTODAY | N82: 隨機虛寶或鑽石獎勵 | O82: happyjanuary2025 | P82: 隨機虛寶或鑽石獎勵 | Q82: happydecember | R82: 隨機虛寶或鑽石獎勵 | S82: happyplay | T82: 隨機虛寶或鑽石獎勵 | U82: discordclub | V82: 隨機虛寶或鑽石獎勵 | X82: 隨機虛寶或鑽石獎勵
A83: 熱練戰士 | B83: ="giftcodesbanner/" & A83 & "-bar.jpg" -> giftcodesbanner/熱練戰士-bar.jpg | D83: =IF(A83="","", "https://www.ssbuy.tw/detail_giftcode/dist/giftcodes/" & IF(ISNUMBER(LEFT(A83,1)*1), "game-", "") & A83 & ".html") -> https://www.ssbuy.tw/detail_giftcode/dist/giftcodes/熱練戰士.html | E83: 《熱練戰士》是任何人都可以輕鬆享受的2D 動作角色扮演類遊戲，和各種吸引人的英雄在清醒夢大冒險的世界背景下進行愉快的冒險。 以四個遊戲角色來組建起屬於自己的隊伍，擊退一波又一波的怪物後完成遊戲劇情。 除主線故事外，還可以在噩夢入侵、PVP 競技場、地下副本、神的遺物等模式中感受樂趣。 | F83: 進入主畫面，點選個人頭像 | G83: 進入設定（齒輪） | H83: 輸入禮包碼 → 確認兌換 | K83: WELCOMEHCLW | L83: 鑽石10,000個、奇加工坊使用券100張 | M83: PLUSHCLW | N83: 靈魂珠400個、鑽石1,500個、骰子200個 | O83: PREREGISTER | P83: 鑽石5,000個、裝備召喚券30張 | Q83: FRIDAYHCLW | R83: 鑽石10,000個、好運Buff藥丸 | S83: COMMUNITY | T83: 鑽石6,500個、裝備召喚券30張 | U83: HAPPY2025 | V83: 鑽石50,000個
A84: 聯盟戰棋 | B84: ="giftcodesbanner/" & A84 & "-bar.jpg" -> giftcodesbanner/聯盟戰棋-bar.jpg | D84: =IF(A84="","", "https://www.ssbuy.tw/detail_giftcode/dist/giftcodes/" & IF(ISNUMBER(LEFT(A84,1)*1), "game-", "") & A84 & ".html") -> https://www.ssbuy.tw/detail_giftcode/dist/giftcodes/聯盟戰棋.html | E84: 《聯盟戰棋》（或稱《雲頂之弈》）是由Riot Games 開發的自走棋類電子遊戲，建立在《英雄聯盟》的世界觀之上。 玩家與七名對手競爭，在回合制的戰鬥中組建隊伍，最終爭奪勝利。 遊戲玩法與《刀塔自走棋》類似，玩家從輪流出現的《英雄聯盟》角色中招募棋子，佈置棋位，並在戰鬥中與對手戰鬥。 | F84: 進入主畫面，點選個人頭像 | G84: 進入設定（齒輪） | H84: 輸入禮包碼 → 確認兌換 | L84: 隨機虛寶或鑽石獎勵 | N84: 隨機虛寶或鑽石獎勵 | P84: 隨機虛寶或鑽石獎勵 | R84: 隨機虛寶或鑽石獎勵 | T84: 隨機虛寶或鑽石獎勵 | V84: 隨機虛寶或鑽石獎勵 | X84: 隨機虛寶或鑽石獎勵
A85: 劍客物語 | B85: ="giftcodesbanner/" & A85 & "-bar.jpg" -> giftcodesbanner/劍客物語-bar.jpg | D85: =IF(A85="","", "https://www.ssbuy.tw/detail_giftcode/dist/giftcodes/" & IF(ISNUMBER(LEFT(A85,1)*1), "game-", "") & A85 & ".html") -> https://www.ssbuy.tw/detail_giftcode/dist/giftcodes/劍客物語.html | E85: 《劍客物語》是一款由SuperPlanet代理的角色扮演遊戲，屬於動作RPG類型，以「該隱」這個平凡學生穿越到異世界後，成為大劍客，與神話英雄組隊，一起冒險和戰鬥，並揭開隱藏的真相為故事核心。 遊戲特色包括華麗技能、高速連擊、二刀流戰鬥系統、裝備強化、角色成長系統、公會合作以及獨特的故事和冒險模式。 | F85: 進入主畫面，點選個人頭像 | G85: 進入設定（齒輪） | H85: 輸入禮包碼 → 確認兌換 | K85: SWORDMASTER | L85: 4星角色召喚卷x1、5星防具箱子x1、S級突襲箱子x3、四葉草x5 | M85: HALLOWEEN | N85: 300紅寶石 | O85: THX12000 | P85: 1200行動力 | Q85: COOLTIPS | R85: 600紅寶石 | S85: GIFT1111DAY | T85: 1111行動力 | U85: TOWERA | V85: 300紅寶石 | W85: EHTUPDATE | X85: 700紅寶石 | Y85: BFGIFT | Z85: 600紅寶石 | AA85: SCROLL3 | AB85: 1000行動力
A86: 人在塔在 | B86: ="giftcodesbanner/" & A86 & "-bar.jpg" -> giftcodesbanner/人在塔在-bar.jpg | D86: =IF(A86="","", "https://www.ssbuy.tw/detail_giftcode/dist/giftcodes/" & IF(ISNUMBER(LEFT(A86,1)*1), "game-", "") & A86 & ".html") -> https://www.ssbuy.tw/detail_giftcode/dist/giftcodes/人在塔在.html | E86: 對抗無情的敵人：野蠻的獸人、高聳的巨魔、邪惡的死靈法師、惡魔大軍以及各種史詩級首領。每個敵人都帶來新的挑戰和獨特的戰鬥能力，為這個類型增添了新維度！召喚強大的援軍，指揮你的弓箭手，釋放毀滅性的技能，並通過遊戲內選項升級你的弓箭手和塔樓，以保護王國免受黑暗的侵害！ | F86: 進入主畫面，點選個人頭像 | G86: 進入設定（齒輪） | H86: 輸入禮包碼 → 確認兌換 | K86: AS3DDISCORD | L86: 隨機虛寶或鑽石獎勵 | M86: AS3DDC | N86: 隨機虛寶或鑽石獎勵
A87: 龍語霜城 | B87: ="giftcodesbanner/" & A87 & "-bar.jpg" -> giftcodesbanner/龍語霜城-bar.jpg | D87: =IF(A87="","", "https://www.ssbuy.tw/detail_giftcode/dist/giftcodes/" & IF(ISNUMBER(LEFT(A87,1)*1), "game-", "") & A87 & ".html") -> https://www.ssbuy.tw/detail_giftcode/dist/giftcodes/龍語霜城.html | E87: 《龍語霜城-元素魔域》是由純白之境發行的西方魔幻題材三消策略手機遊戲，於2023年12月7日正式上線。 遊戲將魔幻大世界與三消策略玩法融合，玩家可以在冰天雪地中冒險，喚醒巨龍，拯救被冰封的家園。 | F87: 進入主畫面，點選個人頭像 | G87: 進入設定（齒輪） | H87: 輸入禮包碼 → 確認兌換 | K87: D5C9P2 | L87: 隨機虛寶或鑽石獎勵 | M87: JoyfulDay | N87: 隨機虛寶或鑽石獎勵 | O87: J4K6R3 | P87: 隨機虛寶或鑽石獎勵 | Q87: G8H2E9 | R87: 隨機虛寶或鑽石獎勵 | S87: HAPPY777 | T87: 隨機虛寶或鑽石獎勵 | U87: PNCGO | V87: 隨機虛寶或鑽石獎勵 | W87: PNC333 | X87: 隨機虛寶或鑽石獎勵 | Y87: PNC888 | Z87: 隨機虛寶或鑽石獎勵 | AA87: PNC168 | AB87: 隨機虛寶或鑽石獎勵 | AC87: PC777 | AD87: 隨機虛寶或鑽石獎勵 | AE87: R2M6N9 | AF87: 隨機虛寶或鑽石獎勵 | AG87: PNC123 | AH87: 隨機虛寶或鑽石獎勵 | AI87: EASTERD8 | AJ87: 隨機虛寶或鑽石獎勵
A88: 洛伊的移動要塞 | B88: ="giftcodesbanner/" & A88 & "-bar.jpg" -> giftcodesbanner/洛伊的移動要塞-bar.jpg | D88: =IF(A88="","", "https://www.ssbuy.tw/detail_giftcode/dist/giftcodes/" & IF(ISNUMBER(LEFT(A88,1)*1), "game-", "") & A88 & ".html") -> https://www.ssbuy.tw/detail_giftcode/dist/giftcodes/洛伊的移動要塞.html | E88: 《洛伊的移動要塞》是韓國開發商Cookapps推出的放置型城堡養成遊戲。 在一個魔王肆虐的世界裡，英雄們利用世界樹的力量對抗邪惡。 玩家將扮演這些英雄，利用世界樹的種子來建造並培養自己的移動城堡。 | F88: 進入主畫面，點選個人頭像 | G88: 進入設定（齒輪） | H88: 輸入禮包碼 → 確認兌換 | K88: THXSSO | L88: 技師20抽、大砲20抽 | M88: 1003DAY | N88: 3000寶石、蛋糕3個 | O88: THANKYOUFO | P88: 1000寶石 | Q88: FSBESTONE | R88: 技師30抽、大砲30抽、英雄10抽 | S88: FSGRANDOPEN | T88: 1000寶石 | U88: FS100KDOWN | V88: 英雄10抽 | W88: 18OMEDETOU | X88: 技師20抽、大砲20抽、英雄20抽、蛋糕20個 | Y88: FSTW2024 | Z88: 技師50抽、大砲50抽、1000寶石
A89: 喵喵王國 | B89: ="giftcodesbanner/" & A89 & "-bar.jpg" -> giftcodesbanner/喵喵王國-bar.jpg | D89: =IF(A89="","", "https://www.ssbuy.tw/detail_giftcode/dist/giftcodes/" & IF(ISNUMBER(LEFT(A89,1)*1), "game-", "") & A89 & ".html") -> https://www.ssbuy.tw/detail_giftcode/dist/giftcodes/喵喵王國.html | E89: 《喵喵王國：貓咪放置rpg》的大體玩法結構為，家園養成+放置對戰，家園養成方面，就是透過放置設施與可愛的貓咪，產出各種道具來培養貓咪（當然也可以只是為了好看養眼），其中你還可以培養貓咪們的好感度，好感度的提升對戰鬥有所加成。 | F89: 進入主畫面，點選個人頭像 | G89: 進入設定（齒輪） | H89: 輸入禮包碼 → 確認兌換 | K89: VYYPMPRM | L89: 隨機虛寶或鑽石獎勵
A90: 東京謎影者 | B90: ="giftcodesbanner/" & A90 & "-bar.jpg" -> giftcodesbanner/東京謎影者-bar.jpg | D90: =IF(A90="","", "https://www.ssbuy.tw/detail_giftcode/dist/giftcodes/" & IF(ISNUMBER(LEFT(A90,1)*1), "game-", "") & A90 & ".html") -> https://www.ssbuy.tw/detail_giftcode/dist/giftcodes/東京謎影者.html | E90: 遊戲故事以Live2D 與漫畫交織展開，講述女主角因被怪異襲擊，遇見將自身出賣給惡魔的「噬魔人」，並被帶至「黑蕊學園」。 在這裡被宣告壽命只剩一年的女主角，為了解開詛咒，將與噬魔人一同調查潛藏於東京市區的怪異事件。 | F90: 進入主畫面，點選個人頭像 | G90: 進入設定（齒輪） | H90: 輸入禮包碼 → 確認兌換 | L90: 隨機虛寶或鑽石獎勵 | N90: 隨機虛寶或鑽石獎勵 | P90: 隨機虛寶或鑽石獎勵 | R90: 隨機虛寶或鑽石獎勵 | T90: 隨機虛寶或鑽石獎勵 | V90: 隨機虛寶或鑽石獎勵 | X90: 隨機虛寶或鑽石獎勵
A91: 戰極死遊 | B91: ="giftcodesbanner/" & A91 & "-bar.jpg" -> giftcodesbanner/戰極死遊-bar.jpg | D91: =IF(A91="","", "https://www.ssbuy.tw/detail_giftcode/dist/giftcodes/" & IF(ISNUMBER(LEFT(A91,1)*1), "game-", "") & A91 & ".html") -> https://www.ssbuy.tw/detail_giftcode/dist/giftcodes/戰極死遊.html | E91: 時間來到20XX年。主宰著新東京國、臉戴面具的謎樣男子「ZERO」宣布，在全國的城市裡「所有事情將以遊戲來做定奪」。自此他便透過「戰極遊戲（Extreme Games）」，通稱「XG」 來統治新東京。 | F91: 進入主畫面，點選個人頭像 | G91: 進入設定（齒輪） | H91: 輸入禮包碼 → 確認兌換 | K91: g0vveW93yH | L91: 神祕粒子結晶 x 120 | M91: Ari7ved0K9 | N91: 神祕粒子結晶 x 120 | O91: tTa2IlRgGN | P91: 神祕粒子結晶 x 120
A92: 進擊的蝸牛 | B92: ="giftcodesbanner/" & A92 & "-bar.jpg" -> giftcodesbanner/進擊的蝸牛-bar.jpg | D92: =IF(A92="","", "https://www.ssbuy.tw/detail_giftcode/dist/giftcodes/" & IF(ISNUMBER(LEFT(A92,1)*1), "game-", "") & A92 & ".html") -> https://www.ssbuy.tw/detail_giftcode/dist/giftcodes/進擊的蝸牛.html | E92: 《進擊的蝸牛》是一款放置類手遊，玩家可以輕鬆進行強化和升級，即使在工作或閒暇時也能享受遊戲樂趣。 遊戲中，玩家可以和夥伴一起探索、爬塔，進行自由遠征。 | F92: 進入主畫面，點選個人頭像 | G92: 進入設定（齒輪） | H92: 輸入禮包碼 → 確認兌換 | K92: SNAIL2025 | L92: 金幣100000，鑽石500 | M92: AOS7777 | N92: 隨機虛寶或鑽石獎勵 | O92: AOS8888 | P92: 隨機虛寶或鑽石獎勵 | Q92: AOS9999 | R92: 隨機虛寶或鑽石獎勵 | S92: AOS2025 | T92: 隨機虛寶或鑽石獎勵 | U92: DBSNAIL | V92: 隨機虛寶或鑽石獎勵 | W92: LICESNAIL | X92: 隨機虛寶或鑽石獎勵 | Y92: VIP666 | Z92: 隨機虛寶或鑽石獎勵 | AA92: VIP777 | AB92: 隨機虛寶或鑽石獎勵 | AC92: VIP888 | AD92: 隨機虛寶或鑽石獎勵 | AE92: SCSNAIL | AF92: 隨機虛寶或鑽石獎勵 | AG92: SUPER555 | AH92: 隨機虛寶或鑽石獎勵 | AI92: SUPER111 | AJ92: 隨機虛寶或鑽石獎勵 | AK92: SVIP666 | AL92: 隨機虛寶或鑽石獎勵 | AM92: SVIP777 | AN92: 隨機虛寶或鑽石獎勵 | AO92: SVIP888 | AP92: 隨機虛寶或鑽石獎勵
A93: 純白大作戰 | B93: ="giftcodesbanner/" & A93 & "-bar.jpg" -> giftcodesbanner/純白大作戰-bar.jpg | D93: =IF(A93="","", "https://www.ssbuy.tw/detail_giftcode/dist/giftcodes/" & IF(ISNUMBER(LEFT(A93,1)*1), "game-", "") & A93 & ".html") -> https://www.ssbuy.tw/detail_giftcode/dist/giftcodes/純白大作戰.html | E93: 本作強調二次元動漫畫風的人物立繪和流暢的動畫表現，玩家將能遇到眾多風格迥異的美少女角色，每一位都擁有獨特而絢麗的技能。 同時將輕鬆的放置玩法與多變的策略相結合。 玩家可以在最小投入下享受遊戲進程，透過精心策劃的策略來克服挑戰。 《純白大作戰》現已開啟預先註冊。 | F93: 進入主畫面，點選個人頭像 | G93: 進入設定（齒輪） | H93: 輸入禮包碼 → 確認兌換 | K93: VIP666 | L93: 寵物票券*20、墨菲斯托*1、鑽石*500、技能票券*20 | M93: VIP777 | N93: 貓貓拉桿*50、鑽石*50 | O93: VIP888 | P93: 鑽石*50、百煉錘*20 | Q93: FOLLOWFB | R93: 技能票券*20、鑽石*100、音魂票券*20、寵物票券*20 | S93: Queen | T93: 金幣*500、技能票券*20 | U93: Prajna | V93: 音魂票券*20、鑽石*50 | X93: 隨機虛寶或鑽石獎勵
A94: 黑星勇者 | B94: ="giftcodesbanner/" & A94 & "-bar.jpg" -> giftcodesbanner/黑星勇者-bar.jpg | D94: =IF(A94="","", "https://www.ssbuy.tw/detail_giftcode/dist/giftcodes/" & IF(ISNUMBER(LEFT(A94,1)*1), "game-", "") & A94 & ".html") -> https://www.ssbuy.tw/detail_giftcode/dist/giftcodes/黑星勇者.html | E94: 黑星勇者是一款象素風格的超自由ＲＰＧ手遊，他與手遊伊洛納製作團隊是同一個，也因此在許多地方是相似或熟悉的。 雖然遊戲是傳統的勇者地下城ＲＰＧ模式，但是他也有許多家園生產體系。 不過最為經典重要的是它是一款養成非常自由的手遊。 | F94: 進入主畫面，點選個人頭像 | G94: 進入設定（齒輪） | H94: 輸入禮包碼 → 確認兌換 | K94: BLACKSTAR | L94: 3枚薔薇之心徽章，10本專精强化書，20瓶致命傷治療藥水 | M94: NEWSERVER | N94: 3枚薔薇之心徽章，10本專精强化書，20瓶致命傷治療藥水
A95: 龍之谷：經典再現 | B95: ="giftcodesbanner/" & A95 & "-bar.jpg" -> giftcodesbanner/龍之谷：經典再現-bar.jpg | D95: =IF(A95="","", "https://www.ssbuy.tw/detail_giftcode/dist/giftcodes/" & IF(ISNUMBER(LEFT(A95,1)*1), "game-", "") & A95 & ".html") -> https://www.ssbuy.tw/detail_giftcode/dist/giftcodes/龍之谷：經典再現.html | E95: 《龍之谷：經典再現》是韓國原廠正版授權，復刻經典的龍之谷遊戲。 這款遊戲以其精緻的畫風、豐富的職業系統、獨特的遊戲機制以及多樣的內容，讓玩家重溫經典的遊戲體驗。 遊戲中，玩家可以扮演不同的職業，例如牧師，體驗不同角色的獨特魅力與戰鬥風格。 | F95: 進入主畫面，點選個人頭像 | G95: 進入設定（齒輪） | H95: 輸入禮包碼 → 確認兌換 | K95: dnm6661 | L95: 隨機虛寶或鑽石獎勵 | M95: dnm999A | N95: 隨機虛寶或鑽石獎勵 | O95: dnm20258 | P95: 隨機虛寶或鑽石獎勵 | Q95: DNMZZXIAM | R95: 隨機虛寶或鑽石獎勵 | S95: DNMHAPPY61MM | T95: 隨機虛寶或鑽石獎勵 | V95: 隨機虛寶或鑽石獎勵 | X95: 隨機虛寶或鑽石獎勵
A96: 楓之谷Artale | B96: ="giftcodesbanner/" & A96 & "-bar.jpg" -> giftcodesbanner/楓之谷Artale-bar.jpg | D96: =IF(A96="","", "https://www.ssbuy.tw/detail_giftcode/dist/giftcodes/" & IF(ISNUMBER(LEFT(A96,1)*1), "game-", "") & A96 & ".html") -> https://www.ssbuy.tw/detail_giftcode/dist/giftcodes/楓之谷Artale.html | E96: Artale 繁體中文版的懷舊版本其遊戲系統MapleStory Worlds 是Nexon 在2022 年年底推出的一款玩家跟開發者能夠自由運用數千萬個楓之谷物件製作遊戲進行遊戲的一個平台，因此吸引了創作者們開始建立最初楓之谷的設定，打造了這款名為《Artale懷舊楓之谷》的版本 | F96: 進入主畫面，點選個人頭像 | G96: 進入設定（齒輪） | H96: 輸入禮包碼 → 確認兌換 | L96: 隨機虛寶或鑽石獎勵 | N96: 隨機虛寶或鑽石獎勵 | P96: 隨機虛寶或鑽石獎勵 | R96: 隨機虛寶或鑽石獎勵 | T96: 隨機虛寶或鑽石獎勵 | V96: 隨機虛寶或鑽石獎勵 | X96: 隨機虛寶或鑽石獎勵
A97: 出發吧麥芬 | B97: ="giftcodesbanner/" & A97 & "-bar.jpg" -> giftcodesbanner/出發吧麥芬-bar.jpg | D97: =IF(A97="","", "https://www.ssbuy.tw/detail_giftcode/dist/giftcodes/" & IF(ISNUMBER(LEFT(A97,1)*1), "game-", "") & A97 & ".html") -> https://www.ssbuy.tw/detail_giftcode/dist/giftcodes/出發吧麥芬.html | E97: 《出發吧麥芬》讓你整天可可愛愛掛機就能成長領被動收入。 只需在空閒時進入遊戲，查看行囊裡多了什麼新裝備，摸頭並餵食一下麥樂獸，就能使其變強大。 當然在駕車兜風途中的Q萌百景、奇珍異獸、帥氣BOSS，也是讓眾多冒險家流連忘返的！ | F97: 進入主畫面，點選個人頭像 | G97: 進入設定（齒輪） | H97: 輸入禮包碼 → 確認兌換 | K97: xvknsqea | L97: 盧恩文字x10, 原材料x200, 金幣x10K
A98: RO仙境傳說：守護永恆的愛 Classic | B98: ="giftcodesbanner/" & A98 & "-bar.jpg" -> giftcodesbanner/RO仙境傳說：守護永恆的愛 Classic-bar.jpg | D98: =IF(A98="","", "https://www.ssbuy.tw/detail_giftcode/dist/giftcodes/" & IF(ISNUMBER(LEFT(A98,1)*1), "game-", "") & A98 & ".html") -> https://www.ssbuy.tw/detail_giftcode/dist/giftcodes/RO仙境傳說：守護永恆的愛 Classic.html | E98: 《RO仙境傳說：守護永恆的愛Classic》是RO守愛的返璞歸真版本。 在這裡沒有商城、沒有抽卡要素、沒有各種儲值貨幣，只有擊敗怪物就可掉落的單一貨幣「Zeny」。 在這裡只有大家熟悉的RO六大基礎職業：劍士、魔法師、盜賊、弓箭手、服事、商人。 | F98: 進入主畫面，點選個人頭像 | G98: 進入設定（齒輪） | H98: 輸入禮包碼 → 確認兌換 | K98: ROMC5DAYS | L98: 隨機虛寶或鑽石獎勵 | M98: 4LEFTROMC | N98: 隨機虛寶或鑽石獎勵 | O98: 3GOROMC | P98: 隨機虛寶或鑽石獎勵 | Q98: ROMC2HYPE | R98: 隨機虛寶或鑽石獎勵 | S98: ROMC1MORE | T98: 隨機虛寶或鑽石獎勵 | U98: ZENYGO | V98: 隨機虛寶或鑽石獎勵 | W98: 15XH6EKE | X98: 隨機虛寶或鑽石獎勵 | Y98: BP04ROMC | Z98: 隨機虛寶或鑽石獎勵 | AA98: 5TSQC2XK | AB98: 隨機虛寶或鑽石獎勵 | AC98: 6X5S82UY | AD98: 隨機虛寶或鑽石獎勵 | AE98: RO6666 | AF98: 隨機虛寶或鑽石獎勵 | AG98: ROMCWEISSG | AH98: 隨機虛寶或鑽石獎勵 | AI98: LILY4UGIFT | AJ98: 隨機虛寶或鑽石獎勵 | AK98: ROMCOBT | AL98: 隨機虛寶或鑽石獎勵 | AM98: ROMCPFY | AN98: 隨機虛寶或鑽石獎勵 | AO98: ROMCBALL | AP98: 隨機虛寶或鑽石獎勵 | AQ98: ROMCWEI | AR98: 隨機虛寶或鑽石獎勵 | AS98: ROMCHSU | AT98: 隨機虛寶或鑽石獎勵 | AU98: ROMCBAIXING | AV98: 隨機虛寶或鑽石獎勵
A99: 魔力寶貝：復興 | B99: ="giftcodesbanner/" & A99 & "-bar.jpg" -> giftcodesbanner/魔力寶貝：復興-bar.jpg | D99: =IF(A99="","", "https://www.ssbuy.tw/detail_giftcode/dist/giftcodes/" & IF(ISNUMBER(LEFT(A99,1)*1), "game-", "") & A99 & ".html") -> https://www.ssbuy.tw/detail_giftcode/dist/giftcodes/魔力寶貝：復興.html | E99: 《魔力寶貝：復興》是一款由 SQUARE ENIX 正版授權GNN 新聞網 的手機遊戲，它採用了3D引擎提升畫面，同時保留了《魔力寶貝》系列的45度角戰鬥畫面。 遊戲保留了《魔力寶貝》的經典元素，讓玩家體驗橫跨24年IP的魅力，並提供多樣化的寵物培養系統，讓玩家可以培養心儀的寵物。 | F99: 進入主畫面，點選個人頭像 | G99: 進入設定（齒輪） | H99: 輸入禮包碼 → 確認兌換 | K99: Cyndi520 | L99: 火焰鼠彩券*1，銀幣*10萬，綁鑽*100 | M99: VIP666 | N99: 初級熟練度卷軸*10 | O99: VIP777 | P99: 大地鼠彩券*5 | Q99: VIP888 | R99: 普通圖鑑卡*5 | S99: VIP999 | T99: 初級魔石*5 | U99: Cyndi2025 | V99: 大地鼠彩券*1，金色圖鑑卡，寵物洗煉藥水*20，綁鑽*100 | W99: 83br75mt | X99: 銀幣*20W，寵物洗煉藥水（綁）*35 | Y99: LAODONG0501 | Z99: 火焰鼠彩券（绑）*1，馴獸寶典（绑）*5，銀色圖鑑卡*1（绑）
A100: 東京喰種Awakening | B100: ="giftcodesbanner/" & A100 & "-bar.jpg" -> giftcodesbanner/東京喰種Awakening-bar.jpg | D100: =IF(A100="","", "https://www.ssbuy.tw/detail_giftcode/dist/giftcodes/" & IF(ISNUMBER(LEFT(A100,1)*1), "game-", "") & A100 & ".html") -> https://www.ssbuy.tw/detail_giftcode/dist/giftcodes/東京喰種Awakening.html | E100: 《東京喰種：Awakening》手遊官網 是一名喜愛讀書、就讀于上井大學的學生。 因移植了“喰種” 利世的部分器官，身體成為了“喰種” ，被迫在“喰種” 的世界中生存。 雖身處絕望的深淵，但在與性格和境遇迥異的“喰種” 相處過程中，他的意識逐漸發生了改變，想要斬斷這個世界悲哀的連鎖。 | F100: 進入主畫面，點選個人頭像 | G100: 進入設定（齒輪） | H100: 輸入禮包碼 → 確認兌換 | K100: DGCDM | L100: 進階結晶Ⅲ×8、赤紅結晶×10、招募券×10、界限晶幣×5 | M100: YXZGO | N100: 強化石×20、招募券×4、改良電池×1、掃蕩券×10 | O100: RYSXL | P100: 強化石×20、界限晶幣×10、黃金兔寶寶×1 | Q100: QSDLS | R100: 鑽石×100、進階結晶Ⅲ×5、進階結晶Ⅱ×10 | S100: JMYAD | T100: 協同銘牌·黃×40、協同銘牌·藍×40、協同銘牌·紅×40 | U100: SQYY30 | V100: 鑽石×188、黃金兔寶寶×1、經驗書·大×5 | W100: SQYY40 | X100: 鑽石×288、赤紅結晶×10、水晶兔寶寶×1 | Y100: SQYY50 | Z100: 鑽石×666、界限晶幣×5、改良電池×1 | AA100: WDDXT | AB100: 強化石×20、經驗書·大×10、掃蕩券×10 | AC100: SQDS2 | AD100: 招募券×3、進階結晶Ⅱ×8、協同銘牌·紅×30 | AE100: SQDS3 | AF100: 招募券×2、進階結晶Ⅱ×8、協同銘牌·藍×30 | AG100: SQDS5 | AH100: 招募券×1、進階結晶Ⅱ×8、協同銘牌·黃×30 | AI100: SQDS7 | AJ100: 鑽石×100、赤紅結晶×5、進階結晶Ⅰ×10
...
